Workbook

Sheet Contenido
B1: SUPERINTENDENCIA DE BANCOS DEL ECUADOR INTENDENCIA NACIONAL DE RIESGOS Y ESTUDIOS DIRECCIÓN DE ESTUDIOS Y GESTIÓN DE LA INFORMACIÓN SUBDIRECCIÓN DE ESTADÍSTICAS Y ESTUDIOS
B3: ESTADÍSTICAS DE RETIROS DE DINERO EN EFECTIVO SOBRE CUENTAS DE AHORRO EN CANALES PROPIOS DE LA ENTIDAD
B4: Enero a Diciembre 2020
C6: TABLA DE CONTENIDO
C8: =+'SECCIÓN I'!B8 -> SECCIÓN I: RETIROS DE DINERO EN GENERAL
C9: 1.1 Evolución de Transacciones y Montos de Retiros de Dinero
C11: =+'SECCIÓN II'!B8 -> SECCIÓN II: RETIROS DE DINERO POR ENTIDAD FINANCIERA
C12: 2.1 Evolución de Transacciones de Retiros de Dinero por Entidad Financiera
C13: 2.2 Evolución del Monto de Retiros de Dinero por Entidad Financiera
C14: 2.3 Evolución del Monto Promedio de Retiros de Dinero por Entidad Financiera
C15: 2.4 Resumen Anual de Transacciones, Monto de Retiros y Monto Promedio de Retiros de Dinero por Entidad Financiera
C17: =+'SECCIÓN III'!B8 -> SECCIÓN III: RETIROS DE DINERO POR CANALES
C18: 3.1 Evolución de Transacciones de Retiros de Dinero por Canales
C19: 3.2 Evolución del Monto de Retiros de Dinero por Canales
C20: 3.3 Evolución del Monto Promedio de Retiros de Dinero por Canales
C21: 3.4 Resumen Anual de Transacciones, Monto de Retiros y Monto Promedio de Retiros de Dinero por Canales
C23: =+'SECCIÓN IV'!B8 -> SECCIÓN IV: RETIROS DE DINERO POR PROVINCIA
C24: 4.1 Evolución de Transacciones de Retiros de Dinero por Provincia
C25: 4.2 Evolución del Monto de Retiros de Dinero por Provincia
C26: 4.3 Evolución del Monto Promedio de Retiros de Dinero por Provincia
C27: 4.4 Resumen Anual de Transacciones, Monto de Retiros y Monto Promedio de Retiros de Dinero por Provincia
C29: =+'SECCIÓN V'!B8 -> SECCIÓN V: RETIROS DE DINERO POR ORDENANTE
C30: 5.1 Evolución de Transacciones de Retiros de Dinero por Ordenante
C31: 5.2 Evolución del Monto de Retiros de Dinero por Ordenante
C32: 5.3 Evolución del Monto Promedio de Retiros de Dinero por Ordenante
C33: 5.4 Resumen Anual de Transacciones, Monto de Retiros y Monto Promedio de Retiros de Dinero por Ordenante
C35: =+'SECCIÓN VI'!B8 -> SECCIÓN VI: RETIROS DE DINERO POR ENTIDAD FINANCIERA POR CANAL
C36: 6.1 Evolución de Transacciones de Retiros de Dinero por Entidad Financiera por Canal
C37: 6.2 Evolución del Monto de Retiros de Dinero por Entidad Financiera por Canal
C38: 6.3. Evolución del Monto Promedio de Retiros de Dinero por Entidad Financiera por Canal
C40: =+'SECCIÓN VII'!B8 -> SECCIÓN VII: RETIROS DE DINERO POR ENTIDAD FINANCIERA POR PROVINCIA
C41: 7.1 Evolución de Transacciones de Retiros de Dinero por Entidad Financiera por Provincia
C42: 7.2 Evolución del Monto de Retiros de Dinero por Entidad Financiera por Provincia
C43: 7.3. Evolución del Monto Promedio de Retiros de Dinero por Entidad Financiera por Provincia
C45: =+'SECCIÓN VIII'!B8 -> SECCIÓN VIII: RETIROS DE DINERO POR ENTIDAD FINANCIERA POR ORDENANTE
C46: 8.1 Evolución de Transacciones de Retiros de Dinero por Entidad Financiera por Ordenante
C47: 8.2 Evolución del Monto de Retiros de Dinero por Entidad Financiera por Ordenante
C48: 8.3. Evolución del Monto Promedio de Retiros de Dinero por Entidad Financiera por Ordenante
C50: =+'SECCIÓN IX'!B8 -> SECCIÓN IX: RETIROS DE DINERO POR CANAL POR PROVINCIA
C51: 9.1 Evolución de Transacciones de Retiros de Dinero por Canal por Provincia
C52: 9.2 Evolución del Monto de Retiros de Dinero por Canal por Provincia
C53: 9.3. Evolución del Monto Promedio de Retiros de Dinero por Canal por Provincia
C55: =+'SECCIÓN X'!B8 -> SECCIÓN X: RETIROS DE DINERO POR CANAL POR ORDENANTE
C56: 10.1 Evolución de Transacciones de Retiros de Dinero por Canal por Ordenante
C57: 10.2 Evolución del Monto de Retiros de Dinero por Canal por Ordenante
C58: 10.3. Evolución del Monto Promedio de Retiros de Dinero por Canal por Ordenante
C60: =+'SECCIÓN XI Y XII'!B8 -> SECCIÓN XI: CONSIDERANDOS
C62: =+'SECCIÓN XI Y XII'!B12 -> SECCIÓN XII: CONTACTOS

Sheet Retiros de Dinero Ene-Dic 2016
B1: SUPERINTENDENCIA DE BANCOS DEL ECUADOR DIRECCIÓN NACIONAL DE ESTUDIOS E INFORMACIÓN SUBDIRECCIÓN DE ADMINISTRACIÓN DE SERVICIOS
B5: ESTADÍSTICAS DE RETIROS DE DINERO EN EFECTIVO SOBRE CUENTAS DE AHORRO EN CANALES PROPIOS DE LA ENTIDAD
B6: Enero - Diciembre 2016
B7: Fecha de publicación: Febrero 2017
B10: SECCIÓN I: RETIROS DE DINERO EN GENERAL
B12: 1.1 Evolución de Transacciones y Montos de Retiros de Dinero
B15: Tipo de Entidad | C15: enero | D15: febrero | E15: marzo | F15: abril | G15: mayo | H15: junio | I15: julio | J15: agosto | K15: septiembre | L15: octubre | M15: noviembre | N15: diciembre | O15: Total | P15: Promedio
B16: Número de Retiros | C16: =+#REF! -> #REF! | D16: =+#REF! -> #REF! | E16: =+#REF! -> #REF! | F16: =+#REF! -> #REF! | G16: =+#REF! -> #REF! | H16: =+#REF! -> #REF! | I16: =+#REF! -> #REF! | J16: =+#REF! -> #REF! | ... N16: =+#REF! -> #REF! | O16: =SUM(C16:N16) -> #REF! | P16: =+AVERAGE(C16:N16) -> #REF!
B17: Monto de Retiros | C17: =+#REF! -> #REF! | D17: =+#REF! -> #REF! | E17: =+#REF! -> #REF! | F17: =+#REF! -> #REF! | G17: =+#REF! -> #REF! | H17: =+#REF! -> #REF! | I17: =+#REF! -> #REF! | J17: =+#REF! -> #REF! | ... N17: =+#REF! -> #REF! | O17: =SUM(C17:N17) -> #REF! | P17: =+AVERAGE(C17:N17) -> #REF!
B18: Monto Promedio por Retiro | C18: =+C17/C16 -> #REF! | D18: =+D17/D16 -> #REF! | E18: =+E17/E16 -> #REF! | F18: =+F17/F16 -> #REF! | G18: =+G17/G16 -> #REF! | H18: =+H17/H16 -> #REF! | I18: =+I17/I16 -> #REF! | J18: =+J17/J16 -> #REF! | ... P18: =+P17/P16 -> #REF!
B38: SECCIÓN II: RETIROS DE DINERO POR ENTIDAD FINANCIERA
B40: 2.1 Evolución de Transacciones de Retiros de Dinero por Entidad Financiera
B43: Entidad Financiera | C43: enero | D43: febrero | E43: marzo | F43: abril | G43: mayo | H43: junio | I43: julio | J43: agosto | K43: septiembre | L43: octubre | M43: noviembre | N43: diciembre | O43: Total | P43: Promedio | Q43: % Número de Retiros | BA43: Entidad Financiera | BB43: enero | BC43: febrero | BD43: marzo | BE43: abril | BF43: mayo | BG43: junio | BH43: julio | BI43: agosto | BJ43: septiembre | BK43: octubre | BL43: noviembre | BM43: diciembre | BN43: Total
B44: =+#REF! -> #REF! | C44: =+#REF! -> #REF! | D44: =+#REF! -> #REF! | E44: =+#REF! -> #REF! | F44: =+#REF! -> #REF! | G44: =+#REF! -> #REF! | H44: =+#REF! -> #REF! | I44: =+#REF! -> #REF! | ... N44: =+#REF! -> #REF! | O44: =SUM(C44:N44) -> #REF! | P44: =+AVERAGE(C44:N44) -> #REF! | Q44: =+O44/$O$78 -> #REF! | BA44: =+B44 -> #REF! | BB44: =+C44 -> #REF! | BC44: =+D44 -> #REF! | BD44: =+E44 -> #REF! | BE44: =+F44 -> #REF! | BF44: =+G44 -> #REF! | BG44: =+H44 -> #REF! | BH44: =+I44 -> #REF! | ... BN44: =+O44 -> #REF!
B45: =+#REF! -> #REF! | C45: =+#REF! -> #REF! | D45: =+#REF! -> #REF! | E45: =+#REF! -> #REF! | F45: =+#REF! -> #REF! | G45: =+#REF! -> #REF! | H45: =+#REF! -> #REF! | I45: =+#REF! -> #REF! | ... N45: =+#REF! -> #REF! | O45: =SUM(C45:N45) -> #REF! | P45: =+AVERAGE(C45:N45) -> #REF! | Q45: =+O45/$O$78 -> #REF! | BA45: =+B45 -> #REF! | BB45: =+C45 -> #REF! | BC45: =+D45 -> #REF! | BD45: =+E45 -> #REF! | BE45: =+F45 -> #REF! | BF45: =+G45 -> #REF! | BG45: =+H45 -> #REF! | BH45: =+I45 -> #REF! | ... BN45: =+O45 -> #REF!
B46: =+#REF! -> #REF! | C46: =+#REF! -> #REF! | D46: =+#REF! -> #REF! | E46: =+#REF! -> #REF! | F46: =+#REF! -> #REF! | G46: =+#REF! -> #REF! | H46: =+#REF! -> #REF! | I46: =+#REF! -> #REF! | ... N46: =+#REF! -> #REF! | O46: =SUM(C46:N46) -> #REF! | P46: =+AVERAGE(C46:N46) -> #REF! | Q46: =+O46/$O$78 -> #REF! | BA46: =+B46 -> #REF! | BB46: =+C46 -> #REF! | BC46: =+D46 -> #REF! | BD46: =+E46 -> #REF! | BE46: =+F46 -> #REF! | BF46: =+G46 -> #REF! | BG46: =+H46 -> #REF! | BH46: =+I46 -> #REF! | ... BN46: =+O46 -> #REF!
B47: =+#REF! -> #REF! | C47: =+#REF! -> #REF! | D47: =+#REF! -> #REF! | E47: =+#REF! -> #REF! | F47: =+#REF! -> #REF! | G47: =+#REF! -> #REF! | H47: =+#REF! -> #REF! | I47: =+#REF! -> #REF! | ... N47: =+#REF! -> #REF! | O47: =SUM(C47:N47) -> #REF! | P47: =+AVERAGE(C47:N47) -> #REF! | Q47: =+O47/$O$78 -> #REF! | BA47: =+B47 -> #REF! | BB47: =+C47 -> #REF! | BC47: =+D47 -> #REF! | BD47: =+E47 -> #REF! | BE47: =+F47 -> #REF! | BF47: =+G47 -> #REF! | BG47: =+H47 -> #REF! | BH47: =+I47 -> #REF! | ... BN47: =+O47 -> #REF!
B48: =+#REF! -> #REF! | C48: =+#REF! -> #REF! | D48: =+#REF! -> #REF! | E48: =+#REF! -> #REF! | F48: =+#REF! -> #REF! | G48: =+#REF! -> #REF! | H48: =+#REF! -> #REF! | I48: =+#REF! -> #REF! | ... N48: =+#REF! -> #REF! | O48: =SUM(C48:N48) -> #REF! | P48: =+AVERAGE(C48:N48) -> #REF! | Q48: =+O48/$O$78 -> #REF! | BA48: =+B48 -> #REF! | BB48: =+C48 -> #REF! | BC48: =+D48 -> #REF! | BD48: =+E48 -> #REF! | BE48: =+F48 -> #REF! | BF48: =+G48 -> #REF! | BG48: =+H48 -> #REF! | BH48: =+I48 -> #REF! | ... BN48: =+O48 -> #REF!
B49: =+#REF! -> #REF! | C49: =+#REF! -> #REF! | D49: =+#REF! -> #REF! | E49: =+#REF! -> #REF! | F49: =+#REF! -> #REF! | G49: =+#REF! -> #REF! | H49: =+#REF! -> #REF! | I49: =+#REF! -> #REF! | ... N49: =+#REF! -> #REF! | O49: =SUM(C49:N49) -> #REF! | P49: =+AVERAGE(C49:N49) -> #REF! | Q49: =+O49/$O$78 -> #REF! | BA49: Resto de Entidades Financieras | BB49: =SUM(BB50:BB78) -> #REF! | BC49: =SUM(BC50:BC78) -> #REF! | BD49: =SUM(BD50:BD78) -> #REF! | BE49: =SUM(BE50:BE78) -> #REF! | BF49: =SUM(BF50:BF78) -> #REF! | BG49: =SUM(BG50:BG78) -> #REF! | BH49: =SUM(BH50:BH78) -> #REF! | BI49: =SUM(BI50:BI78) -> #REF! | ... BN49: =SUM(BN50:BN78) -> #REF!
B50: =+#REF! -> #REF! | C50: =+#REF! -> #REF! | D50: =+#REF! -> #REF! | E50: =+#REF! -> #REF! | F50: =+#REF! -> #REF! | G50: =+#REF! -> #REF! | H50: =+#REF! -> #REF! | I50: =+#REF! -> #REF! | ... N50: =+#REF! -> #REF! | O50: =SUM(C50:N50) -> #REF! | P50: =+AVERAGE(C50:N50) -> #REF! | Q50: =+O50/$O$78 -> #REF! | BA50: =+B49 -> #REF! | BB50: =+C49 -> #REF! | BC50: =+D49 -> #REF! | BD50: =+E49 -> #REF! | BE50: =+F49 -> #REF! | BF50: =+G49 -> #REF! | BG50: =+H49 -> #REF! | BH50: =+I49 -> #REF! | ... BN50: =+O49 -> #REF!
B51: =+#REF! -> #REF! | C51: =+#REF! -> #REF! | D51: =+#REF! -> #REF! | E51: =+#REF! -> #REF! | F51: =+#REF! -> #REF! | G51: =+#REF! -> #REF! | H51: =+#REF! -> #REF! | I51: =+#REF! -> #REF! | ... N51: =+#REF! -> #REF! | O51: =SUM(C51:N51) -> #REF! | P51: =+AVERAGE(C51:N51) -> #REF! | Q51: =+O51/$O$78 -> #REF! | BA51: =+B50 -> #REF! | BB51: =+C50 -> #REF! | BC51: =+D50 -> #REF! | BD51: =+E50 -> #REF! | BE51: =+F50 -> #REF! | BF51: =+G50 -> #REF! | BG51: =+H50 -> #REF! | BH51: =+I50 -> #REF! | ... BN51: =+O50 -> #REF!
B52: =+#REF! -> #REF! | C52: =+#REF! -> #REF! | D52: =+#REF! -> #REF! | E52: =+#REF! -> #REF! | F52: =+#REF! -> #REF! | G52: =+#REF! -> #REF! | H52: =+#REF! -> #REF! | I52: =+#REF! -> #REF! | ... N52: =+#REF! -> #REF! | O52: =SUM(C52:N52) -> #REF! | P52: =+AVERAGE(C52:N52) -> #REF! | Q52: =+O52/$O$78 -> #REF! | BA52: =+B51 -> #REF! | BB52: =+C51 -> #REF! | BC52: =+D51 -> #REF! | BD52: =+E51 -> #REF! | BE52: =+F51 -> #REF! | BF52: =+G51 -> #REF! | BG52: =+H51 -> #REF! | BH52: =+I51 -> #REF! | ... BN52: =+O51 -> #REF!
B53: =+#REF! -> #REF! | C53: =+#REF! -> #REF! | D53: =+#REF! -> #REF! | E53: =+#REF! -> #REF! | F53: =+#REF! -> #REF! | G53: =+#REF! -> #REF! | H53: =+#REF! -> #REF! | I53: =+#REF! -> #REF! | ... N53: =+#REF! -> #REF! | O53: =SUM(C53:N53) -> #REF! | P53: =+AVERAGE(C53:N53) -> #REF! | Q53: =+O53/$O$78 -> #REF! | BA53: =+B52 -> #REF! | BB53: =+C52 -> #REF! | BC53: =+D52 -> #REF! | BD53: =+E52 -> #REF! | BE53: =+F52 -> #REF! | BF53: =+G52 -> #REF! | BG53: =+H52 -> #REF! | BH53: =+I52 -> #REF! | ... BN53: =+O52 -> #REF!
B54: =+#REF! -> #REF! | C54: =+#REF! -> #REF! | D54: =+#REF! -> #REF! | E54: =+#REF! -> #REF! | F54: =+#REF! -> #REF! | G54: =+#REF! -> #REF! | H54: =+#REF! -> #REF! | I54: =+#REF! -> #REF! | ... N54: =+#REF! -> #REF! | O54: =SUM(C54:N54) -> #REF! | P54: =+AVERAGE(C54:N54) -> #REF! | Q54: =+O54/$O$78 -> #REF! | BA54: =+B53 -> #REF! | BB54: =+C53 -> #REF! | BC54: =+D53 -> #REF! | BD54: =+E53 -> #REF! | BE54: =+F53 -> #REF! | BF54: =+G53 -> #REF! | BG54: =+H53 -> #REF! | BH54: =+I53 -> #REF! | ... BN54: =+O53 -> #REF!
B55: =+#REF! -> #REF! | C55: =+#REF! -> #REF! | D55: =+#REF! -> #REF! | E55: =+#REF! -> #REF! | F55: =+#REF! -> #REF! | G55: =+#REF! -> #REF! | H55: =+#REF! -> #REF! | I55: =+#REF! -> #REF! | ... N55: =+#REF! -> #REF! | O55: =SUM(C55:N55) -> #REF! | P55: =+AVERAGE(C55:N55) -> #REF! | Q55: =+O55/$O$78 -> #REF! | BA55: =+B54 -> #REF! | BB55: =+C54 -> #REF! | BC55: =+D54 -> #REF! | BD55: =+E54 -> #REF! | BE55: =+F54 -> #REF! | BF55: =+G54 -> #REF! | BG55: =+H54 -> #REF! | BH55: =+I54 -> #REF! | ... BN55: =+O54 -> #REF!
B56: =+#REF! -> #REF! | C56: =+#REF! -> #REF! | D56: =+#REF! -> #REF! | E56: =+#REF! -> #REF! | F56: =+#REF! -> #REF! | G56: =+#REF! -> #REF! | H56: =+#REF! -> #REF! | I56: =+#REF! -> #REF! | ... N56: =+#REF! -> #REF! | O56: =SUM(C56:N56) -> #REF! | P56: =+AVERAGE(C56:N56) -> #REF! | Q56: =+O56/$O$78 -> #REF! | BA56: =+B55 -> #REF! | BB56: =+C55 -> #REF! | BC56: =+D55 -> #REF! | BD56: =+E55 -> #REF! | BE56: =+F55 -> #REF! | BF56: =+G55 -> #REF! | BG56: =+H55 -> #REF! | BH56: =+I55 -> #REF! | ... BN56: =+O55 -> #REF!
B57: =+#REF! -> #REF! | C57: =+#REF! -> #REF! | D57: =+#REF! -> #REF! | E57: =+#REF! -> #REF! | F57: =+#REF! -> #REF! | G57: =+#REF! -> #REF! | H57: =+#REF! -> #REF! | I57: =+#REF! -> #REF! | ... N57: =+#REF! -> #REF! | O57: =SUM(C57:N57) -> #REF! | P57: =+AVERAGE(C57:N57) -> #REF! | Q57: =+O57/$O$78 -> #REF! | BA57: =+B56 -> #REF! | BB57: =+C56 -> #REF! | BC57: =+D56 -> #REF! | BD57: =+E56 -> #REF! | BE57: =+F56 -> #REF! | BF57: =+G56 -> #REF! | BG57: =+H56 -> #REF! | BH57: =+I56 -> #REF! | ... BN57: =+O56 -> #REF!
B58: =+#REF! -> #REF! | C58: =+#REF! -> #REF! | D58: =+#REF! -> #REF! | E58: =+#REF! -> #REF! | F58: =+#REF! -> #REF! | G58: =+#REF! -> #REF! | H58: =+#REF! -> #REF! | I58: =+#REF! -> #REF! | ... N58: =+#REF! -> #REF! | O58: =SUM(C58:N58) -> #REF! | P58: =+AVERAGE(C58:N58) -> #REF! | Q58: =+O58/$O$78 -> #REF! | BA58: =+B57 -> #REF! | BB58: =+C57 -> #REF! | BC58: =+D57 -> #REF! | BD58: =+E57 -> #REF! | BE58: =+F57 -> #REF! | BF58: =+G57 -> #REF! | BG58: =+H57 -> #REF! | BH58: =+I57 -> #REF! | ... BN58: =+O57 -> #REF!
B59: =+#REF! -> #REF! | C59: =+#REF! -> #REF! | D59: =+#REF! -> #REF! | E59: =+#REF! -> #REF! | F59: =+#REF! -> #REF! | G59: =+#REF! -> #REF! | H59: =+#REF! -> #REF! | I59: =+#REF! -> #REF! | ... N59: =+#REF! -> #REF! | O59: =SUM(C59:N59) -> #REF! | P59: =+AVERAGE(C59:N59) -> #REF! | Q59: =+O59/$O$78 -> #REF! | BA59: =+B58 -> #REF! | BB59: =+C58 -> #REF! | BC59: =+D58 -> #REF! | BD59: =+E58 -> #REF! | BE59: =+F58 -> #REF! | BF59: =+G58 -> #REF! | BG59: =+H58 -> #REF! | BH59: =+I58 -> #REF! | ... BN59: =+O58 -> #REF!
B60: =+#REF! -> #REF! | C60: =+#REF! -> #REF! | D60: =+#REF! -> #REF! | E60: =+#REF! -> #REF! | F60: =+#REF! -> #REF! | G60: =+#REF! -> #REF! | H60: =+#REF! -> #REF! | I60: =+#REF! -> #REF! | ... N60: =+#REF! -> #REF! | O60: =SUM(C60:N60) -> #REF! | P60: =+AVERAGE(C60:N60) -> #REF! | Q60: =+O60/$O$78 -> #REF! | BA60: =+B59 -> #REF! | BB60: =+C59 -> #REF! | BC60: =+D59 -> #REF! | BD60: =+E59 -> #REF! | BE60: =+F59 -> #REF! | BF60: =+G59 -> #REF! | BG60: =+H59 -> #REF! | BH60: =+I59 -> #REF! | ... BN60: =+O59 -> #REF!
B61: =+#REF! -> #REF! | C61: =+#REF! -> #REF! | D61: =+#REF! -> #REF! | E61: =+#REF! -> #REF! | F61: =+#REF! -> #REF! | G61: =+#REF! -> #REF! | H61: =+#REF! -> #REF! | I61: =+#REF! -> #REF! | ... N61: =+#REF! -> #REF! | O61: =SUM(C61:N61) -> #REF! | P61: =+AVERAGE(C61:N61) -> #REF! | Q61: =+O61/$O$78 -> #REF! | BA61: =+B60 -> #REF! | BB61: =+C60 -> #REF! | BC61: =+D60 -> #REF! | BD61: =+E60 -> #REF! | BE61: =+F60 -> #REF! | BF61: =+G60 -> #REF! | BG61: =+H60 -> #REF! | BH61: =+I60 -> #REF! | ... BN61: =+O60 -> #REF!
... B77: =+#REF! -> #REF! | C77: =+#REF! -> #REF! | D77: =+#REF! -> #REF! | E77: =+#REF! -> #REF! | F77: =+#REF! -> #REF! | G77: =+#REF! -> #REF! | H77: =+#REF! -> #REF! | I77: =+#REF! -> #REF! | ... N77: =+#REF! -> #REF! | O77: =SUM(C77:N77) -> #REF! | P77: =+AVERAGE(C77:N77) -> #REF! | Q77: =+O77/$O$78 -> #REF! | BA77: =+B76 -> #REF! | BB77: =+C76 -> #REF! | BC77: =+D76 -> #REF! | BD77: =+E76 -> #REF! | BE77: =+F76 -> #REF! | BF77: =+G76 -> #REF! | BG77: =+H76 -> #REF! | BH77: =+I76 -> #REF! | ... BN77: =+O76 -> #REF!
B78: Total | C78: =SUM(C44:C77) -> #REF! | D78: =SUM(D44:D77) -> #REF! | E78: =SUM(E44:E77) -> #REF! | F78: =SUM(F44:F77) -> #REF! | G78: =SUM(G44:G77) -> #REF! | H78: =SUM(H44:H77) -> #REF! | I78: =SUM(I44:I77) -> #REF! | J78: =SUM(J44:J77) -> #REF! | ... N78: =SUM(N44:N77) -> #REF! | O78: =SUM(C78:N78) -> #REF! | P78: =+AVERAGE(C78:N78) -> #REF! | Q78: =+O78/$O$78 -> #REF! | BA78: =+B77 -> #REF! | BB78: =+C77 -> #REF! | BC78: =+D77 -> #REF! | BD78: =+E77 -> #REF! | BE78: =+F77 -> #REF! | BF78: =+G77 -> #REF! | BG78: =+H77 -> #REF! | BH78: =+I77 -> #REF! | ... BN78: =+O77 -> #REF!
BA79: =+B78 -> Total | BB79: =+C78 -> #REF! | BC79: =+D78 -> #REF! | BD79: =+E78 -> #REF! | BE79: =+F78 -> #REF! | BF79: =+G78 -> #REF! | BG79: =+H78 -> #REF! | BH79: =+I78 -> #REF! | ... BN79: =+O78 -> #REF!
B103: 2.2 Evolución del Monto de Retiros de Dinero por Entidad Financiera
B106: Entidad Financiera | C106: enero | D106: febrero | E106: marzo | F106: abril | G106: mayo | H106: junio | I106: julio | J106: agosto | K106: septiembre | L106: octubre | M106: noviembre | N106: diciembre | O106: Total | P106: Promedio | Q106: % Monto por Retiros | BA106: Entidad Financiera | BB106: enero | BC106: febrero | BD106: marzo | BE106: abril | BF106: mayo | BG106: junio | BH106: julio | BI106: agosto | BJ106: septiembre | BK106: octubre | BL106: noviembre | BM106: diciembre | BN106: Total
B107: =+#REF! -> #REF! | C107: =+#REF! -> #REF! | D107: =+#REF! -> #REF! | E107: =+#REF! -> #REF! | F107: =+#REF! -> #REF! | G107: =+#REF! -> #REF! | H107: =+#REF! -> #REF! | I107: =+#REF! -> #REF! | ... N107: =+#REF! -> #REF! | O107: =SUM(C107:N107) -> #REF! | P107: =+AVERAGE(C107:N107) -> #REF! | Q107: =+O107/$O$141 -> #REF! | BA107: =+B107 -> #REF! | BB107: =+C107 -> #REF! | BC107: =+D107 -> #REF! | BD107: =+E107 -> #REF! | BE107: =+F107 -> #REF! | BF107: =+G107 -> #REF! | BG107: =+H107 -> #REF! | BH107: =+I107 -> #REF! | ... BN107: =+O107 -> #REF!
B108: =+#REF! -> #REF! | C108: =+#REF! -> #REF! | D108: =+#REF! -> #REF! | E108: =+#REF! -> #REF! | F108: =+#REF! -> #REF! | G108: =+#REF! -> #REF! | H108: =+#REF! -> #REF! | I108: =+#REF! -> #REF! | ... N108: =+#REF! -> #REF! | O108: =SUM(C108:N108) -> #REF! | P108: =+AVERAGE(C108:N108) -> #REF! | Q108: =+O108/$O$141 -> #REF! | BA108: =+B108 -> #REF! | BB108: =+C108 -> #REF! | BC108: =+D108 -> #REF! | BD108: =+E108 -> #REF! | BE108: =+F108 -> #REF! | BF108: =+G108 -> #REF! | BG108: =+H108 -> #REF! | BH108: =+I108 -> #REF! | ... BN108: =+O108 -> #REF!
B109: =+#REF! -> #REF! | C109: =+#REF! -> #REF! | D109: =+#REF! -> #REF! | E109: =+#REF! -> #REF! | F109: =+#REF! -> #REF! | G109: =+#REF! -> #REF! | H109: =+#REF! -> #REF! | I109: =+#REF! -> #REF! | ... N109: =+#REF! -> #REF! | O109: =SUM(C109:N109) -> #REF! | P109: =+AVERAGE(C109:N109) -> #REF! | Q109: =+O109/$O$141 -> #REF! | BA109: =+B109 -> #REF! | BB109: =+C109 -> #REF! | BC109: =+D109 -> #REF! | BD109: =+E109 -> #REF! | BE109: =+F109 -> #REF! | BF109: =+G109 -> #REF! | BG109: =+H109 -> #REF! | BH109: =+I109 -> #REF! | ... BN109: =+O109 -> #REF!
B110: =+#REF! -> #REF! | C110: =+#REF! -> #REF! | D110: =+#REF! -> #REF! | E110: =+#REF! -> #REF! | F110: =+#REF! -> #REF! | G110: =+#REF! -> #REF! | H110: =+#REF! -> #REF! | I110: =+#REF! -> #REF! | ... N110: =+#REF! -> #REF! | O110: =SUM(C110:N110) -> #REF! | P110: =+AVERAGE(C110:N110) -> #REF! | Q110: =+O110/$O$141 -> #REF! | BA110: =+B110 -> #REF! | BB110: =+C110 -> #REF! | BC110: =+D110 -> #REF! | BD110: =+E110 -> #REF! | BE110: =+F110 -> #REF! | BF110: =+G110 -> #REF! | BG110: =+H110 -> #REF! | BH110: =+I110 -> #REF! | ... BN110: =+O110 -> #REF!
B111: =+#REF! -> #REF! | C111: =+#REF! -> #REF! | D111: =+#REF! -> #REF! | E111: =+#REF! -> #REF! | F111: =+#REF! -> #REF! | G111: =+#REF! -> #REF! | H111: =+#REF! -> #REF! | I111: =+#REF! -> #REF! | ... N111: =+#REF! -> #REF! | O111: =SUM(C111:N111) -> #REF! | P111: =+AVERAGE(C111:N111) -> #REF! | Q111: =+O111/$O$141 -> #REF! | BA111: =+B111 -> #REF! | BB111: =+C111 -> #REF! | BC111: =+D111 -> #REF! | BD111: =+E111 -> #REF! | BE111: =+F111 -> #REF! | BF111: =+G111 -> #REF! | BG111: =+H111 -> #REF! | BH111: =+I111 -> #REF! | ... BN111: =+O111 -> #REF!
B112: =+#REF! -> #REF! | C112: =+#REF! -> #REF! | D112: =+#REF! -> #REF! | E112: =+#REF! -> #REF! | F112: =+#REF! -> #REF! | G112: =+#REF! -> #REF! | H112: =+#REF! -> #REF! | I112: =+#REF! -> #REF! | ... N112: =+#REF! -> #REF! | O112: =SUM(C112:N112) -> #REF! | P112: =+AVERAGE(C112:N112) -> #REF! | Q112: =+O112/$O$141 -> #REF! | BA112: Resto de Entidades Financieras | BB112: =SUM(BB113:BB141) -> #REF! | BC112: =SUM(BC113:BC141) -> #REF! | BD112: =SUM(BD113:BD141) -> #REF! | BE112: =SUM(BE113:BE141) -> #REF! | BF112: =SUM(BF113:BF141) -> #REF! | BG112: =SUM(BG113:BG141) -> #REF! | BH112: =SUM(BH113:BH141) -> #REF! | BI112: =SUM(BI113:BI141) -> #REF! | ... BN112: =SUM(BN113:BN141) -> #REF!
B113: =+#REF! -> #REF! | C113: =+#REF! -> #REF! | D113: =+#REF! -> #REF! | E113: =+#REF! -> #REF! | F113: =+#REF! -> #REF! | G113: =+#REF! -> #REF! | H113: =+#REF! -> #REF! | I113: =+#REF! -> #REF! | ... N113: =+#REF! -> #REF! | O113: =SUM(C113:N113) -> #REF! | P113: =+AVERAGE(C113:N113) -> #REF! | Q113: =+O113/$O$141 -> #REF! | BA113: =+B112 -> #REF! | BB113: =+C112 -> #REF! | BC113: =+D112 -> #REF! | BD113: =+E112 -> #REF! | BE113: =+F112 -> #REF! | BF113: =+G112 -> #REF! | BG113: =+H112 -> #REF! | BH113: =+I112 -> #REF! | ... BN113: =+O112 -> #REF!
B114: =+#REF! -> #REF! | C114: =+#REF! -> #REF! | D114: =+#REF! -> #REF! | E114: =+#REF! -> #REF! | F114: =+#REF! -> #REF! | G114: =+#REF! -> #REF! | H114: =+#REF! -> #REF! | I114: =+#REF! -> #REF! | ... N114: =+#REF! -> #REF! | O114: =SUM(C114:N114) -> #REF! | P114: =+AVERAGE(C114:N114) -> #REF! | Q114: =+O114/$O$141 -> #REF! | BA114: =+B113 -> #REF! | BB114: =+C113 -> #REF! | BC114: =+D113 -> #REF! | BD114: =+E113 -> #REF! | BE114: =+F113 -> #REF! | BF114: =+G113 -> #REF! | BG114: =+H113 -> #REF! | BH114: =+I113 -> #REF! | ... BN114: =+O113 -> #REF!
B115: =+#REF! -> #REF! | C115: =+#REF! -> #REF! | D115: =+#REF! -> #REF! | E115: =+#REF! -> #REF! | F115: =+#REF! -> #REF! | G115: =+#REF! -> #REF! | H115: =+#REF! -> #REF! | I115: =+#REF! -> #REF! | ... N115: =+#REF! -> #REF! | O115: =SUM(C115:N115) -> #REF! | P115: =+AVERAGE(C115:N115) -> #REF! | Q115: =+O115/$O$141 -> #REF! | BA115: =+B114 -> #REF! | BB115: =+C114 -> #REF! | BC115: =+D114 -> #REF! | BD115: =+E114 -> #REF! | BE115: =+F114 -> #REF! | BF115: =+G114 -> #REF! | BG115: =+H114 -> #REF! | BH115: =+I114 -> #REF! | ... BN115: =+O114 -> #REF!
B116: =+#REF! -> #REF! | C116: =+#REF! -> #REF! | D116: =+#REF! -> #REF! | E116: =+#REF! -> #REF! | F116: =+#REF! -> #REF! | G116: =+#REF! -> #REF! | H116: =+#REF! -> #REF! | I116: =+#REF! -> #REF! | ... N116: =+#REF! -> #REF! | O116: =SUM(C116:N116) -> #REF! | P116: =+AVERAGE(C116:N116) -> #REF! | Q116: =+O116/$O$141 -> #REF! | BA116: =+B115 -> #REF! | BB116: =+C115 -> #REF! | BC116: =+D115 -> #REF! | BD116: =+E115 -> #REF! | BE116: =+F115 -> #REF! | BF116: =+G115 -> #REF! | BG116: =+H115 -> #REF! | BH116: =+I115 -> #REF! | ... BN116: =+O115 -> #REF!
B117: =+#REF! -> #REF! | C117: =+#REF! -> #REF! | D117: =+#REF! -> #REF! | E117: =+#REF! -> #REF! | F117: =+#REF! -> #REF! | G117: =+#REF! -> #REF! | H117: =+#REF! -> #REF! | I117: =+#REF! -> #REF! | ... N117: =+#REF! -> #REF! | O117: =SUM(C117:N117) -> #REF! | P117: =+AVERAGE(C117:N117) -> #REF! | Q117: =+O117/$O$141 -> #REF! | BA117: =+B116 -> #REF! | BB117: =+C116 -> #REF! | BC117: =+D116 -> #REF! | BD117: =+E116 -> #REF! | BE117: =+F116 -> #REF! | BF117: =+G116 -> #REF! | BG117: =+H116 -> #REF! | BH117: =+I116 -> #REF! | ... BN117: =+O116 -> #REF!
B118: =+#REF! -> #REF! | C118: =+#REF! -> #REF! | D118: =+#REF! -> #REF! | E118: =+#REF! -> #REF! | F118: =+#REF! -> #REF! | G118: =+#REF! -> #REF! | H118: =+#REF! -> #REF! | I118: =+#REF! -> #REF! | ... N118: =+#REF! -> #REF! | O118: =SUM(C118:N118) -> #REF! | P118: =+AVERAGE(C118:N118) -> #REF! | Q118: =+O118/$O$141 -> #REF! | BA118: =+B117 -> #REF! | BB118: =+C117 -> #REF! | BC118: =+D117 -> #REF! | BD118: =+E117 -> #REF! | BE118: =+F117 -> #REF! | BF118: =+G117 -> #REF! | BG118: =+H117 -> #REF! | BH118: =+I117 -> #REF! | ... BN118: =+O117 -> #REF!
B119: =+#REF! -> #REF! | C119: =+#REF! -> #REF! | D119: =+#REF! -> #REF! | E119: =+#REF! -> #REF! | F119: =+#REF! -> #REF! | G119: =+#REF! -> #REF! | H119: =+#REF! -> #REF! | I119: =+#REF! -> #REF! | ... N119: =+#REF! -> #REF! | O119: =SUM(C119:N119) -> #REF! | P119: =+AVERAGE(C119:N119) -> #REF! | Q119: =+O119/$O$141 -> #REF! | BA119: =+B118 -> #REF! | BB119: =+C118 -> #REF! | BC119: =+D118 -> #REF! | BD119: =+E118 -> #REF! | BE119: =+F118 -> #REF! | BF119: =+G118 -> #REF! | BG119: =+H118 -> #REF! | BH119: =+I118 -> #REF! | ... BN119: =+O118 -> #REF!
B120: =+#REF! -> #REF! | C120: =+#REF! -> #REF! | D120: =+#REF! -> #REF! | E120: =+#REF! -> #REF! | F120: =+#REF! -> #REF! | G120: =+#REF! -> #REF! | H120: =+#REF! -> #REF! | I120: =+#REF! -> #REF! | ... N120: =+#REF! -> #REF! | O120: =SUM(C120:N120) -> #REF! | P120: =+AVERAGE(C120:N120) -> #REF! | Q120: =+O120/$O$141 -> #REF! | BA120: =+B119 -> #REF! | BB120: =+C119 -> #REF! | BC120: =+D119 -> #REF! | BD120: =+E119 -> #REF! | BE120: =+F119 -> #REF! | BF120: =+G119 -> #REF! | BG120: =+H119 -> #REF! | BH120: =+I119 -> #REF! | ... BN120: =+O119 -> #REF!
B121: =+#REF! -> #REF! | C121: =+#REF! -> #REF! | D121: =+#REF! -> #REF! | E121: =+#REF! -> #REF! | F121: =+#REF! -> #REF! | G121: =+#REF! -> #REF! | H121: =+#REF! -> #REF! | I121: =+#REF! -> #REF! | ... N121: =+#REF! -> #REF! | O121: =SUM(C121:N121) -> #REF! | P121: =+AVERAGE(C121:N121) -> #REF! | Q121: =+O121/$O$141 -> #REF! | BA121: =+B120 -> #REF! | BB121: =+C120 -> #REF! | BC121: =+D120 -> #REF! | BD121: =+E120 -> #REF! | BE121: =+F120 -> #REF! | BF121: =+G120 -> #REF! | BG121: =+H120 -> #REF! | BH121: =+I120 -> #REF! | ... BN121: =+O120 -> #REF!
B122: =+#REF! -> #REF! | C122: =+#REF! -> #REF! | D122: =+#REF! -> #REF! | E122: =+#REF! -> #REF! | F122: =+#REF! -> #REF! | G122: =+#REF! -> #REF! | H122: =+#REF! -> #REF! | I122: =+#REF! -> #REF! | ... N122: =+#REF! -> #REF! | O122: =SUM(C122:N122) -> #REF! | P122: =+AVERAGE(C122:N122) -> #REF! | Q122: =+O122/$O$141 -> #REF! | BA122: =+B121 -> #REF! | BB122: =+C121 -> #REF! | BC122: =+D121 -> #REF! | BD122: =+E121 -> #REF! | BE122: =+F121 -> #REF! | BF122: =+G121 -> #REF! | BG122: =+H121 -> #REF! | BH122: =+I121 -> #REF! | ... BN122: =+O121 -> #REF!
B123: =+#REF! -> #REF! | C123: =+#REF! -> #REF! | D123: =+#REF! -> #REF! | E123: =+#REF! -> #REF! | F123: =+#REF! -> #REF! | G123: =+#REF! -> #REF! | H123: =+#REF! -> #REF! | I123: =+#REF! -> #REF! | ... N123: =+#REF! -> #REF! | O123: =SUM(C123:N123) -> #REF! | P123: =+AVERAGE(C123:N123) -> #REF! | Q123: =+O123/$O$141 -> #REF! | BA123: =+B122 -> #REF! | BB123: =+C122 -> #REF! | BC123: =+D122 -> #REF! | BD123: =+E122 -> #REF! | BE123: =+F122 -> #REF! | BF123: =+G122 -> #REF! | BG123: =+H122 -> #REF! | BH123: =+I122 -> #REF! | ... BN123: =+O122 -> #REF!
B124: =+#REF! -> #REF! | C124: =+#REF! -> #REF! | D124: =+#REF! -> #REF! | E124: =+#REF! -> #REF! | F124: =+#REF! -> #REF! | G124: =+#REF! -> #REF! | H124: =+#REF! -> #REF! | I124: =+#REF! -> #REF! | ... N124: =+#REF! -> #REF! | O124: =SUM(C124:N124) -> #REF! | P124: =+AVERAGE(C124:N124) -> #REF! | Q124: =+O124/$O$141 -> #REF! | BA124: =+B123 -> #REF! | BB124: =+C123 -> #REF! | BC124: =+D123 -> #REF! | BD124: =+E123 -> #REF! | BE124: =+F123 -> #REF! | BF124: =+G123 -> #REF! | BG124: =+H123 -> #REF! | BH124: =+I123 -> #REF! | ... BN124: =+O123 -> #REF!
... B140: =+#REF! -> #REF! | C140: =+#REF! -> #REF! | D140: =+#REF! -> #REF! | E140: =+#REF! -> #REF! | F140: =+#REF! -> #REF! | G140: =+#REF! -> #REF! | H140: =+#REF! -> #REF! | I140: =+#REF! -> #REF! | ... N140: =+#REF! -> #REF! | O140: =SUM(C140:N140) -> #REF! | P140: =+AVERAGE(C140:N140) -> #REF! | Q140: =+O140/$O$141 -> #REF! | BA140: =+B139 -> #REF! | BB140: =+C139 -> #REF! | BC140: =+D139 -> #REF! | BD140: =+E139 -> #REF! | BE140: =+F139 -> #REF! | BF140: =+G139 -> #REF! | BG140: =+H139 -> #REF! | BH140: =+I139 -> #REF! | ... BN140: =+O139 -> #REF!
B141: Total | C141: =SUM(C107:C140) -> #REF! | D141: =SUM(D107:D140) -> #REF! | E141: =SUM(E107:E140) -> #REF! | F141: =SUM(F107:F140) -> #REF! | G141: =SUM(G107:G140) -> #REF! | H141: =SUM(H107:H140) -> #REF! | I141: =SUM(I107:I140) -> #REF! | J141: =SUM(J107:J140) -> #REF! | ... N141: =SUM(N107:N140) -> #REF! | O141: =SUM(C141:N141) -> #REF! | P141: =+AVERAGE(C141:N141) -> #REF! | Q141: =+O141/$O$141 -> #REF! | BA141: =+B140 -> #REF! | BB141: =+C140 -> #REF! | BC141: =+D140 -> #REF! | BD141: =+E140 -> #REF! | BE141: =+F140 -> #REF! | BF141: =+G140 -> #REF! | BG141: =+H140 -> #REF! | BH141: =+I140 -> #REF! | ... BN141: =+O140 -> #REF!
BA142: =+B141 -> Total | BB142: =+C141 -> #REF! | BC142: =+D141 -> #REF! | BD142: =+E141 -> #REF! | BE142: =+F141 -> #REF! | BF142: =+G141 -> #REF! | BG142: =+H141 -> #REF! | BH142: =+I141 -> #REF! | ... BN142: =+O141 -> #REF!
B166: 2.3 Evolución del Monto Promedio de Retiros de Dinero por Entidad Financiera
C168: 2 | D168: 3 | E168: 4 | F168: 5 | G168: 6 | H168: 7 | I168: 8 | J168: 9 | K168: 10 | L168: 11 | M168: 12 | N168: 13 | O168: 14
B169: Entidad Financiera | C169: enero | D169: febrero | E169: marzo | F169: abril | G169: mayo | H169: junio | I169: julio | J169: agosto | K169: septiembre | L169: octubre | M169: noviembre | N169: diciembre | O169: Promedio
B170: =+B107 -> #REF! | C170: =+VLOOKUP($B170,$B$107:$N$140,C$168,0)/(VLOOKUP($B170,$B$44:$N$77,C$168,0)) -> #REF! | D170: =+VLOOKUP($B170,$B$107:$N$140,D$168,0)/(VLOOKUP($B170,$B$44:$N$77,D$168,0)) -> #REF! | E170: =+VLOOKUP($B170,$B$107:$N$140,E$168,0)/(VLOOKUP($B170,$B$44:$N$77,E$168,0)) -> #REF! | F170: =+VLOOKUP($B170,$B$107:$N$140,F$168,0)/(VLOOKUP($B170,$B$44:$N$77,F$168,0)) -> #REF! | G170: =+VLOOKUP($B170,$B$107:$N$140,G$168,0)/(VLOOKUP($B170,$B$44:$N$77,G$168,0)) -> #REF! | H170: =+VLOOKUP($B170,$B$107:$N$140,H$168,0)/(VLOOKUP($B170,$B$44:$N$77,H$168,0)) -> #REF! | I170: =+VLOOKUP($B170,$B$107:$N$140,I$168,0)/(VLOOKUP($B170,$B$44:$N$77,I$168,0)) -> #REF! | J170: =+VLOOKUP($B170,$B$107:$N$140,J$168,0)/(VLOOKUP($B170,$B$44:$N$77,J$168,0)) -> #REF! | ... N170: =+VLOOKUP($B170,$B$107:$N$140,N$168,0)/(VLOOKUP($B170,$B$44:$N$77,N$168,0)) -> #REF! | O170: =+AVERAGE(C170:N170) -> #REF!
B171: =+B108 -> #REF! | C171: =+VLOOKUP($B171,$B$107:$N$140,C$168,0)/(VLOOKUP($B171,$B$44:$N$77,C$168,0)) -> #REF! | D171: =+VLOOKUP($B171,$B$107:$N$140,D$168,0)/(VLOOKUP($B171,$B$44:$N$77,D$168,0)) -> #REF! | E171: =+VLOOKUP($B171,$B$107:$N$140,E$168,0)/(VLOOKUP($B171,$B$44:$N$77,E$168,0)) -> #REF! | F171: =+VLOOKUP($B171,$B$107:$N$140,F$168,0)/(VLOOKUP($B171,$B$44:$N$77,F$168,0)) -> #REF! | G171: =+VLOOKUP($B171,$B$107:$N$140,G$168,0)/(VLOOKUP($B171,$B$44:$N$77,G$168,0)) -> #REF! | H171: =+VLOOKUP($B171,$B$107:$N$140,H$168,0)/(VLOOKUP($B171,$B$44:$N$77,H$168,0)) -> #REF! | I171: =+VLOOKUP($B171,$B$107:$N$140,I$168,0)/(VLOOKUP($B171,$B$44:$N$77,I$168,0)) -> #REF! | J171: =+VLOOKUP($B171,$B$107:$N$140,J$168,0)/(VLOOKUP($B171,$B$44:$N$77,J$168,0)) -> #REF! | ... N171: =+VLOOKUP($B171,$B$107:$N$140,N$168,0)/(VLOOKUP($B171,$B$44:$N$77,N$168,0)) -> #REF! | O171: =+AVERAGE(C171:N171) -> #REF!
B172: =+B109 -> #REF! | C172: =+VLOOKUP($B172,$B$107:$N$140,C$168,0)/(VLOOKUP($B172,$B$44:$N$77,C$168,0)) -> #REF! | D172: =+VLOOKUP($B172,$B$107:$N$140,D$168,0)/(VLOOKUP($B172,$B$44:$N$77,D$168,0)) -> #REF! | E172: =+VLOOKUP($B172,$B$107:$N$140,E$168,0)/(VLOOKUP($B172,$B$44:$N$77,E$168,0)) -> #REF! | F172: =+VLOOKUP($B172,$B$107:$N$140,F$168,0)/(VLOOKUP($B172,$B$44:$N$77,F$168,0)) -> #REF! | G172: =+VLOOKUP($B172,$B$107:$N$140,G$168,0)/(VLOOKUP($B172,$B$44:$N$77,G$168,0)) -> #REF! | H172: =+VLOOKUP($B172,$B$107:$N$140,H$168,0)/(VLOOKUP($B172,$B$44:$N$77,H$168,0)) -> #REF! | I172: =+VLOOKUP($B172,$B$107:$N$140,I$168,0)/(VLOOKUP($B172,$B$44:$N$77,I$168,0)) -> #REF! | J172: =+VLOOKUP($B172,$B$107:$N$140,J$168,0)/(VLOOKUP($B172,$B$44:$N$77,J$168,0)) -> #REF! | ... N172: =+VLOOKUP($B172,$B$107:$N$140,N$168,0)/(VLOOKUP($B172,$B$44:$N$77,N$168,0)) -> #REF! | O172: =+AVERAGE(C172:N172) -> #REF!
B173: =+B110 -> #REF! | C173: =+VLOOKUP($B173,$B$107:$N$140,C$168,0)/(VLOOKUP($B173,$B$44:$N$77,C$168,0)) -> #REF! | D173: =+VLOOKUP($B173,$B$107:$N$140,D$168,0)/(VLOOKUP($B173,$B$44:$N$77,D$168,0)) -> #REF! | E173: =+VLOOKUP($B173,$B$107:$N$140,E$168,0)/(VLOOKUP($B173,$B$44:$N$77,E$168,0)) -> #REF! | F173: =+VLOOKUP($B173,$B$107:$N$140,F$168,0)/(VLOOKUP($B173,$B$44:$N$77,F$168,0)) -> #REF! | G173: =+VLOOKUP($B173,$B$107:$N$140,G$168,0)/(VLOOKUP($B173,$B$44:$N$77,G$168,0)) -> #REF! | H173: =+VLOOKUP($B173,$B$107:$N$140,H$168,0)/(VLOOKUP($B173,$B$44:$N$77,H$168,0)) -> #REF! | I173: =+VLOOKUP($B173,$B$107:$N$140,I$168,0)/(VLOOKUP($B173,$B$44:$N$77,I$168,0)) -> #REF! | J173: =+VLOOKUP($B173,$B$107:$N$140,J$168,0)/(VLOOKUP($B173,$B$44:$N$77,J$168,0)) -> #REF! | ... N173: =+VLOOKUP($B173,$B$107:$N$140,N$168,0)/(VLOOKUP($B173,$B$44:$N$77,N$168,0)) -> #REF! | O173: =+AVERAGE(C173:N173) -> #REF!
B174: =+B111 -> #REF! | C174: =+VLOOKUP($B174,$B$107:$N$140,C$168,0)/(VLOOKUP($B174,$B$44:$N$77,C$168,0)) -> #REF! | D174: =+VLOOKUP($B174,$B$107:$N$140,D$168,0)/(VLOOKUP($B174,$B$44:$N$77,D$168,0)) -> #REF! | E174: =+VLOOKUP($B174,$B$107:$N$140,E$168,0)/(VLOOKUP($B174,$B$44:$N$77,E$168,0)) -> #REF! | F174: =+VLOOKUP($B174,$B$107:$N$140,F$168,0)/(VLOOKUP($B174,$B$44:$N$77,F$168,0)) -> #REF! | G174: =+VLOOKUP($B174,$B$107:$N$140,G$168,0)/(VLOOKUP($B174,$B$44:$N$77,G$168,0)) -> #REF! | H174: =+VLOOKUP($B174,$B$107:$N$140,H$168,0)/(VLOOKUP($B174,$B$44:$N$77,H$168,0)) -> #REF! | I174: =+VLOOKUP($B174,$B$107:$N$140,I$168,0)/(VLOOKUP($B174,$B$44:$N$77,I$168,0)) -> #REF! | J174: =+VLOOKUP($B174,$B$107:$N$140,J$168,0)/(VLOOKUP($B174,$B$44:$N$77,J$168,0)) -> #REF! | ... N174: =+VLOOKUP($B174,$B$107:$N$140,N$168,0)/(VLOOKUP($B174,$B$44:$N$77,N$168,0)) -> #REF! | O174: =+AVERAGE(C174:N174) -> #REF!
B175: =+B112 -> #REF! | C175: =+VLOOKUP($B175,$B$107:$N$140,C$168,0)/(VLOOKUP($B175,$B$44:$N$77,C$168,0)) -> #REF! | D175: =+VLOOKUP($B175,$B$107:$N$140,D$168,0)/(VLOOKUP($B175,$B$44:$N$77,D$168,0)) -> #REF! | E175: =+VLOOKUP($B175,$B$107:$N$140,E$168,0)/(VLOOKUP($B175,$B$44:$N$77,E$168,0)) -> #REF! | F175: =+VLOOKUP($B175,$B$107:$N$140,F$168,0)/(VLOOKUP($B175,$B$44:$N$77,F$168,0)) -> #REF! | G175: =+VLOOKUP($B175,$B$107:$N$140,G$168,0)/(VLOOKUP($B175,$B$44:$N$77,G$168,0)) -> #REF! | H175: =+VLOOKUP($B175,$B$107:$N$140,H$168,0)/(VLOOKUP($B175,$B$44:$N$77,H$168,0)) -> #REF! | I175: =+VLOOKUP($B175,$B$107:$N$140,I$168,0)/(VLOOKUP($B175,$B$44:$N$77,I$168,0)) -> #REF! | J175: =+VLOOKUP($B175,$B$107:$N$140,J$168,0)/(VLOOKUP($B175,$B$44:$N$77,J$168,0)) -> #REF! | ... N175: =+VLOOKUP($B175,$B$107:$N$140,N$168,0)/(VLOOKUP($B175,$B$44:$N$77,N$168,0)) -> #REF! | O175: =+AVERAGE(C175:N175) -> #REF!
B176: =+B113 -> #REF! | C176: =+VLOOKUP($B176,$B$107:$N$140,C$168,0)/(VLOOKUP($B176,$B$44:$N$77,C$168,0)) -> #REF! | D176: =+VLOOKUP($B176,$B$107:$N$140,D$168,0)/(VLOOKUP($B176,$B$44:$N$77,D$168,0)) -> #REF! | E176: =+VLOOKUP($B176,$B$107:$N$140,E$168,0)/(VLOOKUP($B176,$B$44:$N$77,E$168,0)) -> #REF! | F176: =+VLOOKUP($B176,$B$107:$N$140,F$168,0)/(VLOOKUP($B176,$B$44:$N$77,F$168,0)) -> #REF! | G176: =+VLOOKUP($B176,$B$107:$N$140,G$168,0)/(VLOOKUP($B176,$B$44:$N$77,G$168,0)) -> #REF! | H176: =+VLOOKUP($B176,$B$107:$N$140,H$168,0)/(VLOOKUP($B176,$B$44:$N$77,H$168,0)) -> #REF! | I176: =+VLOOKUP($B176,$B$107:$N$140,I$168,0)/(VLOOKUP($B176,$B$44:$N$77,I$168,0)) -> #REF! | J176: =+VLOOKUP($B176,$B$107:$N$140,J$168,0)/(VLOOKUP($B176,$B$44:$N$77,J$168,0)) -> #REF! | ... N176: =+VLOOKUP($B176,$B$107:$N$140,N$168,0)/(VLOOKUP($B176,$B$44:$N$77,N$168,0)) -> #REF! | O176: =+AVERAGE(C176:N176) -> #REF!
B177: =+B114 -> #REF! | C177: =+VLOOKUP($B177,$B$107:$N$140,C$168,0)/(VLOOKUP($B177,$B$44:$N$77,C$168,0)) -> #REF! | D177: =+VLOOKUP($B177,$B$107:$N$140,D$168,0)/(VLOOKUP($B177,$B$44:$N$77,D$168,0)) -> #REF! | E177: =+VLOOKUP($B177,$B$107:$N$140,E$168,0)/(VLOOKUP($B177,$B$44:$N$77,E$168,0)) -> #REF! | F177: =+VLOOKUP($B177,$B$107:$N$140,F$168,0)/(VLOOKUP($B177,$B$44:$N$77,F$168,0)) -> #REF! | G177: =+VLOOKUP($B177,$B$107:$N$140,G$168,0)/(VLOOKUP($B177,$B$44:$N$77,G$168,0)) -> #REF! | H177: =+VLOOKUP($B177,$B$107:$N$140,H$168,0)/(VLOOKUP($B177,$B$44:$N$77,H$168,0)) -> #REF! | I177: =+VLOOKUP($B177,$B$107:$N$140,I$168,0)/(VLOOKUP($B177,$B$44:$N$77,I$168,0)) -> #REF! | J177: =+VLOOKUP($B177,$B$107:$N$140,J$168,0)/(VLOOKUP($B177,$B$44:$N$77,J$168,0)) -> #REF! | ... N177: =+VLOOKUP($B177,$B$107:$N$140,N$168,0)/(VLOOKUP($B177,$B$44:$N$77,N$168,0)) -> #REF! | O177: =+AVERAGE(C177:N177) -> #REF!
B178: =+B115 -> #REF! | C178: =+VLOOKUP($B178,$B$107:$N$140,C$168,0)/(VLOOKUP($B178,$B$44:$N$77,C$168,0)) -> #REF! | D178: =+VLOOKUP($B178,$B$107:$N$140,D$168,0)/(VLOOKUP($B178,$B$44:$N$77,D$168,0)) -> #REF! | E178: =+VLOOKUP($B178,$B$107:$N$140,E$168,0)/(VLOOKUP($B178,$B$44:$N$77,E$168,0)) -> #REF! | F178: =+VLOOKUP($B178,$B$107:$N$140,F$168,0)/(VLOOKUP($B178,$B$44:$N$77,F$168,0)) -> #REF! | G178: =+VLOOKUP($B178,$B$107:$N$140,G$168,0)/(VLOOKUP($B178,$B$44:$N$77,G$168,0)) -> #REF! | H178: =+VLOOKUP($B178,$B$107:$N$140,H$168,0)/(VLOOKUP($B178,$B$44:$N$77,H$168,0)) -> #REF! | I178: =+VLOOKUP($B178,$B$107:$N$140,I$168,0)/(VLOOKUP($B178,$B$44:$N$77,I$168,0)) -> #REF! | J178: =+VLOOKUP($B178,$B$107:$N$140,J$168,0)/(VLOOKUP($B178,$B$44:$N$77,J$168,0)) -> #REF! | ... N178: =+VLOOKUP($B178,$B$107:$N$140,N$168,0)/(VLOOKUP($B178,$B$44:$N$77,N$168,0)) -> #REF! | O178: =+AVERAGE(C178:N178) -> #REF!
B179: =+B116 -> #REF! | C179: =+VLOOKUP($B179,$B$107:$N$140,C$168,0)/(VLOOKUP($B179,$B$44:$N$77,C$168,0)) -> #REF! | D179: =+VLOOKUP($B179,$B$107:$N$140,D$168,0)/(VLOOKUP($B179,$B$44:$N$77,D$168,0)) -> #REF! | E179: =+VLOOKUP($B179,$B$107:$N$140,E$168,0)/(VLOOKUP($B179,$B$44:$N$77,E$168,0)) -> #REF! | F179: =+VLOOKUP($B179,$B$107:$N$140,F$168,0)/(VLOOKUP($B179,$B$44:$N$77,F$168,0)) -> #REF! | G179: =+VLOOKUP($B179,$B$107:$N$140,G$168,0)/(VLOOKUP($B179,$B$44:$N$77,G$168,0)) -> #REF! | H179: =+VLOOKUP($B179,$B$107:$N$140,H$168,0)/(VLOOKUP($B179,$B$44:$N$77,H$168,0)) -> #REF! | I179: =+VLOOKUP($B179,$B$107:$N$140,I$168,0)/(VLOOKUP($B179,$B$44:$N$77,I$168,0)) -> #REF! | J179: =+VLOOKUP($B179,$B$107:$N$140,J$168,0)/(VLOOKUP($B179,$B$44:$N$77,J$168,0)) -> #REF! | ... N179: =+VLOOKUP($B179,$B$107:$N$140,N$168,0)/(VLOOKUP($B179,$B$44:$N$77,N$168,0)) -> #REF! | O179: =+AVERAGE(C179:N179) -> #REF!
B180: =+B117 -> #REF! | C180: =+VLOOKUP($B180,$B$107:$N$140,C$168,0)/(VLOOKUP($B180,$B$44:$N$77,C$168,0)) -> #REF! | D180: =+VLOOKUP($B180,$B$107:$N$140,D$168,0)/(VLOOKUP($B180,$B$44:$N$77,D$168,0)) -> #REF! | E180: =+VLOOKUP($B180,$B$107:$N$140,E$168,0)/(VLOOKUP($B180,$B$44:$N$77,E$168,0)) -> #REF! | F180: =+VLOOKUP($B180,$B$107:$N$140,F$168,0)/(VLOOKUP($B180,$B$44:$N$77,F$168,0)) -> #REF! | G180: =+VLOOKUP($B180,$B$107:$N$140,G$168,0)/(VLOOKUP($B180,$B$44:$N$77,G$168,0)) -> #REF! | H180: =+VLOOKUP($B180,$B$107:$N$140,H$168,0)/(VLOOKUP($B180,$B$44:$N$77,H$168,0)) -> #REF! | I180: =+VLOOKUP($B180,$B$107:$N$140,I$168,0)/(VLOOKUP($B180,$B$44:$N$77,I$168,0)) -> #REF! | J180: =+VLOOKUP($B180,$B$107:$N$140,J$168,0)/(VLOOKUP($B180,$B$44:$N$77,J$168,0)) -> #REF! | ... N180: =+VLOOKUP($B180,$B$107:$N$140,N$168,0)/(VLOOKUP($B180,$B$44:$N$77,N$168,0)) -> #REF! | O180: =+AVERAGE(C180:N180) -> #REF!
B181: =+B118 -> #REF! | C181: =+VLOOKUP($B181,$B$107:$N$140,C$168,0)/(VLOOKUP($B181,$B$44:$N$77,C$168,0)) -> #REF! | D181: =+VLOOKUP($B181,$B$107:$N$140,D$168,0)/(VLOOKUP($B181,$B$44:$N$77,D$168,0)) -> #REF! | E181: =+VLOOKUP($B181,$B$107:$N$140,E$168,0)/(VLOOKUP($B181,$B$44:$N$77,E$168,0)) -> #REF! | F181: =+VLOOKUP($B181,$B$107:$N$140,F$168,0)/(VLOOKUP($B181,$B$44:$N$77,F$168,0)) -> #REF! | G181: =+VLOOKUP($B181,$B$107:$N$140,G$168,0)/(VLOOKUP($B181,$B$44:$N$77,G$168,0)) -> #REF! | H181: =+VLOOKUP($B181,$B$107:$N$140,H$168,0)/(VLOOKUP($B181,$B$44:$N$77,H$168,0)) -> #REF! | I181: =+VLOOKUP($B181,$B$107:$N$140,I$168,0)/(VLOOKUP($B181,$B$44:$N$77,I$168,0)) -> #REF! | J181: =+VLOOKUP($B181,$B$107:$N$140,J$168,0)/(VLOOKUP($B181,$B$44:$N$77,J$168,0)) -> #REF! | ... N181: =+VLOOKUP($B181,$B$107:$N$140,N$168,0)/(VLOOKUP($B181,$B$44:$N$77,N$168,0)) -> #REF! | O181: =+AVERAGE(C181:N181) -> #REF!
... B203: =+B140 -> #REF! | C203: =+VLOOKUP($B203,$B$107:$N$140,C$168,0)/(VLOOKUP($B203,$B$44:$N$77,C$168,0)) -> #REF! | D203: =+VLOOKUP($B203,$B$107:$N$140,D$168,0)/(VLOOKUP($B203,$B$44:$N$77,D$168,0)) -> #REF! | E203: =+VLOOKUP($B203,$B$107:$N$140,E$168,0)/(VLOOKUP($B203,$B$44:$N$77,E$168,0)) -> #REF! | F203: =+VLOOKUP($B203,$B$107:$N$140,F$168,0)/(VLOOKUP($B203,$B$44:$N$77,F$168,0)) -> #REF! | G203: =+VLOOKUP($B203,$B$107:$N$140,G$168,0)/(VLOOKUP($B203,$B$44:$N$77,G$168,0)) -> #REF! | H203: =+VLOOKUP($B203,$B$107:$N$140,H$168,0)/(VLOOKUP($B203,$B$44:$N$77,H$168,0)) -> #REF! | I203: =+VLOOKUP($B203,$B$107:$N$140,I$168,0)/(VLOOKUP($B203,$B$44:$N$77,I$168,0)) -> #REF! | J203: =+VLOOKUP($B203,$B$107:$N$140,J$168,0)/(VLOOKUP($B203,$B$44:$N$77,J$168,0)) -> #REF! | ... N203: =+VLOOKUP($B203,$B$107:$N$140,N$168,0)/(VLOOKUP($B203,$B$44:$N$77,N$168,0)) -> #REF! | O203: =+AVERAGE(C203:N203) -> #REF!
B204: Promedio | C204: =+C141/C78 -> #REF! | D204: =+D141/D78 -> #REF! | E204: =+E141/E78 -> #REF! | F204: =+F141/F78 -> #REF! | G204: =+G141/G78 -> #REF! | H204: =+H141/H78 -> #REF! | I204: =+I141/I78 -> #REF! | J204: =+J141/J78 -> #REF! | ... O204: =+O141/O78 -> #REF!
B229: 2.4 Resumen Anual de Transacciones, Monto de Retiros y Monto Promedio de Retiros de Dinero por Entidad Financiera
B232: Entidad Financiera | C232: Transacciones | D232: Monto de Retiros (USD) | E232: Monto promedio de Retiros (USD) | F232: % Transacciones | G232: % Monto de Retiros
B233: =+B170 -> #REF! | C233: =+VLOOKUP($B233,$B$44:$O$77,O$168,0) -> #REF! | D233: =+VLOOKUP($B233,$B$107:$O$140,O$168,0) -> #REF! | E233: =+D233/C233 -> #REF! | F233: =+C233/$C$267 -> #REF! | G233: =+D233/$D$267 -> #REF!
B234: =+B171 -> #REF! | C234: =+VLOOKUP($B234,$B$44:$O$77,O$168,0) -> #REF! | D234: =+VLOOKUP($B234,$B$107:$O$140,O$168,0) -> #REF! | E234: =+D234/C234 -> #REF! | F234: =+C234/$C$267 -> #REF! | G234: =+D234/$D$267 -> #REF!
B235: =+B172 -> #REF! | C235: =+VLOOKUP($B235,$B$44:$O$77,O$168,0) -> #REF! | D235: =+VLOOKUP($B235,$B$107:$O$140,O$168,0) -> #REF! | E235: =+D235/C235 -> #REF! | F235: =+C235/$C$267 -> #REF! | G235: =+D235/$D$267 -> #REF!
B236: =+B173 -> #REF! | C236: =+VLOOKUP($B236,$B$44:$O$77,O$168,0) -> #REF! | D236: =+VLOOKUP($B236,$B$107:$O$140,O$168,0) -> #REF! | E236: =+D236/C236 -> #REF! | F236: =+C236/$C$267 -> #REF! | G236: =+D236/$D$267 -> #REF!
B237: =+B174 -> #REF! | C237: =+VLOOKUP($B237,$B$44:$O$77,O$168,0) -> #REF! | D237: =+VLOOKUP($B237,$B$107:$O$140,O$168,0) -> #REF! | E237: =+D237/C237 -> #REF! | F237: =+C237/$C$267 -> #REF! | G237: =+D237/$D$267 -> #REF!
B238: =+B175 -> #REF! | C238: =+VLOOKUP($B238,$B$44:$O$77,O$168,0) -> #REF! | D238: =+VLOOKUP($B238,$B$107:$O$140,O$168,0) -> #REF! | E238: =+D238/C238 -> #REF! | F238: =+C238/$C$267 -> #REF! | G238: =+D238/$D$267 -> #REF!
B239: =+B176 -> #REF! | C239: =+VLOOKUP($B239,$B$44:$O$77,O$168,0) -> #REF! | D239: =+VLOOKUP($B239,$B$107:$O$140,O$168,0) -> #REF! | E239: =+D239/C239 -> #REF! | F239: =+C239/$C$267 -> #REF! | G239: =+D239/$D$267 -> #REF!
B240: =+B177 -> #REF! | C240: =+VLOOKUP($B240,$B$44:$O$77,O$168,0) -> #REF! | D240: =+VLOOKUP($B240,$B$107:$O$140,O$168,0) -> #REF! | E240: =+D240/C240 -> #REF! | F240: =+C240/$C$267 -> #REF! | G240: =+D240/$D$267 -> #REF!
B241: =+B178 -> #REF! | C241: =+VLOOKUP($B241,$B$44:$O$77,O$168,0) -> #REF! | D241: =+VLOOKUP($B241,$B$107:$O$140,O$168,0) -> #REF! | E241: =+D241/C241 -> #REF! | F241: =+C241/$C$267 -> #REF! | G241: =+D241/$D$267 -> #REF!
B242: =+B179 -> #REF! | C242: =+VLOOKUP($B242,$B$44:$O$77,O$168,0) -> #REF! | D242: =+VLOOKUP($B242,$B$107:$O$140,O$168,0) -> #REF! | E242: =+D242/C242 -> #REF! | F242: =+C242/$C$267 -> #REF! | G242: =+D242/$D$267 -> #REF!
B243: =+B180 -> #REF! | C243: =+VLOOKUP($B243,$B$44:$O$77,O$168,0) -> #REF! | D243: =+VLOOKUP($B243,$B$107:$O$140,O$168,0) -> #REF! | E243: =+D243/C243 -> #REF! | F243: =+C243/$C$267 -> #REF! | G243: =+D243/$D$267 -> #REF!
B244: =+B181 -> #REF! | C244: =+VLOOKUP($B244,$B$44:$O$77,O$168,0) -> #REF! | D244: =+VLOOKUP($B244,$B$107:$O$140,O$168,0) -> #REF! | E244: =+D244/C244 -> #REF! | F244: =+C244/$C$267 -> #REF! | G244: =+D244/$D$267 -> #REF!
... B266: =+B203 -> #REF! | C266: =+VLOOKUP($B266,$B$44:$O$77,O$168,0) -> #REF! | D266: =+VLOOKUP($B266,$B$107:$O$140,O$168,0) -> #REF! | E266: =+D266/C266 -> #REF! | F266: =+C266/$C$267 -> #REF! | G266: =+D266/$D$267 -> #REF!
B267: Total | C267: =SUM(C233:C266) -> #REF! | D267: =SUM(D233:D266) -> #REF! | E267: =+D267/C267 -> #REF! | F267: =SUM(F233:F266) -> #REF! | G267: =SUM(G233:G266) -> #REF!
B292: SECCIÓN III: RETIROS DE DINERO POR CANALES
B294: 3.1 Evolución de Transacciones de Retiros de Dinero por Canales
B297: Canal | C297: enero | D297: febrero | E297: marzo | F297: abril | G297: mayo | H297: junio | I297: julio | J297: agosto | K297: septiembre | L297: octubre | M297: noviembre | N297: diciembre | O297: Total | P297: Promedio | Q297: % Número de Retiros
B298: =+#REF! -> #REF! | C298: =+#REF! -> #REF! | D298: =+#REF! -> #REF! | E298: =+#REF! -> #REF! | F298: =+#REF! -> #REF! | G298: =+#REF! -> #REF! | H298: =+#REF! -> #REF! | I298: =+#REF! -> #REF! | ... N298: =+#REF! -> #REF! | O298: =SUM(C298:N298) -> #REF! | P298: =AVERAGE(D298:O298) -> #REF! | Q298: =+O298/$O$304 -> #REF!
B299: =+#REF! -> #REF! | C299: =+#REF! -> #REF! | D299: =+#REF! -> #REF! | E299: =+#REF! -> #REF! | F299: =+#REF! -> #REF! | G299: =+#REF! -> #REF! | H299: =+#REF! -> #REF! | I299: =+#REF! -> #REF! | ... N299: =+#REF! -> #REF! | O299: =SUM(C299:N299) -> #REF! | P299: =AVERAGE(D299:O299) -> #REF! | Q299: =+O299/$O$304 -> #REF!
B300: =+#REF! -> #REF! | C300: =+#REF! -> #REF! | D300: =+#REF! -> #REF! | E300: =+#REF! -> #REF! | F300: =+#REF! -> #REF! | G300: =+#REF! -> #REF! | H300: =+#REF! -> #REF! | I300: =+#REF! -> #REF! | ... N300: =+#REF! -> #REF! | O300: =SUM(C300:N300) -> #REF! | P300: =AVERAGE(D300:O300) -> #REF! | Q300: =+O300/$O$304 -> #REF!
B301: =+#REF! -> #REF! | C301: =+#REF! -> #REF! | D301: =+#REF! -> #REF! | E301: =+#REF! -> #REF! | F301: =+#REF! -> #REF! | G301: =+#REF! -> #REF! | H301: =+#REF! -> #REF! | I301: =+#REF! -> #REF! | ... N301: =+#REF! -> #REF! | O301: =SUM(C301:N301) -> #REF! | P301: =AVERAGE(D301:O301) -> #REF! | Q301: =+O301/$O$304 -> #REF!
B302: =+#REF! -> #REF! | C302: =+#REF! -> #REF! | D302: =+#REF! -> #REF! | E302: =+#REF! -> #REF! | F302: =+#REF! -> #REF! | G302: =+#REF! -> #REF! | H302: =+#REF! -> #REF! | I302: =+#REF! -> #REF! | ... N302: =+#REF! -> #REF! | O302: =SUM(C302:N302) -> #REF! | P302: =AVERAGE(D302:O302) -> #REF! | Q302: =+O302/$O$304 -> #REF!
B303: =+#REF! -> #REF! | C303: =+#REF! -> #REF! | D303: =+#REF! -> #REF! | E303: =+#REF! -> #REF! | F303: =+#REF! -> #REF! | G303: =+#REF! -> #REF! | H303: =+#REF! -> #REF! | I303: =+#REF! -> #REF! | ... N303: =+#REF! -> #REF! | O303: =SUM(C303:N303) -> #REF! | P303: =AVERAGE(D303:O303) -> #REF! | Q303: =+O303/$O$304 -> #REF!
B304: Total | C304: =SUM(C298:C303) -> #REF! | D304: =SUM(D298:D303) -> #REF! | E304: =SUM(E298:E303) -> #REF! | F304: =SUM(F298:F303) -> #REF! | G304: =SUM(G298:G303) -> #REF! | H304: =SUM(H298:H303) -> #REF! | I304: =SUM(I298:I303) -> #REF! | J304: =SUM(J298:J303) -> #REF! | ... N304: =SUM(N298:N303) -> #REF! | O304: =SUM(C304:N304) -> #REF! | P304: =AVERAGE(D304:O304) -> #REF! | Q304: =+O304/$O$304 -> #REF!
...

Sheet SECCIÓN I
B1: SUPERINTENDENCIA DE BANCOS DEL ECUADOR INTENDENCIA NACIONAL DE RIESGOS Y ESTUDIOS DIRECCIÓN DE ESTUDIOS Y GESTIÓN DE LA INFORMACIÓN SUBDIRECCIÓN DE ESTADÍSTICAS Y ESTUDIOS
B3: ESTADÍSTICAS DE RETIROS DE DINERO EN EFECTIVO SOBRE CUENTAS DE AHORRO EN CANALES PROPIOS DE LA ENTIDAD
B4: Enero a Diciembre 2020
B5: Fecha de publicación: Enero 2021
B6: Datos Provisionales
B8: SECCIÓN I: RETIROS DE DINERO EN GENERAL
B10: 1.1 Evolución de Transacciones y Montos de Retiros de Dinero
C11: 3 | D11: 4 | E11: 5 | F11: 6 | G11: 7 | H11: 8 | I11: 9 | J11: 10 | K11: 11 | L11: 12 | M11: 13 | N11: 14 | O11: 15
B12: Tipo de Entidad | C12: Enero | D12: Febrero | E12: Marzo | F12: Abril | G12: Mayo | H12: Junio | I12: Julio | J12: Agosto | K12: Septiembre | L12: Octubre | M12: Noviembre | N12: Diciembre | O12: Total | P12: Promedio
B13: Número de Retiros | C13: 21544651 | D13: 20636370 | E13: 16135331 | F13: 9464804 | G13: 11658889 | H13: 14957371 | I13: 16297665 | J13: 16897460 | K13: 17528920 | L13: 19102888 | M13: 18152210 | N13: 23519450 | O13: 2.0589601e+08 | P13: 17158001
B14: Monto de Retiros | C14: 3.5410659e+09 | D14: 3.3005592e+09 | E14: 2.7782638e+09 | F14: 1.7651048e+09 | G14: 2.0501476e+09 | H14: 2.55783e+09 | I14: 2.7437331e+09 | J14: 2.7246167e+09 | K14: 2.9052076e+09 | L14: 3.0969903e+09 | M14: 2.8566374e+09 | N14: 3.8389795e+09 | O14: 3.4159136e+10 | P14: 2.8465947e+09
B15: Monto Promedio por Retiro | C15: 164.3594 | D15: 159.93894 | E15: 172.18511 | F15: 186.49142 | G15: 175.84416 | H15: 171.008 | I15: 168.3513 | J15: 161.24416 | K15: 165.73797 | L15: 162.12158 | M15: 157.37133 | N15: 163.22573 | P15: 165.9048

Sheet SECCIÓN II
B1: SUPERINTENDENCIA DE BANCOS DEL ECUADOR INTENDENCIA NACIONAL DE RIESGOS Y ESTUDIOS DIRECCIÓN DE ESTUDIOS Y GESTIÓN DE LA INFORMACIÓN SUBDIRECCIÓN DE ESTADÍSTICAS Y ESTUDIOS
B3: ESTADÍSTICAS DE RETIROS DE DINERO EN EFECTIVO SOBRE CUENTAS DE AHORRO EN CANALES PROPIOS DE LA ENTIDAD
B4: Enero a Diciembre 2020
B5: Fecha de publicación: Enero 2021
B6: Datos Provisionales
B8: SECCIÓN II: RETIROS DE DINERO POR ENTIDAD FINANCIERA
B10: 2.1 Evolución de Transacciones de Retiros de Dinero por Entidad Financiera
C11: 2 | D11: 3 | E11: 4 | F11: 5 | G11: 6 | H11: 7 | I11: 8 | J11: 9 | K11: 10 | L11: 11 | M11: 12 | N11: 13 | O11: 14 | P11: 15
B12: Entidad Financiera | C12: Enero | D12: Febrero | E12: Marzo | F12: Abril | G12: Mayo | H12: Junio | I12: Julio | J12: Agosto | K12: Septiembre | L12: Octubre | M12: Noviembre | N12: Diciembre | O12: Total | P12: Promedio | Q12: % Número de Retiros | BA12: Entidad Financiera | BB12: Enero | BC12: Febrero | BD12: Marzo | BE12: Abril | BF12: Mayo | BG12: Junio | BH12: Julio | BI12: Agosto | BJ12: Septiembre | BK12: Octubre | BL12: Noviembre | BM12: Diciembre | BN12: Total
B13: Banco Pichincha | C13: 9356898 | D13: 9143527 | E13: 6702892 | F13: 3747549 | G13: 4727072 | H13: 6321403 | I13: 7034388 | J13: 7368183 | K13: 7682739 | L13: 8612765 | M13: 8079432 | N13: 9903107 | O13: 88679955 | P13: 7389996.2 | Q13: 0.43070264 | BA13: Banco Pichincha | BB13: 9356898 | BC13: 9143527 | BD13: 6702892 | BE13: 3747549 | BF13: 4727072 | BG13: 6321403 | BH13: 7034388 | BI13: 7368183 | BJ13: 7682739 | BK13: 8612765 | BL13: 8079432 | BM13: 9903107 | BN13: 88679955
B14: Banco de Guayaquil | C14: 3636390 | D14: 3339408 | E14: 3012153 | F14: 1838633 | G14: 2109870 | H14: 2764666 | I14: 2923349 | J14: 3017675 | K14: 3090959 | L14: 3267287 | M14: 3338384 | N14: 3959865 | O14: 36298639 | P14: 3024886.6 | Q14: 0.17629598 | BA14: Banco de Guayaquil | BB14: 3636390 | BC14: 3339408 | BD14: 3012153 | BE14: 1838633 | BF14: 2109870 | BG14: 2764666 | BH14: 2923349 | BI14: 3017675 | BJ14: 3090959 | BK14: 3267287 | BL14: 3338384 | BM14: 3959865 | BN14: 36298639
B15: Banco del Pacífico | C15: 2913669 | D15: 2820005 | E15: 2194288 | F15: 1376443 | G15: 1745571 | H15: 2038885 | I15: 2198389 | J15: 2257560 | K15: 2373335 | L15: 2619315 | M15: 2403631 | N15: 3110757 | O15: 28051848 | P15: 2337654 | Q15: 0.1362428 | BA15: Banco del Pacífico | BB15: 2913669 | BC15: 2820005 | BD15: 2194288 | BE15: 1376443 | BF15: 1745571 | BG15: 2038885 | BH15: 2198389 | BI15: 2257560 | BJ15: 2373335 | BK15: 2619315 | BL15: 2403631 | BM15: 3110757 | BN15: 28051848
B16: Banco Bolivariano | C16: 1350730 | D16: 1214459 | E16: 1113232 | F16: 693058 | G16: 821626 | H16: 1052001 | I16: 1085012 | J16: 1080692 | K16: 1092927 | L16: 1139120 | M16: 1167595 | N16: 1404740 | O16: 13215192 | P16: 1101266 | Q16: 0.064183818 | BA16: Banco Bolivariano | BB16: 1350730 | BC16: 1214459 | BD16: 1113232 | BE16: 693058 | BF16: 821626 | BG16: 1052001 | BH16: 1085012 | BI16: 1080692 | BJ16: 1092927 | BK16: 1139120 | BL16: 1167595 | BM16: 1404740 | BN16: 13215192
B17: Banco Produbanco Grupo Promerica | C17: 1357634 | D17: 1318129 | E17: 967959 | F17: 535153 | G17: 659922 | H17: 857609 | I17: 931269 | J17: 979707 | K17: 988654 | L17: 1084712 | M17: 986301 | N17: 2411463 | O17: 13078512 | P17: 1089876 | Q17: 0.063519988 | BA17: Banco Produbanco Grupo Promerica | BB17: 1357634 | BC17: 1318129 | BD17: 967959 | BE17: 535153 | BF17: 659922 | BG17: 857609 | BH17: 931269 | BI17: 979707 | BJ17: 988654 | BK17: 1084712 | BL17: 986301 | BM17: 2411463 | BN17: 13078512
B18: Banco Internacional | C18: 902995 | D18: 876204 | E18: 674958 | F18: 458031 | G18: 542643 | H18: 557760 | I18: 655232 | J18: 692225 | K18: 697769 | L18: 760043 | M18: 692642 | N18: 836946 | O18: 8347448 | P18: 695620.67 | Q18: 0.040542058 | BA18: Banco Internacional | BB18: 902995 | BC18: 876204 | BD18: 674958 | BE18: 458031 | BF18: 542643 | BG18: 557760 | BH18: 655232 | BI18: 692225 | BJ18: 697769 | BK18: 760043 | BL18: 692642 | BM18: 836946 | BN18: 8347448
B19: Banco del Austro | C19: 556494 | D19: 526347 | E19: 393095 | F19: 225464 | G19: 296577 | H19: 381135 | I19: 411705 | J19: 426684 | K19: 447248 | L19: 480385 | M19: 445430 | N19: 552175 | O19: 5142739 | P19: 428561.58 | Q19: 0.024977361 | BA19: Resto de Entidades Financieras | BB19: 2026335 | BC19: 1924638 | BD19: 1469849 | BE19: 815937 | BF19: 1052185 | BG19: 1365047 | BH19: 1470026 | BI19: 1501418 | BJ19: 1602537 | BK19: 1619646 | BL19: 1484225 | BM19: 1892572 | BN19: 18224415
B20: Banco de Loja | C20: 427872 | D20: 417583 | E20: 304755 | F20: 160986 | G20: 212810 | H20: 278517 | I20: 298521 | J20: 311001 | K20: 339530 | L20: 269509 | M20: 248919 | N20: 318619 | O20: 3588622 | P20: 299051.83 | Q20: 0.017429294 | BA20: Banco del Austro | BB20: 556494 | BC20: 526347 | BD20: 393095 | BE20: 225464 | BF20: 296577 | BG20: 381135 | BH20: 411705 | BI20: 426684 | BJ20: 447248 | BK20: 480385 | BL20: 445430 | BM20: 552175 | BN20: 5142739
B21: Banco General Rumiñahui | C21: 289814 | D21: 275525 | E21: 218543 | F21: 148279 | G21: 182977 | H21: 200127 | I21: 213682 | J21: 231768 | K21: 249766 | L21: 268317 | M21: 226045 | N21: 327536 | O21: 2832379 | P21: 236031.58 | Q21: 0.013756357 | BA21: Banco de Loja | BB21: 427872 | BC21: 417583 | BD21: 304755 | BE21: 160986 | BF21: 212810 | BG21: 278517 | BH21: 298521 | BI21: 311001 | BJ21: 339530 | BK21: 269509 | BL21: 248919 | BM21: 318619 | BN21: 3588622
B22: Banco de Machala | C22: 299049 | D22: 276479 | E22: 245096 | F22: 141872 | G22: 168605 | H22: 216421 | I22: 230390 | J22: 221278 | K22: 234436 | L22: 248425 | M22: 237392 | N22: 298372 | O22: 2817815 | P22: 234817.92 | Q22: 0.013685622 | BA22: Banco General Rumiñahui | BB22: 289814 | BC22: 275525 | BD22: 218543 | BE22: 148279 | BF22: 182977 | BG22: 200127 | BH22: 213682 | BI22: 231768 | BJ22: 249766 | BK22: 268317 | BL22: 226045 | BM22: 327536 | BN22: 2832379
B23: Banco Coopnacional | C23: 108524 | D23: 96850 | E23: 80882 | F23: 48106 | G23: 64534 | H23: 88278 | I23: 92482 | J23: 81442 | K23: 88894 | L23: 92258 | M23: 85319 | N23: 96629 | O23: 1024198 | P23: 85349.833 | Q23: 0.0049743461 | BA23: Banco de Machala | BB23: 299049 | BC23: 276479 | BD23: 245096 | BE23: 141872 | BF23: 168605 | BG23: 216421 | BH23: 230390 | BI23: 221278 | BJ23: 234436 | BK23: 248425 | BL23: 237392 | BM23: 298372 | BN23: 2817815
B24: Servipagos | C24: 134279 | D24: 132045 | E24: 76573 | F24: 12642 | G24: 26315 | H24: 65330 | I24: 74841 | J24: 82202 | K24: 83161 | L24: 92640 | M24: 81381 | N24: 99360 | O24: 960769 | P24: 80064.083 | Q24: 0.0046662828 | BA24: Servipagos | BB24: 134279 | BC24: 132045 | BD24: 76573 | BE24: 12642 | BF24: 26315 | BG24: 65330 | BH24: 74841 | BI24: 82202 | BJ24: 83161 | BK24: 92640 | BL24: 81381 | BM24: 99360 | BN24: 960769
... B36: Total | C36: 21544651 | D36: 20636370 | E36: 16135331 | F36: 9464804 | G36: 11658889 | H36: 14957371 | I36: 16297665 | J36: 16897460 | K36: 17528920 | L36: 19102888 | M36: 18152210 | N36: 23519450 | O36: 205896009 | P36: 17158001 | Q36: 1 | BA36: Banco Visionfund | BB36: 8102 | BC36: 7451 | BD36: 4897 | BE36: 1560 | BF36: 1751 | BG36: 2425 | BH36: 5520 | BI36: 6735 | BJ36: 7394 | BK36: 7554 | BL36: 7423 | BM36: 8665 | BN36: 69477
BA37: Total | BB37: 21544651 | BC37: 20636370 | BD37: 16135331 | BE37: 9464804 | BF37: 11658889 | BG37: 14957371 | BH37: 16297665 | BI37: 16897460 | BJ37: 17528920 | BK37: 19102888 | BL37: 18152210 | BM37: 23519450 | BN37: 205896009
B63: 2.2 Evolución del Monto de Retiros de Dinero por Entidad Financiera
B64: (en dólares)
B65: Entidad Financiera | C65: Enero | D65: Febrero | E65: Marzo | F65: Abril | G65: Mayo | H65: Junio | I65: Julio | J65: Agosto | K65: Septiembre | L65: Octubre | M65: Noviembre | N65: Diciembre | O65: Total | P65: Promedio | Q65: % Monto por Retiros | BA65: Entidad Financiera | BB65: Enero | BC65: Febrero | BD65: Marzo | BE65: Abril | BF65: Mayo | BG65: Junio | BH65: Julio | BI65: Agosto | BJ65: Septiembre | BK65: Octubre | BL65: Noviembre | BM65: Diciembre | BN65: Total
B66: Banco Pichincha | C66: 1.6541333e+09 | D66: 1.5757648e+09 | E66: 1.2453934e+09 | F66: 7.3666686e+08 | G66: 8.9642399e+08 | H66: 1.1848766e+09 | I66: 1.2851275e+09 | J66: 1.2907008e+09 | K66: 1.3758687e+09 | L66: 1.5112006e+09 | M66: 1.383773e+09 | N66: 1.7547046e+09 | O66: 1.5894634e+10 | P66: 1.3245528e+09 | Q66: 0.46531137 | BA66: Banco Pichincha | BB66: 1.6541333e+09 | BC66: 1.5757648e+09 | BD66: 1.2453934e+09 | BE66: 7.3666686e+08 | BF66: 8.9642399e+08 | BG66: 1.1848766e+09 | BH66: 1.2851275e+09 | BI66: 1.2907008e+09 | BJ66: 1.3758687e+09 | BK66: 1.5112006e+09 | BL66: 1.383773e+09 | BM66: 1.7547046e+09 | BN66: 1.5894634e+10
B67: Banco de Guayaquil | C67: 4.0922588e+08 | D67: 3.5361336e+08 | E67: 3.4138197e+08 | F67: 2.2850172e+08 | G67: 2.5062819e+08 | H67: 2.9608052e+08 | I67: 3.1496587e+08 | J67: 3.0183259e+08 | K67: 3.2568453e+08 | L67: 3.4205769e+08 | M67: 3.4002513e+08 | N67: 4.4537263e+08 | O67: 3.9493701e+09 | P67: 3.2911417e+08 | Q67: 0.1156168 | BA67: Banco de Guayaquil | BB67: 4.0922588e+08 | BC67: 3.5361336e+08 | BD67: 3.4138197e+08 | BE67: 2.2850172e+08 | BF67: 2.5062819e+08 | BG67: 2.9608052e+08 | BH67: 3.1496587e+08 | BI67: 3.0183259e+08 | BJ67: 3.2568453e+08 | BK67: 3.4205769e+08 | BL67: 3.4002513e+08 | BM67: 4.4537263e+08 | BN67: 3.9493701e+09
B68: Banco del Pacífico | C68: 3.5582017e+08 | D68: 3.3227203e+08 | E68: 2.8995302e+08 | F68: 2.0238085e+08 | G68: 2.4222735e+08 | H68: 2.6760948e+08 | I68: 2.8088622e+08 | J68: 2.8086719e+08 | K68: 2.9492452e+08 | L68: 3.1797207e+08 | M68: 2.8449394e+08 | N68: 4.0532337e+08 | O68: 3.5547302e+09 | P68: 2.9622752e+08 | Q68: 0.10406382 | BA68: Banco del Pacífico | BB68: 3.5582017e+08 | BC68: 3.3227203e+08 | BD68: 2.8995302e+08 | BE68: 2.0238085e+08 | BF68: 2.4222735e+08 | BG68: 2.6760948e+08 | BH68: 2.8088622e+08 | BI68: 2.8086719e+08 | BJ68: 2.9492452e+08 | BK68: 3.1797207e+08 | BL68: 2.8449394e+08 | BM68: 4.0532337e+08 | BN68: 3.5547302e+09
B69: Banco Produbanco Grupo Promerica | C69: 2.5399982e+08 | D69: 2.4066916e+08 | E69: 1.9539707e+08 | F69: 1.4325534e+08 | G69: 1.5257241e+08 | H69: 1.7374205e+08 | I69: 1.8044785e+08 | J69: 1.8586157e+08 | K69: 1.9110929e+08 | L69: 2.0539563e+08 | M69: 1.8224619e+08 | N69: 4.0109357e+08 | O69: 2.50579e+09 | P69: 2.0881583e+08 | Q69: 0.073356363 | BA69: Banco Bolivariano | BB69: 2.2521223e+08 | BC69: 2.0246167e+08 | BD69: 2.0692242e+08 | BE69: 1.5289974e+08 | BF69: 1.5533901e+08 | BG69: 1.8893491e+08 | BH69: 1.924674e+08 | BI69: 1.8452875e+08 | BJ69: 1.920817e+08 | BK69: 2.0288985e+08 | BL69: 2.0193008e+08 | BM69: 2.6494707e+08 | BN69: 2.3706148e+09
B70: Banco Bolivariano | C70: 2.2521223e+08 | D70: 2.0246167e+08 | E70: 2.0692242e+08 | F70: 1.5289974e+08 | G70: 1.5533901e+08 | H70: 1.8893491e+08 | I70: 1.924674e+08 | J70: 1.8452875e+08 | K70: 1.920817e+08 | L70: 2.0288985e+08 | M70: 2.0193008e+08 | N70: 2.6494707e+08 | O70: 2.3706148e+09 | P70: 1.9755123e+08 | Q70: 0.069399145 | BA70: Banco Produbanco Grupo Promerica | BB70: 2.5399982e+08 | BC70: 2.4066916e+08 | BD70: 1.9539707e+08 | BE70: 1.4325534e+08 | BF70: 1.5257241e+08 | BG70: 1.7374205e+08 | BH70: 1.8044785e+08 | BI70: 1.8586157e+08 | BJ70: 1.9110929e+08 | BK70: 2.0539563e+08 | BL70: 1.8224619e+08 | BM70: 4.0109357e+08 | BN70: 2.50579e+09
B71: Banco Internacional | C71: 1.4210931e+08 | D71: 1.321181e+08 | E71: 1.1333408e+08 | F71: 86138783 | G71: 95877276 | H71: 1.0252598e+08 | I71: 1.1360103e+08 | J71: 1.1411239e+08 | K71: 1.1632523e+08 | L71: 1.2753117e+08 | M71: 1.1406114e+08 | N71: 89137800 | O71: 1.3468723e+09 | P71: 1.1223936e+08 | Q71: 0.039429343 | BA71: Resto de Entidades Financieras | BB71: 6.4267449e+08 | BC71: 5.9577816e+08 | BD71: 4.992159e+08 | BE71: 3.0140025e+08 | BF71: 3.5295662e+08 | BG71: 4.4658649e+08 | BH71: 4.8983825e+08 | BI71: 4.8082575e+08 | BJ71: 5.255389e+08 | BK71: 5.1747444e+08 | BL71: 4.641691e+08 | BM71: 5.6753827e+08 | BN71: 5.8839966e+09
B72: Banco del Austro | C72: 1.365322e+08 | D72: 1.2357656e+08 | E72: 1.0474295e+08 | F72: 58531340 | G72: 71587434 | H72: 95844230 | I72: 1.0525887e+08 | J72: 1.0717132e+08 | K72: 1.1611619e+08 | L72: 1.1755051e+08 | M72: 1.0627087e+08 | N72: 1.3691934e+08 | O72: 1.2801018e+09 | P72: 1.0667515e+08 | Q72: 0.037474654 | BA72: Banco Internacional | BB72: 1.4210931e+08 | BC72: 1.321181e+08 | BD72: 1.1333408e+08 | BE72: 86138783 | BF72: 95877276 | BG72: 1.0252598e+08 | BH72: 1.1360103e+08 | BI72: 1.1411239e+08 | BJ72: 1.1632523e+08 | BK72: 1.2753117e+08 | BL72: 1.1406114e+08 | BM72: 89137800 | BN72: 1.3468723e+09
B73: Banco de Machala | C73: 79569822 | D73: 70779163 | E73: 68669727 | F73: 45206929 | G73: 49345990 | H73: 60807114 | I73: 65623766 | J73: 58221386 | K73: 64905460 | L73: 68646878 | M73: 62546436 | N73: 88197164 | O73: 7.8251984e+08 | P73: 65209986 | Q73: 0.022908069 | BA73: Banco del Austro | BB73: 1.365322e+08 | BC73: 1.2357656e+08 | BD73: 1.0474295e+08 | BE73: 58531340 | BF73: 71587434 | BG73: 95844230 | BH73: 1.0525887e+08 | BI73: 1.0717132e+08 | BJ73: 1.1611619e+08 | BK73: 1.1755051e+08 | BL73: 1.0627087e+08 | BM73: 1.3691934e+08 | BN73: 1.2801018e+09
B74: Banco General Rumiñahui | C74: 73711385 | D74: 69071221 | E74: 58154928 | F74: 38451208 | G74: 41930819 | H74: 48372496 | I74: 51623555 | J74: 54432164 | K74: 62885338 | L74: 66839701 | M74: 54216950 | N74: 88125615 | O74: 7.0781538e+08 | P74: 58984615 | Q74: 0.020721115 | BA74: Banco de Machala | BB74: 79569822 | BC74: 70779163 | BD74: 68669727 | BE74: 45206929 | BF74: 49345990 | BG74: 60807114 | BH74: 65623766 | BI74: 58221386 | BJ74: 64905460 | BK74: 68646878 | BL74: 62546436 | BM74: 88197164 | BN74: 7.8251984e+08
B75: Banco de Loja | C75: 67294450 | D75: 64666850 | E75: 52151334 | F75: 29755413 | G75: 34290650 | H75: 44226758 | I75: 49796384 | J75: 50454277 | K75: 56273643 | L75: 23234510 | M75: 20715290 | N75: 29089900 | O75: 5.2194946e+08 | P75: 43495788 | Q75: 0.015279937 | BA75: Banco General Rumiñahui | BB75: 73711385 | BC75: 69071221 | BD75: 58154928 | BE75: 38451208 | BF75: 41930819 | BG75: 48372496 | BH75: 51623555 | BI75: 54432164 | BJ75: 62885338 | BK75: 66839701 | BL75: 54216950 | BM75: 88125615 | BN75: 7.0781538e+08
B76: Banco Coopnacional | C76: 29766216 | D76: 26774148 | E76: 26636184 | F76: 16189595 | G76: 22133240 | H76: 31118898 | I76: 30616668 | J76: 22703824 | K76: 26949334 | L76: 28176294 | M76: 25052074 | N76: 33821876 | O76: 319938351 | P76: 26661529 | Q76: 0.0093661137 | BA76: Banco de Loja | BB76: 67294450 | BC76: 64666850 | BD76: 52151334 | BE76: 29755413 | BF76: 34290650 | BG76: 44226758 | BH76: 49796384 | BI76: 50454277 | BJ76: 56273643 | BK76: 23234510 | BL76: 20715290 | BM76: 29089900 | BN76: 5.2194946e+08
B77: Servipagos | C77: 37277424 | D77: 35709370 | E77: 22985299 | F77: 5615120.1 | G77: 9743524.9 | H77: 24154218 | I77: 26205201 | J77: 25966200 | K77: 25383993 | L77: 27444599 | M77: 23735788 | N77: 32152700 | O77: 2.9637344e+08 | P77: 24697786 | Q77: 0.0086762569 | BA77: Servipagos | BB77: 37277424 | BC77: 35709370 | BD77: 22985299 | BE77: 5615120.1 | BF77: 9743524.9 | BG77: 24154218 | BH77: 26205201 | BI77: 25966200 | BJ77: 25383993 | BK77: 27444599 | BL77: 23735788 | BM77: 32152700 | BN77: 2.9637344e+08
... B89: Total | C89: 3.5410659e+09 | D89: 3.3005592e+09 | E89: 2.7782638e+09 | F89: 1.7651048e+09 | G89: 2.0501476e+09 | H89: 2.55783e+09 | I89: 2.7437331e+09 | J89: 2.7246167e+09 | K89: 2.9052076e+09 | L89: 3.0969903e+09 | M89: 2.8566374e+09 | N89: 3.8389795e+09 | O89: 3.4159136e+10 | P89: 2.8465947e+09 | Q89: 1 | BA89: Banco Visionfund | BB89: 6030139.3 | BC89: 5648501 | BD89: 3198082.7 | BE89: 507589.24 | BF89: 452717.21 | BG89: 874689.67 | BH89: 4024229.8 | BI89: 5068524.1 | BJ89: 5730839.5 | BK89: 5756937.1 | BL89: 6010455.9 | BM89: 6719545.9 | BN89: 50022251
BA90: Total | BB90: 3.5410659e+09 | BC90: 3.3005592e+09 | BD90: 2.7782638e+09 | BE90: 1.7651048e+09 | BF90: 2.0501476e+09 | BG90: 2.55783e+09 | BH90: 2.7437331e+09 | BI90: 2.7246167e+09 | BJ90: 2.9052076e+09 | BK90: 3.0969903e+09 | BL90: 2.8566374e+09 | BM90: 3.8389795e+09 | BN90: 3.4159136e+10
B115: 2.3 Evolución del Monto Promedio de Retiros de Dinero por Entidad Financiera
B116: (en dólares) | C116: 2 | D116: 3 | E116: 4 | F116: 5 | G116: 6 | H116: 7 | I116: 8 | J116: 9 | K116: 10 | L116: 11 | M116: 12 | N116: 13 | O116: 14
B117: Entidad Financiera | C117: Enero | D117: Febrero | E117: Marzo | F117: Abril | G117: Mayo | H117: Junio | I117: Julio | J117: Agosto | K117: Septiembre | L117: Octubre | M117: Noviembre | N117: Diciembre | O117: Promedio
B118: Banco Dmiro | C118: 761.90513 | D118: 788.80136 | E118: 806.93495 | F118: 442.9279 | G118: 480.41546 | H118: 538.91112 | I118: 855.12512 | J118: 882.56113 | K118: 913.55936 | L118: 762.85119 | M118: 759.25592 | N118: 715.83747 | O118: 763.42433
B119: Banco Visionfund | C119: 744.27786 | D119: 758.0863 | E119: 653.06977 | F119: 325.37772 | G119: 258.54781 | H119: 360.69677 | I119: 729.02714 | J119: 752.56483 | K119: 775.0662 | L119: 762.10446 | M119: 809.70711 | N119: 775.48135 | O119: 719.98289
B120: Banco Amazonas | C120: 569.00376 | D120: 507.48492 | E120: 590.53718 | F120: 606.03486 | G120: 707.9926 | H120: 499.93365 | I120: 469.84875 | J120: 461.40238 | K120: 480.16369 | L120: 430.64434 | M120: 514.50597 | N120: 541.77126 | O120: 527.4098
B121: Banco Finca | C121: 501.97514 | D121: 530.65692 | E121: 460.75742 | F121: 282.95863 | G121: 268.89449 | H121: 237.39835 | I121: 216.02152 | J121: 242.90865 | K121: 488.91129 | L121: 522.93568 | M121: 583.06665 | N121: 543.29399 | O121: 433.25358
B122: Banco Solidario | C122: 438.28289 | D122: 431.07319 | E122: 426.66799 | F122: 301.07694 | G122: 293.69869 | H122: 354.85532 | I122: 337.68465 | J122: 347.11102 | K122: 394.56685 | L122: 400.54425 | M122: 424.79529 | N122: 387.73647 | O122: 389.90555
B123: Banco Capital | C123: 405.1211 | D123: 316.85584 | E123: 368.16574 | F123: 417.56458 | G123: 408.90836 | H123: 416.26203 | I123: 367.69788 | J123: 347.8043 | K123: 367.38372 | L123: 327.00088 | M123: 407.87228 | N123: 403.16192 | O123: 377.2035
B124: Banco del Litoral | C124: 285.1548 | D124: 387.4317 | E124: 360.89618 | F124: 357.2914 | G124: 409.04051 | H124: 314.34171 | I124: 340.2627 | J124: 282.07181 | K124: 288.54632 | L124: 295.89211 | M124: 319.18394 | N124: 374.39783 | O124: 335.36713
B125: Banco Coopnacional | C125: 274.28233 | D125: 276.44964 | E125: 329.32153 | F125: 336.54004 | G125: 342.97022 | H125: 352.51023 | I125: 331.05543 | J125: 278.77292 | K125: 303.16258 | L125: 305.4076 | M125: 293.62831 | N125: 350.01786 | O125: 312.37939
B126: Servipagos | C126: 277.61172 | D126: 270.43334 | E126: 300.17498 | F126: 444.16391 | G126: 370.26505 | H126: 369.72628 | I126: 350.14499 | J126: 315.88283 | K126: 305.23915 | L126: 296.24999 | M126: 291.66253 | N126: 323.59803 | O126: 308.47523
B127: Banco Desarrollo de los Pueblos | C127: 299.80218 | D127: 297.25253 | E127: 294.48847 | F127: 275.14789 | G127: 274.04028 | H127: 284.21085 | I127: 322.82794 | J127: 301.94298 | K127: 325.07691 | L127: 309.88243 | M127: 304.23859 | N127: 310.74485 | O127: 301.494
B128: Banco de Machala | C128: 266.0762 | D128: 256.00195 | E128: 280.17482 | F128: 318.64588 | G128: 292.67216 | H128: 280.96679 | I128: 284.83773 | J128: 263.11421 | K128: 276.8579 | L128: 276.32838 | M128: 263.47322 | N128: 295.59464 | O128: 277.70448
B129: Banco Procredit | C129: 235.88925 | D129: 235.96887 | E129: 266.36229 | F129: 312.24752 | G129: 301.80553 | H129: 259.72439 | I129: 248.56485 | J129: 246.38612 | K129: 240.07375 | L129: 244.17548 | M129: 243.44691 | N129: 265.87773 | O129: 253.80544
... B141: Promedio | C141: 164.3594 | D141: 159.93894 | E141: 172.18511 | F141: 186.49142 | G141: 175.84416 | H141: 171.008 | I141: 168.3513 | J141: 161.24416 | K141: 165.73797 | L141: 162.12158 | M141: 157.37133 | N141: 163.22573 | O141: 165.9048
B168: 2.4 Resumen Anual de Transacciones, Monto de Retiros y Monto Promedio de Retiros de Dinero por Entidad Financiera
B170: Entidad Financiera | C170: Transacciones | D170: Monto de Retiros (USD) | E170: Monto promedio de Retiros (USD) | F170: % Transacciones | G170: % Monto de Retiros
B171: Banco Pichincha | C171: 88679955 | D171: 1.5894634e+10 | E171: 179.23593 | F171: 0.43070264 | G171: 0.46531137
B172: Banco de Guayaquil | C172: 36298639 | D172: 3.9493701e+09 | E172: 108.80215 | F172: 0.17629598 | G172: 0.1156168
B173: Banco del Pacífico | C173: 28051848 | D173: 3.5547302e+09 | E173: 126.72 | F173: 0.1362428 | G173: 0.10406382
B174: Banco Produbanco Grupo Promerica | C174: 13078512 | D174: 2.50579e+09 | E174: 191.59595 | F174: 0.063519988 | G174: 0.073356363
B175: Banco Bolivariano | C175: 13215192 | D175: 2.3706148e+09 | E175: 179.38557 | F175: 0.064183818 | G175: 0.069399145
B176: Banco Internacional | C176: 8347448 | D176: 1.3468723e+09 | E176: 161.35138 | F176: 0.040542058 | G176: 0.039429343
B177: Banco del Austro | C177: 5142739 | D177: 1.2801018e+09 | E177: 248.9144 | F177: 0.024977361 | G177: 0.037474654
B178: Banco de Machala | C178: 2817815 | D178: 7.8251984e+08 | E178: 277.70448 | F178: 0.013685622 | G178: 0.022908069
B179: Banco General Rumiñahui | C179: 2832379 | D179: 7.0781538e+08 | E179: 249.90137 | F179: 0.013756357 | G179: 0.020721115
B180: Banco de Loja | C180: 3588622 | D180: 5.2194946e+08 | E180: 145.44565 | F180: 0.017429294 | G180: 0.015279937
B181: Banco Coopnacional | C181: 1024198 | D181: 319938351 | E181: 312.37939 | F181: 0.0049743461 | G181: 0.0093661137
B182: Servipagos | C182: 960769 | D182: 2.9637344e+08 | E182: 308.47523 | F182: 0.0046662828 | G182: 0.0086762569
... B194: Total | C194: 2.0589601e+08 | D194: 3.4159136e+10 | E194: 165.9048 | F194: 1 | G194: 1

Sheet SECCIÓN III
B1: SUPERINTENDENCIA DE BANCOS DEL ECUADOR INTENDENCIA NACIONAL DE RIESGOS Y ESTUDIOS DIRECCIÓN DE ESTUDIOS Y GESTIÓN DE LA INFORMACIÓN SUBDIRECCIÓN DE ESTADÍSTICAS Y ESTUDIOS
B3: ESTADÍSTICAS DE RETIROS DE DINERO EN EFECTIVO SOBRE CUENTAS DE AHORRO EN CANALES PROPIOS DE LA ENTIDAD
B4: Enero a Diciembre 2020
B5: Fecha de publicación: Enero 2021
B6: Datos Provisionales
B8: SECCIÓN III: RETIROS DE DINERO POR CANALES
B10: 3.1 Evolución de Transacciones de Retiros de Dinero por Canales
C11: 2 | D11: 3 | E11: 4 | F11: 5 | G11: 6 | H11: 7 | I11: 8 | J11: 9 | K11: 10 | L11: 11 | M11: 12 | N11: 13 | O11: 14 | P11: 15
B12: Canal | C12: Enero | D12: Febrero | E12: Marzo | F12: Abril | G12: Mayo | H12: Junio | I12: Julio | J12: Agosto | K12: Septiembre | L12: Octubre | M12: Noviembre | N12: Diciembre | O12: Total | P12: Promedio | Q12: % Número de Retiros
B13: Cajero Automático | C13: 15002936 | D13: 14474861 | E13: 11357557 | F13: 6585609 | G13: 8051740 | H13: 10170243 | I13: 11045419 | J13: 11519404 | K13: 11808526 | L13: 13009865 | M13: 12402841 | N13: 16622226 | O13: 1.4205123e+08 | P13: 11837602 | Q13: 0.68991734
B14: Cajero Automático Plus | C14: 1061580 | D14: 1030535 | E14: 823295 | F14: 563150 | G14: 718275 | H14: 811461 | I14: 883216 | J14: 937020 | K14: 1002649 | L14: 1126218 | M14: 1059601 | N14: 1390965 | O14: 11407965 | P14: 950663.75 | Q14: 0.055406441
B15: Cajero Automático Móvil | C15: 0 | D15: 0 | E15: 0 | F15: 0 | G15: 0 | H15: 0 | I15: 0 | J15: 0 | K15: 0 | L15: 0 | M15: 0 | N15: 0 | O15: 0 | P15: 0 | Q15: 0
B16: Corresponsal No Bancario | C16: 2421834 | D16: 2375742 | E16: 1844106 | F16: 1280021 | G16: 1589520 | H16: 2040228 | I16: 2275250 | J16: 2402410 | K16: 2496329 | L16: 2739326 | M16: 2628632 | N16: 3110279 | O16: 27203677 | P16: 2266973.1 | Q16: 0.13212338
B17: Oficina / Ventanilla | C17: 3025718 | D17: 2724380 | E17: 2086873 | F17: 1022373 | G17: 1285090 | H17: 1916952 | I17: 2075548 | J17: 2019533 | K17: 2202033 | L17: 2207342 | M17: 2043685 | N17: 2371113 | O17: 24980640 | P17: 2081720 | Q17: 0.12132649
B18: Ventanilla Compartida | C18: 32583 | D18: 30852 | E18: 23500 | F18: 13651 | G18: 14264 | H18: 18487 | I18: 18232 | J18: 19093 | K18: 19383 | L18: 20137 | M18: 17451 | N18: 24867 | O18: 252500 | P18: 21041.667 | Q18: 0.0012263472
B19: Total | C19: 21544651 | D19: 20636370 | E19: 16135331 | F19: 9464804 | G19: 11658889 | H19: 14957371 | I19: 16297665 | J19: 16897460 | K19: 17528920 | L19: 19102888 | M19: 18152210 | N19: 23519450 | O19: 2.0589601e+08 | P19: 17158001 | Q19: 1
B46: 3.2 Evolución del Monto de Retiros de Dinero por Canales
B47: (en dólares)
B48: Canal | C48: Enero | D48: Febrero | E48: Marzo | F48: Abril | G48: Mayo | H48: Junio | I48: Julio | J48: Agosto | K48: Septiembre | L48: Octubre | M48: Noviembre | N48: Diciembre | O48: Total | P48: Promedio | Q48: % Monto por Retiros
B49: Cajero Automático | C49: 1.4534694e+09 | D49: 1.4261195e+09 | E49: 1.2377401e+09 | F49: 842212955 | G49: 9.8786582e+08 | H49: 1.1226309e+09 | I49: 1.2018758e+09 | J49: 1.2467402e+09 | K49: 1.2555665e+09 | L49: 1.3760303e+09 | M49: 1.2819948e+09 | N49: 1.9249981e+09 | O49: 1.5357244e+10 | P49: 1.2797704e+09 | Q49: 0.44957941
B50: Cajero Automático Plus | C50: 95000696 | D50: 94021679 | E50: 83379548 | F50: 66082994 | G50: 80328002 | H50: 83171203 | I50: 88145573 | J50: 92139606 | K50: 98064237 | L50: 1.1069605e+08 | M50: 1.0119057e+08 | N50: 1.502027e+08 | O50: 1.1424229e+09 | P50: 95201904 | Q50: 0.033444138
B51: Cajero Automático Móvil | C51: 0 | D51: 0 | E51: 0 | F51: 0 | G51: 0 | H51: 0 | I51: 0 | J51: 0 | K51: 0 | L51: 0 | M51: 0 | N51: 0 | O51: 0 | P51: 0 | Q51: 0
B52: Corresponsal No Bancario | C52: 1.5992788e+08 | D52: 1.5999948e+08 | E52: 1.3218417e+08 | F52: 99828259 | G52: 1.299024e+08 | H52: 1.5647305e+08 | I52: 1.7358102e+08 | J52: 1.8170907e+08 | K52: 1.8711822e+08 | L52: 2.0620502e+08 | M52: 1.9293653e+08 | N52: 2.5373734e+08 | O52: 2.0336024e+09 | P52: 1.6946687e+08 | Q52: 0.059533193
B53: Oficina / Ventanilla | C53: 1.8137305e+09 | D53: 1.6017557e+09 | E53: 1.3107494e+09 | F53: 7.4850412e+08 | G53: 8.4366399e+08 | H53: 1.1853988e+09 | I53: 1.2698526e+09 | J53: 1.1938063e+09 | K53: 1.3529683e+09 | L53: 1.3925326e+09 | M53: 1.2706155e+09 | N53: 1.4945447e+09 | O53: 1.5478123e+10 | P53: 1.2898436e+09 | Q53: 0.4531181
B54: Ventanilla Compartida | C54: 18937416 | D54: 18662824 | E54: 14210551 | F54: 8476438.3 | G54: 8387358.9 | H54: 10156050 | I54: 10278070 | J54: 10221517 | K54: 11490424 | L54: 11526369 | M54: 9899970.6 | N54: 15496688 | O54: 1.4774368e+08 | P54: 12311973 | Q54: 0.0043251585
B55: Total | C55: 3.5410659e+09 | D55: 3.3005592e+09 | E55: 2.7782638e+09 | F55: 1.7651048e+09 | G55: 2.0501476e+09 | H55: 2.55783e+09 | I55: 2.7437331e+09 | J55: 2.7246167e+09 | K55: 2.9052076e+09 | L55: 3.0969903e+09 | M55: 2.8566374e+09 | N55: 3.8389795e+09 | O55: 3.4159136e+10 | P55: 2.8465947e+09 | Q55: 1
B83: 3.3 Evolución del Monto Promedio de Retiros de Dinero por Canales
B84: (en dólares)
B85: Canal | C85: Enero | D85: Febrero | E85: Marzo | F85: Abril | G85: Mayo | H85: Junio | I85: Julio | J85: Agosto | K85: Septiembre | L85: Octubre | M85: Noviembre | N85: Diciembre | O85: Promedio
B86: Cajero Automático | C86: 96.879 | D86: 98.523882 | E86: 108.97943 | F86: 127.88688 | G86: 122.68973 | H86: 110.38388 | I86: 108.81215 | J86: 108.22957 | K86: 106.32711 | L86: 105.76822 | M86: 103.36299 | N86: 115.80868 | O86: 108.11061
B87: Cajero Automático Plus | C87: 89.489907 | D87: 91.235794 | E87: 101.27542 | F87: 117.34528 | G87: 111.83461 | H87: 102.49563 | I87: 99.800698 | J87: 98.332592 | K87: 97.805151 | L87: 98.29007 | M87: 95.498752 | N87: 107.98453 | O87: 100.14256
B88: Cajero Automático Móvil
B89: Corresponsal No Bancario | C89: 66.035854 | D89: 67.347159 | E89: 71.67927 | F89: 77.989548 | G89: 81.724293 | H89: 76.693903 | I89: 76.290965 | J89: 75.636163 | K89: 74.957354 | L89: 75.275823 | M89: 73.398077 | N89: 81.580252 | O89: 74.75469
B90: Oficina / Ventanilla | C90: 599.43805 | D90: 587.93403 | E90: 628.09257 | F90: 732.1243 | G90: 656.50187 | H90: 618.3769 | I90: 611.81558 | J90: 591.12989 | K90: 614.41782 | L90: 630.86401 | M90: 621.72769 | N90: 630.31357 | O90: 619.60473
B91: Ventanilla Compartida | C91: 581.20541 | D91: 604.91455 | E91: 604.70431 | F91: 620.939 | G91: 588.0089 | H91: 549.36169 | I91: 563.73796 | J91: 535.35417 | K91: 592.80936 | L91: 572.39753 | M91: 567.30105 | N91: 623.18287 | O91: 585.12347
B92: Promedio | C92: 164.3594 | D92: 159.93894 | E92: 172.18511 | F92: 186.49142 | G92: 175.84416 | H92: 171.008 | I92: 168.3513 | J92: 161.24416 | K92: 165.73797 | L92: 162.12158 | M92: 157.37133 | N92: 163.22573 | O92: 165.9048
B119: 3.4 Resumen Anual de Transacciones, Monto de Retiros y Monto Promedio de Retiros de Dinero por Canales
B121: Canal | C121: Transacciones | D121: Monto de Retiros (USD) | E121: Monto promedio de Retiros (USD) | F121: % Transacciones | G121: % Monto de Retiros
B122: Cajero Automático | C122: 1.4205123e+08 | D122: 1.5357244e+10 | E122: 108.11061 | F122: 0.68991734 | G122: 0.44957941
B123: Cajero Automático Plus | C123: 11407965 | D123: 1.1424229e+09 | E123: 100.14256 | F123: 0.055406441 | G123: 0.033444138
B124: Cajero Automático Móvil | C124: 0 | D124: 0 | F124: 0 | G124: 0
B125: Corresponsal No Bancario | C125: 27203677 | D125: 2.0336024e+09 | E125: 74.75469 | F125: 0.13212338 | G125: 0.059533193
B126: Oficina / Ventanilla | C126: 24980640 | D126: 1.5478123e+10 | E126: 619.60473 | F126: 0.12132649 | G126: 0.4531181
B127: Ventanilla Compartida | C127: 252500 | D127: 1.4774368e+08 | E127: 585.12347 | F127: 0.0012263472 | G127: 0.0043251585
B128: Total | C128: 2.0589601e+08 | D128: 3.4159136e+10 | E128: 165.9048 | F128: 1 | G128: 1

Sheet SECCIÓN IV
B1: SUPERINTENDENCIA DE BANCOS DEL ECUADOR INTENDENCIA NACIONAL DE RIESGOS Y ESTUDIOS DIRECCIÓN DE ESTUDIOS Y GESTIÓN DE LA INFORMACIÓN SUBDIRECCIÓN DE ESTADÍSTICAS Y ESTUDIOS
B3: ESTADÍSTICAS DE RETIROS DE DINERO EN EFECTIVO SOBRE CUENTAS DE AHORRO EN CANALES PROPIOS DE LA ENTIDAD
B4: Enero a Diciembre 2020
B5: Fecha de publicación: Enero 2021
B6: Datos Provisionales
B8: SECCIÓN IV: RETIROS DE DINERO POR PROVINCIA
B10: 4.1 Evolución de Transacciones de Retiros de Dinero por Provincia
C11: 2 | D11: 3 | E11: 4 | F11: 5 | G11: 6 | H11: 7 | I11: 8 | J11: 9 | K11: 10 | L11: 11 | M11: 12 | N11: 13 | O11: 14 | P11: 15
B12: Provincia | C12: Enero | D12: Febrero | E12: Marzo | F12: Abril | G12: Mayo | H12: Junio | I12: Julio | J12: Agosto | K12: Septiembre | L12: Octubre | M12: Noviembre | N12: Diciembre | O12: Total | P12: Promedio | Q12: % Número de Retiros | BA12: Provincia | BB12: Enero | BC12: Febrero | BD12: Marzo | BE12: Abril | BF12: Mayo | BG12: Junio | BH12: Julio | BI12: Agosto | BJ12: Septiembre | BK12: Octubre | BL12: Noviembre | BM12: Diciembre | BN12: Total
B13: Guayas | C13: 6058163 | D13: 5662502 | E13: 4848238 | F13: 2957486 | G13: 3729841 | H13: 4735956 | I13: 4758919 | J13: 5073829 | K13: 4867620 | L13: 5655796 | M13: 5436233 | N13: 7023698 | O13: 60808281 | P13: 5067356.7 | Q13: 0.29533492 | BA13: Pichincha | BB13: 6732235 | BC13: 6434319 | BD13: 4661672 | BE13: 2551993 | BF13: 3052886 | BG13: 4122566 | BH13: 4517047 | BI13: 4907754 | BJ13: 5063423 | BK13: 5537827 | BL13: 5273107 | BM13: 7006925 | BN13: 59861754
B14: Pichincha | C14: 6732235 | D14: 6434319 | E14: 4661672 | F14: 2551993 | G14: 3052886 | H14: 4122566 | I14: 4517047 | J14: 4907754 | K14: 5063423 | L14: 5537827 | M14: 5273107 | N14: 7006925 | O14: 59861754 | P14: 4988479.5 | Q14: 0.29073781 | BA14: Guayas | BB14: 6058163 | BC14: 5662502 | BD14: 4848238 | BE14: 2957486 | BF14: 3729841 | BG14: 4735956 | BH14: 4758919 | BI14: 5073829 | BJ14: 4867620 | BK14: 5655796 | BL14: 5436233 | BM14: 7023698 | BN14: 60808281
B15: Manabí | C15: 1342389 | D15: 1316127 | E15: 1066040 | F15: 649353 | G15: 766840 | H15: 932156 | I15: 1050660 | J15: 1069112 | K15: 1119359 | L15: 1271446 | M15: 1170223 | N15: 1513608 | O15: 13267313 | P15: 1105609.4 | Q15: 0.064436961 | BA15: Manabí | BB15: 1342389 | BC15: 1316127 | BD15: 1066040 | BE15: 649353 | BF15: 766840 | BG15: 932156 | BH15: 1050660 | BI15: 1069112 | BJ15: 1119359 | BK15: 1271446 | BL15: 1170223 | BM15: 1513608 | BN15: 13267313
B16: Los Ríos | C16: 875193 | D16: 847885 | E16: 748356 | F16: 500919 | G16: 602591 | H16: 709896 | I16: 755673 | J16: 761873 | K16: 772070 | L16: 862832 | M16: 816487 | N16: 1049298 | O16: 9303073 | P16: 775256.08 | Q16: 0.045183358 | BA16: Los Ríos | BB16: 875193 | BC16: 847885 | BD16: 748356 | BE16: 500919 | BF16: 602591 | BG16: 709896 | BH16: 755673 | BI16: 761873 | BJ16: 772070 | BK16: 862832 | BL16: 816487 | BM16: 1049298 | BN16: 9303073
B17: Santo Domingo de los Tsáchilas | C17: 719587 | D17: 708088 | E17: 548445 | F17: 317816 | G17: 412404 | H17: 535366 | I17: 575893 | J17: 594287 | K17: 621432 | L17: 699115 | M17: 719455 | N17: 820175 | O17: 7272063 | P17: 606005.25 | Q17: 0.035319106 | BA17: Azuay | BB17: 690165 | BC17: 645366 | BD17: 465133 | BE17: 257995 | BF17: 337683 | BG17: 442041 | BH17: 889205 | BI17: 505276 | BJ17: 945978 | BK17: 567679 | BL17: 539657 | BM17: 686016 | BN17: 6972194
B18: Azuay | C18: 690165 | D18: 645366 | E18: 465133 | F18: 257995 | G18: 337683 | H18: 442041 | I18: 889205 | J18: 505276 | K18: 945978 | L18: 567679 | M18: 539657 | N18: 686016 | O18: 6972194 | P18: 581016.17 | Q18: 0.033862696 | BA18: Resto de Provincias | BB18: 5846506 | BC18: 5730171 | BD18: 4345892 | BE18: 2547058 | BF18: 3169048 | BG18: 4014756 | BH18: 4326161 | BI18: 4579616 | BJ18: 4760470 | BK18: 5207308 | BL18: 4916503 | BM18: 6239905 | BN18: 55683394
B19: El Oro | C19: 647936 | D19: 626072 | E19: 517041 | F19: 297970 | G19: 374257 | H19: 474121 | I19: 506170 | J19: 519297 | K19: 538446 | L19: 595078 | M19: 572484 | N19: 709357 | O19: 6378229 | P19: 531519.08 | Q19: 0.030977915 | BA19: El Oro | BB19: 647936 | BC19: 626072 | BD19: 517041 | BE19: 297970 | BF19: 374257 | BG19: 474121 | BH19: 506170 | BI19: 519297 | BJ19: 538446 | BK19: 595078 | BL19: 572484 | BM19: 709357 | BN19: 6378229
B20: Tungurahua | C20: 617685 | D20: 601224 | E20: 423257 | F20: 226715 | G20: 297430 | H20: 391537 | I20: 409535 | J20: 454946 | K20: 468454 | L20: 518029 | M20: 497733 | N20: 664379 | O20: 5570924 | P20: 464243.67 | Q20: 0.027056979 | BA20: Santo Domingo de los Tsáchilas | BB20: 719587 | BC20: 708088 | BD20: 548445 | BE20: 317816 | BF20: 412404 | BG20: 535366 | BH20: 575893 | BI20: 594287 | BJ20: 621432 | BK20: 699115 | BL20: 719455 | BM20: 820175 | BN20: 7272063
B21: Esmeraldas | C21: 493574 | D21: 507635 | E21: 419237 | F21: 286848 | G21: 329521 | H21: 378501 | I21: 410200 | J21: 420072 | K21: 436884 | L21: 507628 | M21: 410855 | N21: 619067 | O21: 5220022 | P21: 435001.83 | Q21: 0.025352711 | BA21: Tungurahua | BB21: 617685 | BC21: 601224 | BD21: 423257 | BE21: 226715 | BF21: 297430 | BG21: 391537 | BH21: 409535 | BI21: 454946 | BJ21: 468454 | BK21: 518029 | BL21: 497733 | BM21: 664379 | BN21: 5570924
B22: Imbabura | C22: 506634 | D22: 501899 | E22: 358695 | F22: 196471 | G22: 242730 | H22: 326442 | I22: 365851 | J22: 397664 | K22: 405608 | L22: 444642 | M22: 422604 | N22: 539464 | O22: 4708704 | P22: 392392 | Q22: 0.022869331 | BA22: Imbabura | BB22: 506634 | BC22: 501899 | BD22: 358695 | BE22: 196471 | BF22: 242730 | BG22: 326442 | BH22: 365851 | BI22: 397664 | BJ22: 405608 | BK22: 444642 | BL22: 422604 | BM22: 539464 | BN22: 4708704
B23: Loja | C23: 533341 | D23: 511170 | E23: 371037 | F23: 189783 | G23: 256979 | H23: 347149 | I23: 368559 | J23: 386613 | K23: 422650 | L23: 377664 | M23: 350771 | N23: 447245 | O23: 4562961 | P23: 380246.75 | Q23: 0.022161483 | BA23: Esmeraldas | BB23: 493574 | BC23: 507635 | BD23: 419237 | BE23: 286848 | BF23: 329521 | BG23: 378501 | BH23: 410200 | BI23: 420072 | BJ23: 436884 | BK23: 507628 | BL23: 410855 | BM23: 619067 | BN23: 5220022
B24: Chimborazo | C24: 419703 | D24: 405565 | E24: 269510 | F24: 151495 | G24: 194076 | H24: 257125 | I24: 258374 | J24: 292842 | K24: 282493 | L24: 330150 | M24: 312285 | N24: 393244 | O24: 3566862 | P24: 297238.5 | Q24: 0.017323609 | BA24: Loja | BB24: 533341 | BC24: 511170 | BD24: 371037 | BE24: 189783 | BF24: 256979 | BG24: 347149 | BH24: 368559 | BI24: 386613 | BJ24: 422650 | BK24: 377664 | BL24: 350771 | BM24: 447245 | BN24: 4562961
... B37: Total | C37: 21544651 | D37: 20636370 | E37: 16135331 | F37: 9464804 | G37: 11658889 | H37: 14957371 | I37: 16297665 | J37: 16897460 | K37: 17528920 | L37: 19102888 | M37: 18152210 | N37: 23519450 | O37: 205896009 | P37: 17158001 | Q37: 1 | BA37: Morona Santiago | BB37: 41796 | BC37: 40616 | BD37: 29784 | BE37: 17870 | BF37: 23395 | BG37: 28185 | BH37: 29980 | BI37: 33778 | BJ37: 33399 | BK37: 33046 | BL37: 31489 | BM37: 38224 | BN37: 381562
BA38: Total | BB38: 21544651 | BC38: 20636370 | BD38: 16135331 | BE38: 9464804 | BF38: 11658889 | BG38: 14957371 | BH38: 16297665 | BI38: 16897460 | BJ38: 17528920 | BK38: 19102888 | BL38: 18152210 | BM38: 23519450 | BN38: 205896009
B65: 4.2 Evolución del Monto de Retiros de Dinero por Provincia
B66: (en dólares)
B67: Provincia | C67: Enero | D67: Febrero | E67: Marzo | F67: Abril | G67: Mayo | H67: Junio | I67: Julio | J67: Agosto | K67: Septiembre | L67: Octubre | M67: Noviembre | N67: Diciembre | O67: Total | P67: Promedio | Q67: % Monto por Retiros | BA67: Provincia | BB67: Enero | BC67: Febrero | BD67: Marzo | BE67: Abril | BF67: Mayo | BG67: Junio | BH67: Julio | BI67: Agosto | BJ67: Septiembre | BK67: Octubre | BL67: Noviembre | BM67: Diciembre | BN67: Total
B68: Guayas | C68: 9.2307799e+08 | D68: 8.5208458e+08 | E68: 7.8346478e+08 | F68: 5.2255139e+08 | G68: 6.2279071e+08 | H68: 7.4457042e+08 | I68: 7.6205326e+08 | J68: 7.3648963e+08 | K68: 7.6949081e+08 | L68: 8.5350102e+08 | M68: 7.9747791e+08 | N68: 1.0985997e+09 | O68: 9.4661522e+09 | P68: 7.8884602e+08 | Q68: 0.27711919 | BA68: Pichincha | BB68: 9.605419e+08 | BC68: 8.9905296e+08 | BD68: 7.0442296e+08 | BE68: 4.4008663e+08 | BF68: 4.8130572e+08 | BG68: 6.1225094e+08 | BH68: 6.5258259e+08 | BI68: 6.9333189e+08 | BJ68: 7.1881336e+08 | BK68: 7.6905379e+08 | BL68: 7.1206307e+08 | BM68: 9.8057847e+08 | BN68: 8.6240843e+09
B69: Pichincha | C69: 9.605419e+08 | D69: 8.9905296e+08 | E69: 7.0442296e+08 | F69: 4.4008663e+08 | G69: 4.8130572e+08 | H69: 6.1225094e+08 | I69: 6.5258259e+08 | J69: 6.9333189e+08 | K69: 7.1881336e+08 | L69: 7.6905379e+08 | M69: 7.1206307e+08 | N69: 9.8057847e+08 | O69: 8.6240843e+09 | P69: 7.1867369e+08 | Q69: 0.25246787 | BA69: Guayas | BB69: 9.2307799e+08 | BC69: 8.5208458e+08 | BD69: 7.8346478e+08 | BE69: 5.2255139e+08 | BF69: 6.2279071e+08 | BG69: 7.4457042e+08 | BH69: 7.6205326e+08 | BI69: 7.3648963e+08 | BJ69: 7.6949081e+08 | BK69: 8.5350102e+08 | BL69: 7.9747791e+08 | BM69: 1.0985997e+09 | BN69: 9.4661522e+09
B70: Manabí | C70: 2.2941528e+08 | D70: 2.1726446e+08 | E70: 1.8735575e+08 | F70: 1.1791145e+08 | G70: 1.39704e+08 | H70: 1.7268998e+08 | I70: 1.917471e+08 | J70: 1.8314506e+08 | K70: 1.9564428e+08 | L70: 2.1724303e+08 | M70: 1.9391673e+08 | N70: 2.6377827e+08 | O70: 2.3098154e+09 | P70: 1.9248462e+08 | Q70: 0.067619257 | BA70: Manabí | BB70: 2.2941528e+08 | BC70: 2.1726446e+08 | BD70: 1.8735575e+08 | BE70: 1.1791145e+08 | BF70: 1.39704e+08 | BG70: 1.7268998e+08 | BH70: 1.917471e+08 | BI70: 1.8314506e+08 | BJ70: 1.9564428e+08 | BK70: 2.1724303e+08 | BL70: 1.9391673e+08 | BM70: 2.6377827e+08 | BN70: 2.3098154e+09
B71: Azuay | C71: 1.6880606e+08 | D71: 1.5787865e+08 | E71: 1.1995637e+08 | F71: 74015293 | G71: 84732247 | H71: 1.133051e+08 | I71: 1.5075109e+08 | J71: 1.2817287e+08 | K71: 1.5944355e+08 | L71: 1.4126145e+08 | M71: 1.30207e+08 | N71: 1.6204825e+08 | O71: 1.5905779e+09 | P71: 1.3254816e+08 | Q71: 0.046563763 | BA71: Los Ríos | BB71: 1.4524556e+08 | BC71: 1.3617189e+08 | BD71: 1.2467206e+08 | BE71: 84743302 | BF71: 1.0180494e+08 | BG71: 1.2639505e+08 | BH71: 1.2980802e+08 | BI71: 1.2383319e+08 | BJ71: 1.3116252e+08 | BK71: 1.4497984e+08 | BL71: 1.3467316e+08 | BM71: 1.8032839e+08 | BN71: 1.5638179e+09
B72: Los Ríos | C72: 1.4524556e+08 | D72: 1.3617189e+08 | E72: 1.2467206e+08 | F72: 84743302 | G72: 1.0180494e+08 | H72: 1.2639505e+08 | I72: 1.2980802e+08 | J72: 1.2383319e+08 | K72: 1.3116252e+08 | L72: 1.4497984e+08 | M72: 1.3467316e+08 | N72: 1.8032839e+08 | O72: 1.5638179e+09 | P72: 1.3031816e+08 | Q72: 0.045780371 | BA72: Azuay | BB72: 1.6880606e+08 | BC72: 1.5787865e+08 | BD72: 1.1995637e+08 | BE72: 74015293 | BF72: 84732247 | BG72: 1.133051e+08 | BH72: 1.5075109e+08 | BI72: 1.2817287e+08 | BJ72: 1.5944355e+08 | BK72: 1.4126145e+08 | BL72: 1.30207e+08 | BM72: 1.6204825e+08 | BN72: 1.5905779e+09
B73: El Oro | C73: 1.6032168e+08 | D73: 1.4506822e+08 | E73: 1.2886033e+08 | F73: 79049263 | G73: 91973016 | H73: 1.1328837e+08 | I73: 1.2523801e+08 | J73: 1.2027492e+08 | K73: 1.3068392e+08 | L73: 1.4078513e+08 | M73: 1.2938463e+08 | N73: 1.6969613e+08 | O73: 1.5346236e+09 | P73: 1.278853e+08 | Q73: 0.044925715 | BA73: Resto de Provincias | BB73: 1.1139791e+09 | BC73: 1.0381067e+09 | BD73: 8.5839183e+08 | BE73: 5.2579671e+08 | BF73: 6.1980995e+08 | BG73: 7.8861855e+08 | BH73: 8.5679101e+08 | BI73: 8.5964406e+08 | BJ73: 9.3065313e+08 | BK73: 9.7095118e+08 | BL73: 8.8829954e+08 | BM73: 1.1536464e+09 | BN73: 1.0604688e+10
B74: Santo Domingo de los Tsáchilas | C74: 1.1651702e+08 | D74: 1.1129202e+08 | E74: 91441944 | F74: 53930939 | G74: 65270382 | H74: 87074291 | I74: 93289726 | J74: 92428070 | K74: 1.0103065e+08 | L74: 1.1142693e+08 | M74: 1.0752305e+08 | N74: 1.2635123e+08 | O74: 1.1575762e+09 | P74: 96464687 | Q74: 0.03388775 | BA74: El Oro | BB74: 1.6032168e+08 | BC74: 1.4506822e+08 | BD74: 1.2886033e+08 | BE74: 79049263 | BF74: 91973016 | BG74: 1.1328837e+08 | BH74: 1.2523801e+08 | BI74: 1.2027492e+08 | BJ74: 1.3068392e+08 | BK74: 1.4078513e+08 | BL74: 1.2938463e+08 | BM74: 1.6969613e+08 | BN74: 1.5346236e+09
B75: Tungurahua | C75: 1.2411986e+08 | D75: 1.1291764e+08 | E75: 90522882 | F75: 53650418 | G75: 62737295 | H75: 80032611 | I75: 86035264 | J75: 91774458 | K75: 95664941 | L75: 1.0222023e+08 | M75: 94916351 | N75: 1.2816876e+08 | O75: 1.1227607e+09 | P75: 93563392 | Q75: 0.032868534 | BA75: Santo Domingo de los Tsáchilas | BB75: 1.1651702e+08 | BC75: 1.1129202e+08 | BD75: 91441944 | BE75: 53930939 | BF75: 65270382 | BG75: 87074291 | BH75: 93289726 | BI75: 92428070 | BJ75: 1.0103065e+08 | BK75: 1.1142693e+08 | BL75: 1.0752305e+08 | BM75: 1.2635123e+08 | BN75: 1.1575762e+09
B76: Imbabura | C76: 95238118 | D76: 88654427 | E76: 69522113 | F76: 41511331 | G76: 47778289 | H76: 64123274 | I76: 71997027 | J76: 74456603 | K76: 79328229 | L76: 83735745 | M76: 76706054 | N76: 99663685 | O76: 8.9271489e+08 | P76: 74392908 | Q76: 0.026134001 | BA76: Tungurahua | BB76: 1.2411986e+08 | BC76: 1.1291764e+08 | BD76: 90522882 | BE76: 53650418 | BF76: 62737295 | BG76: 80032611 | BH76: 86035264 | BI76: 91774458 | BJ76: 95664941 | BK76: 1.0222023e+08 | BL76: 94916351 | BM76: 1.2816876e+08 | BN76: 1.1227607e+09
B77: Esmeraldas | C77: 74612793 | D77: 74272460 | E77: 63858519 | F77: 43623251 | G77: 52954378 | H77: 61605694 | I77: 64205966 | J77: 62930107 | K77: 67500422 | L77: 78362839 | M77: 64622533 | N77: 97826066 | O77: 8.0637503e+08 | P77: 67197919 | Q77: 0.023606424 | BA77: Imbabura | BB77: 95238118 | BC77: 88654427 | BD77: 69522113 | BE77: 41511331 | BF77: 47778289 | BG77: 64123274 | BH77: 71997027 | BI77: 74456603 | BJ77: 79328229 | BK77: 83735745 | BL77: 76706054 | BM77: 99663685 | BN77: 8.9271489e+08
B78: Loja | C78: 97655544 | D78: 91119142 | E78: 73177235 | F78: 39200584 | G78: 45637626 | H78: 63783777 | I78: 69282264 | J78: 66665724 | K78: 74895139 | L78: 51014331 | M78: 47718782 | N78: 65086571 | O78: 7.8523672e+08 | P78: 65436393 | Q78: 0.022987605 | BA78: Esmeraldas | BB78: 74612793 | BC78: 74272460 | BD78: 63858519 | BE78: 43623251 | BF78: 52954378 | BG78: 61605694 | BH78: 64205966 | BI78: 62930107 | BJ78: 67500422 | BK78: 78362839 | BL78: 64622533 | BM78: 97826066 | BN78: 8.0637503e+08
B79: Cotopaxi | C79: 74803759 | D79: 69557103 | E79: 58545478 | F79: 35856320 | G79: 40321810 | H79: 50296561 | I79: 57250838 | J79: 59741802 | K79: 63647744 | L79: 70714252 | M79: 63180121 | N79: 82274160 | O79: 7.2618995e+08 | P79: 60515829 | Q79: 0.021259026 | BA79: Loja | BB79: 97655544 | BC79: 91119142 | BD79: 73177235 | BE79: 39200584 | BF79: 45637626 | BG79: 63783777 | BH79: 69282264 | BI79: 66665724 | BJ79: 74895139 | BK79: 51014331 | BL79: 47718782 | BM79: 65086571 | BN79: 7.8523672e+08
... B92: Total | C92: 3.5410659e+09 | D92: 3.3005592e+09 | E92: 2.7782638e+09 | F92: 1.7651048e+09 | G92: 2.0501476e+09 | H92: 2.55783e+09 | I92: 2.7437331e+09 | J92: 2.7246167e+09 | K92: 2.9052076e+09 | L92: 3.0969903e+09 | M92: 2.8566374e+09 | N92: 3.8389795e+09 | O92: 3.4159136e+10 | P92: 2.8465947e+09 | Q92: 1 | BA92: Morona Santiago | BB92: 9410213.4 | BC92: 8839599.2 | BD92: 6801497.5 | BE92: 4140721.2 | BF92: 4728972 | BG92: 6414356.3 | BH92: 7328273.7 | BI92: 7697581.8 | BJ92: 8743973.9 | BK92: 7857176.7 | BL92: 7544074.9 | BM92: 8869788.1 | BN92: 88376229
BA93: Total | BB93: 3.5410659e+09 | BC93: 3.3005592e+09 | BD93: 2.7782638e+09 | BE93: 1.7651048e+09 | BF93: 2.0501476e+09 | BG93: 2.55783e+09 | BH93: 2.7437331e+09 | BI93: 2.7246167e+09 | BJ93: 2.9052076e+09 | BK93: 3.0969903e+09 | BL93: 2.8566374e+09 | BM93: 3.8389795e+09 | BN93: 3.4159136e+10
B119: 4.3 Evolución del Monto Promedio de Retiros de Dinero por Provincia
B120: (en dólares)
B121: Provincia | C121: Enero | D121: Febrero | E121: Marzo | F121: Abril | G121: Mayo | H121: Junio | I121: Julio | J121: Agosto | K121: Septiembre | L121: Octubre | M121: Noviembre | N121: Diciembre | O121: Promedio
B122: Cañar | C122: 295.36349 | D122: 278.41416 | E122: 295.82412 | F122: 284.77141 | G122: 288.42895 | H122: 303.90025 | I122: 306.27864 | J122: 294.6976 | K122: 323.83108 | L122: 296.85816 | M122: 295.77984 | N122: 301.55851 | O122: 297.65806
B123: Carchi | C123: 279.24749 | D123: 271.14135 | E123: 288.11528 | F123: 281.15867 | G123: 287.60435 | H123: 293.16386 | I123: 285.54773 | J123: 274.30098 | K123: 281.67652 | L123: 278.22931 | M123: 264.28278 | N123: 264.01532 | O123: 277.6731
B124: El Oro | C124: 247.43443 | D124: 231.71172 | E124: 249.22651 | F124: 265.29269 | G124: 245.74828 | H124: 238.94399 | I124: 247.42282 | J124: 231.61103 | K124: 242.70571 | L124: 236.58264 | M124: 226.00567 | N124: 239.22529 | O124: 240.6034
B125: Morona Santiago | C125: 225.14627 | D125: 217.63835 | E125: 228.36078 | F125: 231.71355 | G125: 202.13601 | H125: 227.5805 | I125: 244.43875 | J125: 227.88743 | K125: 261.80346 | L125: 237.76483 | M125: 239.5781 | N125: 232.04762 | O125: 231.61695
B126: Bolívar | C126: 220.04158 | D126: 194.19935 | E126: 223.62717 | F126: 239.07581 | G126: 239.10104 | H126: 247.57769 | I126: 248.52871 | J126: 230.33007 | K126: 244.5623 | L126: 232.9833 | M126: 238.85913 | N126: 231.60379 | O126: 230.34231
B127: Azuay | C127: 244.58797 | D127: 244.63428 | E127: 257.89692 | F127: 286.88654 | G127: 250.92245 | H127: 256.3226 | I127: 169.53468 | J127: 253.66902 | K127: 168.54889 | L127: 248.84037 | M127: 241.27733 | N127: 236.21643 | O127: 228.13162
B128: Pastaza | C128: 203.19925 | D128: 195.94221 | E128: 217.29572 | F128: 218.15579 | G128: 205.0565 | H128: 232.3354 | I128: 230.18299 | J128: 228.22579 | K128: 237.78308 | L128: 241.58522 | M128: 218.23878 | N128: 201.01088 | O128: 218.34163
B129: Cotopaxi | C129: 200.31373 | D129: 194.49677 | E129: 214.82372 | F129: 217.68307 | G129: 202.61401 | H129: 203.72465 | I129: 211.90358 | J129: 199.15062 | K129: 212.0828 | L129: 206.53251 | M129: 200.10617 | N129: 205.31993 | O129: 204.94758
B130: Tungurahua | C130: 200.94362 | D130: 187.81292 | E130: 213.87214 | F130: 236.64256 | G130: 210.93129 | H130: 204.40625 | I130: 210.08037 | J130: 201.72605 | K130: 204.21416 | L130: 197.32531 | M130: 190.69732 | N130: 192.91513 | O130: 201.5394
B131: Chimborazo | C131: 176.79007 | D131: 168.53334 | E131: 200.28244 | F131: 200.65631 | G131: 194.82494 | H131: 191.84547 | I131: 203.07258 | J131: 189.74741 | K131: 209.53935 | L131: 193.64676 | M131: 186.05564 | N131: 191.43282 | O131: 190.25377
B132: Imbabura | C132: 187.98209 | D132: 176.63798 | E132: 193.81958 | F132: 211.28478 | G132: 196.83718 | H132: 196.43083 | I132: 196.7933 | J132: 187.23496 | K132: 195.57856 | L132: 188.32172 | M132: 181.50811 | N132: 184.74576 | O132: 189.58824
B133: Zamora Chinchipe | C133: 203.29467 | D133: 190.50479 | E133: 213.00399 | F133: 197.42395 | G133: 177.69886 | H133: 193.7211 | I133: 201.262 | J133: 212.15199 | K133: 212.16046 | L133: 154.3864 | M133: 161.22898 | N133: 152.46122 | O133: 188.44811
... B146: Promedio | C146: 164.3594 | D146: 159.93894 | E146: 172.18511 | F146: 186.49142 | G146: 175.84416 | H146: 171.008 | I146: 168.3513 | J146: 161.24416 | K146: 165.73797 | L146: 162.12158 | M146: 157.37133 | N146: 163.22573 | O146: 165.9048
B173: 4.4 Resumen Anual de Transacciones, Monto de Retiros y Monto Promedio de Retiros de Dinero por Provincia
B175: Provincia | C175: Transacciones | D175: Monto de Retiros (USD) | E175: Monto promedio de Retiros (USD) | F175: % Transacciones | G175: % Monto de Retiros
B176: Guayas | C176: 60808281 | D176: 9.4661522e+09 | E176: 155.67209 | F176: 0.29533492 | G176: 0.27711919
B177: Pichincha | C177: 59861754 | D177: 8.6240843e+09 | E177: 144.06668 | F177: 0.29073781 | G177: 0.25246787
B178: Manabí | C178: 13267313 | D178: 2.3098154e+09 | E178: 174.09821 | F178: 0.064436961 | G178: 0.067619257
B179: Azuay | C179: 6972194 | D179: 1.5905779e+09 | E179: 228.13162 | F179: 0.033862696 | G179: 0.046563763
B180: Los Ríos | C180: 9303073 | D180: 1.5638179e+09 | E180: 168.09692 | F180: 0.045183358 | G180: 0.045780371
B181: El Oro | C181: 6378229 | D181: 1.5346236e+09 | E181: 240.6034 | F181: 0.030977915 | G181: 0.044925715
B182: Santo Domingo de los Tsáchilas | C182: 7272063 | D182: 1.1575762e+09 | E182: 159.18127 | F182: 0.035319106 | G182: 0.03388775
B183: Tungurahua | C183: 5570924 | D183: 1.1227607e+09 | E183: 201.5394 | F183: 0.027056979 | G183: 0.032868534
B184: Imbabura | C184: 4708704 | D184: 8.9271489e+08 | E184: 189.58824 | F184: 0.022869331 | G184: 0.026134001
B185: Esmeraldas | C185: 5220022 | D185: 8.0637503e+08 | E185: 154.47732 | F185: 0.025352711 | G185: 0.023606424
B186: Loja | C186: 4562961 | D186: 7.8523672e+08 | E186: 172.08929 | F186: 0.022161483 | G186: 0.022987605
B187: Cotopaxi | C187: 3543296 | D187: 7.2618995e+08 | E187: 204.94758 | F187: 0.017209153 | G187: 0.021259026
... B200: Total | C200: 205896009 | D200: 3.4159136e+10 | E200: 165.9048 | F200: 1 | G200: 1

Sheet SECCIÓN V
B1: SUPERINTENDENCIA DE BANCOS DEL ECUADOR INTENDENCIA NACIONAL DE RIESGOS Y ESTUDIOS DIRECCIÓN DE ESTUDIOS Y GESTIÓN DE LA INFORMACIÓN SUBDIRECCIÓN DE ESTADÍSTICAS Y ESTUDIOS
B3: ESTADÍSTICAS DE RETIROS DE DINERO EN EFECTIVO SOBRE CUENTAS DE AHORRO EN CANALES PROPIOS DE LA ENTIDAD
B4: Enero a Diciembre 2020
B5: Fecha de publicación: Enero 2021
B6: Datos Provisionales
B8: SECCIÓN V: RETIROS DE DINERO POR ORDENANTE
B10: 5.1 Evolución de Transacciones de Retiros de Dinero por Ordenante
C11: 2 | D11: 3 | E11: 4 | F11: 5 | G11: 6 | H11: 7 | I11: 8 | J11: 9 | K11: 10 | L11: 11 | M11: 12 | N11: 13 | O11: 14 | P11: 15
B12: Ordenante | C12: Enero | D12: Febrero | E12: Marzo | F12: Abril | G12: Mayo | H12: Junio | I12: Julio | J12: Agosto | K12: Septiembre | L12: Octubre | M12: Noviembre | N12: Diciembre | O12: Total | P12: Promedio | Q12: % Número de Retiros
B13: Cliente | C13: 17679553 | D13: 16895758 | E13: 13097222 | F13: 7388107 | G13: 9250158 | H13: 12285130 | I13: 13511892 | J13: 13981104 | K13: 14548346 | L13: 15919023 | M13: 15096410 | N13: 19525958 | O13: 1.6917866e+08 | P13: 26723147 | Q13: 0.82167042
B14: Usuario | C14: 3865098 | D14: 3740612 | E14: 3038109 | F14: 2076697 | G14: 2408731 | H14: 2672241 | I14: 2785773 | J14: 2916356 | K14: 2980574 | L14: 3183865 | M14: 3055800 | N14: 3993492 | O14: 36717348 | P14: 5797466.5 | Q14: 0.17832958
B15: Total | C15: 21544651 | D15: 20636370 | E15: 16135331 | F15: 9464804 | G15: 11658889 | H15: 14957371 | I15: 16297665 | J15: 16897460 | K15: 17528920 | L15: 19102888 | M15: 18152210 | N15: 23519450 | O15: 2.0589601e+08 | P15: 17158001 | Q15: 1
B42: 5.2 Evolución del Monto de Retiros de Dinero por Ordenante
B43: (en dólares)
B44: Ordenante | C44: Enero | D44: Febrero | E44: Marzo | F44: Abril | G44: Mayo | H44: Junio | I44: Julio | J44: Agosto | K44: Septiembre | L44: Octubre | M44: Noviembre | N44: Diciembre | O44: Total | P44: Promedio | Q44: % Monto por Retiros
B45: Cliente | C45: 3.2387952e+09 | D45: 3.0041571e+09 | E45: 2.5338962e+09 | F45: 1.5901337e+09 | G45: 1.8491564e+09 | H45: 2.3365791e+09 | I45: 2.51538e+09 | J45: 2.4892128e+09 | K45: 2.6656004e+09 | L45: 2.8436019e+09 | M45: 2.6206734e+09 | N45: 3.5059113e+09 | O45: 3.1193097e+10 | P45: 4.92895e+09 | Q45: 0.91316998
B46: Usuario | C46: 3.0227071e+08 | D46: 2.9640212e+08 | E46: 2.4436758e+08 | F46: 1.7497105e+08 | G46: 2.009912e+08 | H46: 2.2125092e+08 | I46: 2.2835304e+08 | J46: 2.3540386e+08 | K46: 2.3960728e+08 | L46: 2.5338836e+08 | M46: 2.3596405e+08 | N46: 3.3306819e+08 | O46: 2.9660383e+09 | P46: 4.691505e+08 | Q46: 0.086830017
B47: Total | C47: 3.5410659e+09 | D47: 3.3005592e+09 | E47: 2.7782638e+09 | F47: 1.7651048e+09 | G47: 2.0501476e+09 | H47: 2.55783e+09 | I47: 2.7437331e+09 | J47: 2.7246167e+09 | K47: 2.9052076e+09 | L47: 3.0969903e+09 | M47: 2.8566374e+09 | N47: 3.8389795e+09 | O47: 3.4159136e+10 | P47: 2.8465947e+09 | Q47: 1
B74: 5.3 Evolución del Monto Promedio de Retiros de Dinero por Ordenante
B75: (en dólares)
B76: Ordenante | C76: Enero | D76: Febrero | E76: Marzo | F76: Abril | G76: Mayo | H76: Junio | I76: Julio | J76: Agosto | K76: Septiembre | L76: Octubre | M76: Noviembre | N76: Diciembre | O76: Promedio
B77: Cliente | C77: 183.19441 | D77: 177.8054 | E77: 193.46822 | F77: 215.22884 | G77: 199.90538 | H77: 190.19572 | I77: 186.16046 | J77: 178.04122 | K77: 183.2236 | L77: 178.62918 | M77: 173.5958 | N77: 179.55131 | O77: 184.37962
B78: Usuario | C78: 78.205186 | D78: 79.238937 | E78: 80.434105 | F78: 84.254493 | G78: 83.442775 | H78: 82.796021 | I78: 81.971157 | J78: 80.718492 | K78: 80.389643 | L78: 79.585147 | M78: 77.21842 | N78: 83.402743 | O78: 80.780299
B79: Promedio | C79: 164.3594 | D79: 159.93894 | E79: 172.18511 | F79: 186.49142 | G79: 175.84416 | H79: 171.008 | I79: 168.3513 | J79: 161.24416 | K79: 165.73797 | L79: 162.12158 | M79: 157.37133 | N79: 163.22573 | O79: 165.9048
B106: 5.4 Resumen Anual de Transacciones, Monto de Retiros y Monto Promedio de Retiros de Dinero por Ordenante
B108: Ordenante | C108: Transacciones | D108: Monto de Retiros (USD) | E108: Monto promedio de Retiros (USD) | F108: % Transacciones | G108: % Monto de Retiros
B109: Cliente | C109: 1.6917866e+08 | D109: 3.1193097e+10 | E109: 184.37962 | F109: 0.82167042 | G109: 0.91316998
B110: Usuario | C110: 36717348 | D110: 2.9660383e+09 | E110: 80.780299 | F110: 0.17832958 | G110: 0.086830017
B111: Total | C111: 2.0589601e+08 | D111: 3.4159136e+10 | E111: 165.9048 | F111: 1 | G111: 1

Sheet SECCIÓN VI
B1: SUPERINTENDENCIA DE BANCOS DEL ECUADOR INTENDENCIA NACIONAL DE RIESGOS Y ESTUDIOS DIRECCIÓN DE ESTUDIOS Y GESTIÓN DE LA INFORMACIÓN SUBDIRECCIÓN DE ESTADÍSTICAS Y ESTUDIOS
B3: ESTADÍSTICAS DE RETIROS DE DINERO EN EFECTIVO SOBRE CUENTAS DE AHORRO EN CANALES PROPIOS DE LA ENTIDAD
B4: Enero a Diciembre 2020
B5: Fecha de publicación: Enero 2021
B6: Datos Provisionales
B8: SECCIÓN VI: RETIROS DE DINERO POR ENTIDAD FINANCIERA POR CANAL
B10: 6.1 Evolución de Transacciones de Retiros de Dinero por Entidad Financiera por Canal
C11: 2 | D11: 3 | E11: 4 | F11: 5 | G11: 6 | H11: 7 | I11: 8 | J11: 9 | K11: 10 | L11: 11 | M11: 12 | N11: 13 | O11: 14 | P11: 15
B12: Entidad Financiera | C12: Canal | D12: Enero | E12: Febrero | F12: Marzo | G12: Abril | H12: Mayo | I12: Junio | J12: Julio | K12: Agosto | L12: Septiembre | M12: Octubre | N12: Noviembre | O12: Diciembre | P12: Total | Q12: Promedio | R12: % Número de retiros
B13: Banco Amazonas | C13: Cajero Automático | D13: 0 | E13: 0 | F13: 0 | G13: 0 | H13: 0 | I13: 0 | J13: 0 | K13: 0 | L13: 0 | M13: 0 | N13: 0 | O13: 0 | P13: 0 | Q13: 0 | R13: 0
C14: Cajero Automático Plus | D14: 0 | E14: 0 | F14: 0 | G14: 0 | H14: 0 | I14: 0 | J14: 0 | K14: 0 | L14: 0 | M14: 0 | N14: 0 | O14: 0 | P14: 0 | Q14: 0 | R14: 0
C15: Cajero Automático Móvil | D15: 0 | E15: 0 | F15: 0 | G15: 0 | H15: 0 | I15: 0 | J15: 0 | K15: 0 | L15: 0 | M15: 0 | N15: 0 | O15: 0 | P15: 0 | Q15: 0 | R15: 0
C16: Corresponsal No Bancario | D16: 0 | E16: 0 | F16: 0 | G16: 0 | H16: 0 | I16: 0 | J16: 0 | K16: 0 | L16: 0 | M16: 0 | N16: 0 | O16: 0 | P16: 0 | Q16: 0 | R16: 0
C17: Oficina / Ventanilla | D17: 2036 | E17: 1914 | F17: 1723 | G17: 851 | H17: 872 | I17: 1208 | J17: 1319 | K17: 1221 | L17: 1336 | M17: 1412 | N17: 1272 | O17: 1823 | P17: 16987 | Q17: 1415.5833 | R17: 1
C18: Ventanilla Compartida | D18: 0 | E18: 0 | F18: 0 | G18: 0 | H18: 0 | I18: 0 | J18: 0 | K18: 0 | L18: 0 | M18: 0 | N18: 0 | O18: 0 | P18: 0 | Q18: 0 | R18: 0
B19: Total Banco Amazonas | D19: 2036 | E19: 1914 | F19: 1723 | G19: 851 | H19: 872 | I19: 1208 | J19: 1319 | K19: 1221 | L19: 1336 | M19: 1412 | N19: 1272 | O19: 1823 | P19: 16987 | Q19: 1415.5833 | R19: 1
B21: Banco del Austro | C21: Cajero Automático | D21: 388387 | E21: 379169 | F21: 275868 | G21: 161908 | H21: 217194 | I21: 270614 | J21: 292843 | K21: 310683 | L21: 322736 | M21: 357166 | N21: 330832 | O21: 419660 | P21: 3727060 | Q21: 310588.33 | R21: 0.72472276
C22: Cajero Automático Plus | D22: 0 | E22: 0 | F22: 0 | G22: 0 | H22: 0 | I22: 0 | J22: 0 | K22: 0 | L22: 0 | M22: 0 | N22: 0 | O22: 0 | P22: 0 | Q22: 0 | R22: 0
C23: Cajero Automático Móvil | D23: 0 | E23: 0 | F23: 0 | G23: 0 | H23: 0 | I23: 0 | J23: 0 | K23: 0 | L23: 0 | M23: 0 | N23: 0 | O23: 0 | P23: 0 | Q23: 0 | R23: 0
C24: Corresponsal No Bancario | D24: 0 | E24: 0 | F24: 0 | G24: 0 | H24: 0 | I24: 0 | J24: 0 | K24: 0 | L24: 0 | M24: 0 | N24: 0 | O24: 0 | P24: 0 | Q24: 0 | R24: 0
C25: Oficina / Ventanilla | D25: 168107 | E25: 147178 | F25: 117227 | G25: 63556 | H25: 79383 | I25: 110521 | J25: 118862 | K25: 116001 | L25: 124512 | M25: 123219 | N25: 114598 | O25: 132515 | P25: 1415679 | Q25: 117973.25 | R25: 0.27527724
C26: Ventanilla Compartida | D26: 0 | E26: 0 | F26: 0 | G26: 0 | H26: 0 | I26: 0 | J26: 0 | K26: 0 | L26: 0 | M26: 0 | N26: 0 | O26: 0 | P26: 0 | Q26: 0 | R26: 0
B27: Total Banco del Austro | D27: 556494 | E27: 526347 | F27: 393095 | G27: 225464 | H27: 296577 | I27: 381135 | J27: 411705 | K27: 426684 | L27: 447248 | M27: 480385 | N27: 445430 | O27: 552175 | P27: 5142739 | Q27: 428561.58 | R27: 1
B29: Banco de Guayaquil | C29: Cajero Automático | D29: 2746872 | E29: 2535737 | F29: 2312275 | G29: 1376634 | H29: 1529917 | I29: 2013483 | J29: 2110763 | K29: 2184106 | L29: 2229879 | M29: 2404799 | N29: 2462548 | O29: 2943221 | P29: 26850234 | Q29: 2237519.5 | R29: 0.7397036
C30: Cajero Automático Plus | D30: 0 | E30: 0 | F30: 0 | G30: 0 | H30: 0 | I30: 0 | J30: 0 | K30: 0 | L30: 0 | M30: 0 | N30: 0 | O30: 0 | P30: 0 | Q30: 0 | R30: 0
C31: Cajero Automático Móvil | D31: 0 | E31: 0 | F31: 0 | G31: 0 | H31: 0 | I31: 0 | J31: 0 | K31: 0 | L31: 0 | M31: 0 | N31: 0 | O31: 0 | P31: 0 | Q31: 0 | R31: 0
C32: Corresponsal No Bancario | D32: 445072 | E32: 401838 | F32: 355645 | G32: 252913 | H32: 320652 | I32: 407803 | J32: 434999 | K32: 453562 | L32: 455235 | M32: 477467 | N32: 492093 | O32: 545903 | P32: 5043182 | Q32: 420265.17 | R32: 0.13893584
C33: Oficina / Ventanilla | D33: 444446 | E33: 401833 | F33: 344233 | G33: 209086 | H33: 259301 | I33: 343380 | J33: 377587 | K33: 380007 | L33: 405845 | M33: 385021 | N33: 383743 | O33: 470741 | P33: 4405223 | Q33: 367101.92 | R33: 0.12136056
C34: Ventanilla Compartida | D34: 0 | E34: 0 | F34: 0 | G34: 0 | H34: 0 | I34: 0 | J34: 0 | K34: 0 | L34: 0 | M34: 0 | N34: 0 | O34: 0 | P34: 0 | Q34: 0 | R34: 0
B35: Total Banco de Guayaquil | D35: 3636390 | E35: 3339408 | F35: 3012153 | G35: 1838633 | H35: 2109870 | I35: 2764666 | J35: 2923349 | K35: 3017675 | L35: 3090959 | M35: 3267287 | N35: 3338384 | O35: 3959865 | P35: 36298639 | Q35: 3024886.6 | R35: 1
B37: Banco Bolivariano | C37: Cajero Automático | D37: 1211451 | E37: 1091024 | F37: 1010233 | G37: 640891 | H37: 757126 | I37: 955910 | J37: 981690 | K37: 980955 | L37: 985840 | M37: 1026729 | N37: 1059209 | O37: 1267573 | P37: 11968631 | Q37: 997385.92 | R37: 0.90567212
C38: Cajero Automático Plus | D38: 0 | E38: 0 | F38: 0 | G38: 0 | H38: 0 | I38: 0 | J38: 0 | K38: 0 | L38: 0 | M38: 0 | N38: 0 | O38: 0 | P38: 0 | Q38: 0 | R38: 0
C39: Cajero Automático Móvil | D39: 0 | E39: 0 | F39: 0 | G39: 0 | H39: 0 | I39: 0 | J39: 0 | K39: 0 | L39: 0 | M39: 0 | N39: 0 | O39: 0 | P39: 0 | Q39: 0 | R39: 0
C40: Corresponsal No Bancario | D40: 24731 | E40: 22212 | F40: 21903 | G40: 15779 | H40: 15855 | I40: 20520 | J40: 21438 | K40: 22552 | L40: 22675 | M40: 25036 | N40: 26800 | O40: 33385 | P40: 272886 | Q40: 22740.5 | R40: 0.020649416
C41: Oficina / Ventanilla | D41: 114548 | E41: 101223 | F41: 81096 | G41: 36388 | H41: 48645 | I41: 75571 | J41: 81884 | K41: 77185 | L41: 84412 | M41: 87355 | N41: 81586 | O41: 103782 | P41: 973675 | Q41: 81139.583 | R41: 0.07367846
C42: Ventanilla Compartida | D42: 0 | E42: 0 | F42: 0 | G42: 0 | H42: 0 | I42: 0 | J42: 0 | K42: 0 | L42: 0 | M42: 0 | N42: 0 | O42: 0 | P42: 0 | Q42: 0 | R42: 0
B43: Total Banco Bolivariano | D43: 1350730 | E43: 1214459 | F43: 1113232 | G43: 693058 | H43: 821626 | I43: 1052001 | J43: 1085012 | K43: 1080692 | L43: 1092927 | M43: 1139120 | N43: 1167595 | O43: 1404740 | P43: 13215192 | Q43: 1101266 | R43: 1
B45: Citibank | C45: Cajero Automático | D45: 0 | E45: 0 | F45: 0 | G45: 0 | H45: 0 | I45: 0 | J45: 0 | K45: 0 | L45: 0 | M45: 0 | N45: 0 | O45: 0 | P45: 0 | Q45: 0
C46: Cajero Automático Plus | D46: 0 | E46: 0 | F46: 0 | G46: 0 | H46: 0 | I46: 0 | J46: 0 | K46: 0 | L46: 0 | M46: 0 | N46: 0 | O46: 0 | P46: 0 | Q46: 0
C47: Cajero Automático Móvil | D47: 0 | E47: 0 | F47: 0 | G47: 0 | H47: 0 | I47: 0 | J47: 0 | K47: 0 | L47: 0 | M47: 0 | N47: 0 | O47: 0 | P47: 0 | Q47: 0
C48: Corresponsal No Bancario | D48: 0 | E48: 0 | F48: 0 | G48: 0 | H48: 0 | I48: 0 | J48: 0 | K48: 0 | L48: 0 | M48: 0 | N48: 0 | O48: 0 | P48: 0 | Q48: 0
C49: Oficina / Ventanilla | D49: 0 | E49: 0 | F49: 0 | G49: 0 | H49: 0 | I49: 0 | J49: 0 | K49: 0 | L49: 0 | M49: 0 | N49: 0 | O49: 0 | P49: 0 | Q49: 0
C50: Ventanilla Compartida | D50: 0 | E50: 0 | F50: 0 | G50: 0 | H50: 0 | I50: 0 | J50: 0 | K50: 0 | L50: 0 | M50: 0 | N50: 0 | O50: 0 | P50: 0 | Q50: 0
B51: Total Banco Citibank | D51: 0 | E51: 0 | F51: 0 | G51: 0 | H51: 0 | I51: 0 | J51: 0 | K51: 0 | L51: 0 | M51: 0 | N51: 0 | O51: 0 | P51: 0 | Q51: 0
B53: Banco Comercial de Manabí | C53: Cajero Automático | D53: 25757 | E53: 23741 | F53: 23361 | G53: 14446 | H53: 18363 | I53: 19956 | J53: 20076 | K53: 17192 | L53: 20494 | M53: 22559 | N53: 21910 | O53: 27196 | P53: 255051 | Q53: 21254.25 | R53: 0.70345507
C54: Cajero Automático Plus | D54: 0 | E54: 0 | F54: 0 | G54: 0 | H54: 0 | I54: 0 | J54: 0 | K54: 0 | L54: 0 | M54: 0 | N54: 0 | O54: 0 | P54: 0 | Q54: 0 | R54: 0
C55: Cajero Automático Móvil | D55: 0 | E55: 0 | F55: 0 | G55: 0 | H55: 0 | I55: 0 | J55: 0 | K55: 0 | L55: 0 | M55: 0 | N55: 0 | O55: 0 | P55: 0 | Q55: 0 | R55: 0
C56: Corresponsal No Bancario | D56: 0 | E56: 0 | F56: 0 | G56: 0 | H56: 0 | I56: 0 | J56: 0 | K56: 0 | L56: 0 | M56: 0 | N56: 0 | O56: 0 | P56: 0 | Q56: 0 | R56: 0
C57: Oficina / Ventanilla | D57: 11231 | E57: 10520 | F57: 9305 | G57: 5194 | H57: 6357 | I57: 7952 | J57: 9026 | K57: 8309 | L57: 9173 | M57: 10169 | N57: 8723 | O57: 11559 | P57: 107518 | Q57: 8959.8333 | R57: 0.29654493
C58: Ventanilla Compartida | D58: 0 | E58: 0 | F58: 0 | G58: 0 | H58: 0 | I58: 0 | J58: 0 | K58: 0 | L58: 0 | M58: 0 | N58: 0 | O58: 0 | P58: 0 | Q58: 0 | R58: 0
B59: Total Banco Comercial de Manabí | D59: 36988 | E59: 34261 | F59: 32666 | G59: 19640 | H59: 24720 | I59: 27908 | J59: 29102 | K59: 25501 | L59: 29667 | M59: 32728 | N59: 30633 | O59: 38755 | P59: 362569 | Q59: 30214.083 | R59: 1
B61: Banco del Litoral | C61: Cajero Automático | D61: 0 | E61: 0 | F61: 0 | G61: 0 | H61: 0 | I61: 0 | J61: 0 | K61: 0 | L61: 0 | M61: 0 | N61: 0 | O61: 0 | P61: 0 | Q61: 0 | R61: 0
C62: Cajero Automático Plus | D62: 0 | E62: 0 | F62: 0 | G62: 0 | H62: 0 | I62: 0 | J62: 0 | K62: 0 | L62: 0 | M62: 0 | N62: 0 | O62: 0 | P62: 0 | Q62: 0 | R62: 0
C63: Cajero Automático Móvil | D63: 0 | E63: 0 | F63: 0 | G63: 0 | H63: 0 | I63: 0 | J63: 0 | K63: 0 | L63: 0 | M63: 0 | N63: 0 | O63: 0 | P63: 0 | Q63: 0 | R63: 0
C64: Corresponsal No Bancario | D64: 0 | E64: 0 | F64: 0 | G64: 0 | H64: 0 | I64: 0 | J64: 0 | K64: 0 | L64: 0 | M64: 0 | N64: 0 | O64: 0 | P64: 0 | Q64: 0 | R64: 0
C65: Oficina / Ventanilla | D65: 4419 | E65: 5836 | F65: 3555 | G65: 2276 | H65: 2738 | I65: 3561 | J65: 3942 | K65: 3364 | L65: 3464 | M65: 3862 | N65: 3307 | O65: 4578 | P65: 44902 | Q65: 3741.8333 | R65: 1
C66: Ventanilla Compartida | D66: 0 | E66: 0 | F66: 0 | G66: 0 | H66: 0 | I66: 0 | J66: 0 | K66: 0 | L66: 0 | M66: 0 | N66: 0 | O66: 0 | P66: 0 | Q66: 0 | R66: 0
B67: Total Banco del Litoral | D67: 4419 | E67: 5836 | F67: 3555 | G67: 2276 | H67: 2738 | I67: 3561 | J67: 3942 | K67: 3364 | L67: 3464 | M67: 3862 | N67: 3307 | O67: 4578 | P67: 44902 | Q67: 3741.8333 | R67: 1
B69: Banco General Rumiñahui | C69: Cajero Automático | D69: 216199 | E69: 210961 | F69: 166948 | G69: 122578 | H69: 154316 | I69: 158415 | J69: 167585 | K69: 183686 | L69: 194703 | M69: 211681 | N69: 177596 | O69: 257105 | P69: 2221773 | Q69: 185147.75 | R69: 0.78441939
C70: Cajero Automático Plus | D70: 0 | E70: 0 | F70: 0 | G70: 0 | H70: 0 | I70: 0 | J70: 0 | K70: 0 | L70: 0 | M70: 0 | N70: 0 | O70: 0 | P70: 0 | Q70: 0 | R70: 0
C71: Cajero Automático Móvil | D71: 0 | E71: 0 | F71: 0 | G71: 0 | H71: 0 | I71: 0 | J71: 0 | K71: 0 | L71: 0 | M71: 0 | N71: 0 | O71: 0 | P71: 0 | Q71: 0 | R71: 0
C72: Corresponsal No Bancario | D72: 0 | E72: 0 | F72: 0 | G72: 0 | H72: 0 | I72: 0 | J72: 0 | K72: 0 | L72: 0 | M72: 0 | N72: 0 | O72: 0 | P72: 0 | Q72: 0 | R72: 0
C73: Oficina / Ventanilla | D73: 73050 | E73: 64103 | F73: 51233 | G73: 25520 | H73: 28472 | I73: 41483 | J73: 45801 | K73: 47840 | L73: 54776 | M73: 56314 | N73: 48127 | O73: 70095 | P73: 606814 | Q73: 50567.833 | R73: 0.21424181
C74: Ventanilla Compartida | D74: 565 | E74: 461 | F74: 362 | G74: 181 | H74: 189 | I74: 229 | J74: 296 | K74: 242 | L74: 287 | M74: 322 | N74: 322 | O74: 336 | P74: 3792 | Q74: 316 | R74: 0.0013388039
B75: Total Banco General Rumiñahui | D75: 289814 | E75: 275525 | F75: 218543 | G75: 148279 | H75: 182977 | I75: 200127 | J75: 213682 | K75: 231768 | L75: 249766 | M75: 268317 | N75: 226045 | O75: 327536 | P75: 2832379 | Q75: 236031.58 | R75: 1
B77: Banco Internacional | C77: Cajero Automático | D77: 807074 | E77: 791484 | F77: 608309 | G77: 422568 | H77: 500450 | I77: 495452 | J77: 587407 | K77: 626087 | L77: 626987 | M77: 686825 | N77: 625452 | O77: 836946 | P77: 7615041 | Q77: 634586.75 | R77: 0.91225977
C78: Cajero Automático Plus | D78: 0 | E78: 0 | F78: 0 | G78: 0 | H78: 0 | I78: 0 | J78: 0 | K78: 0 | L78: 0 | M78: 0 | N78: 0 | O78: 0 | P78: 0 | Q78: 0 | R78: 0
C79: Cajero Automático Móvil | D79: 0 | E79: 0 | F79: 0 | G79: 0 | H79: 0 | I79: 0 | J79: 0 | K79: 0 | L79: 0 | M79: 0 | N79: 0 | O79: 0 | P79: 0 | Q79: 0 | R79: 0
C80: Corresponsal No Bancario | D80: 0 | E80: 0 | F80: 0 | G80: 0 | H80: 0 | I80: 0 | J80: 0 | K80: 0 | L80: 0 | M80: 0 | N80: 0 | O80: 0 | P80: 0 | Q80: 0 | R80: 0
C81: Oficina / Ventanilla | D81: 95921 | E81: 84720 | F81: 66649 | G81: 35463 | H81: 42193 | I81: 62308 | J81: 67825 | K81: 66138 | L81: 70782 | M81: 73218 | N81: 67190 | O81: 0 | P81: 732407 | Q81: 61033.917 | R81: 0.087740229
C82: Ventanilla Compartida | D82: 0 | E82: 0 | F82: 0 | G82: 0 | H82: 0 | I82: 0 | J82: 0 | K82: 0 | L82: 0 | M82: 0 | N82: 0 | O82: 0 | P82: 0 | Q82: 0 | R82: 0
B83: Total Banco Internacional | D83: 902995 | E83: 876204 | F83: 674958 | G83: 458031 | H83: 542643 | I83: 557760 | J83: 655232 | K83: 692225 | L83: 697769 | M83: 760043 | N83: 692642 | O83: 836946 | P83: 8347448 | Q83: 695620.67 | R83: 1
B85: Banco de Loja | C85: Cajero Automático | D85: 349935 | E85: 346356 | F85: 253861 | G85: 136162 | H85: 185110 | I85: 241088 | J85: 256922 | K85: 270215 | L85: 291551 | M85: 269509 | N85: 248919 | O85: 318619 | P85: 3168247 | Q85: 264020.58 | R85: 0.88285894
C86: Cajero Automático Plus | D86: 0 | E86: 0 | F86: 0 | G86: 0 | H86: 0 | I86: 0 | J86: 0 | K86: 0 | L86: 0 | M86: 0 | N86: 0 | O86: 0 | P86: 0 | Q86: 0 | R86: 0
C87: Cajero Automático Móvil | D87: 0 | E87: 0 | F87: 0 | G87: 0 | H87: 0 | I87: 0 | J87: 0 | K87: 0 | L87: 0 | M87: 0 | N87: 0 | O87: 0 | P87: 0 | Q87: 0 | R87: 0
C88: Corresponsal No Bancario | D88: 0 | E88: 0 | F88: 0 | G88: 0 | H88: 0 | I88: 0 | J88: 0 | K88: 0 | L88: 0 | M88: 0 | N88: 0 | O88: 0 | P88: 0 | Q88: 0 | R88: 0
C89: Oficina / Ventanilla | D89: 73893 | E89: 67634 | F89: 48193 | G89: 23104 | H89: 27700 | I89: 37429 | J89: 41599 | K89: 40786 | L89: 47979 | M89: 0 | N89: 0 | O89: 0 | P89: 408317 | Q89: 34026.417 | R89: 0.113781
C90: Ventanilla Compartida | D90: 4044 | E90: 3593 | F90: 2701 | G90: 1720 | H90: 0 | I90: 0 | J90: 0 | K90: 0 | L90: 0 | M90: 0 | N90: 0 | O90: 0 | P90: 12058 | Q90: 1004.8333 | R90: 0.0033600641
B91: Total Banco de Loja | D91: 427872 | E91: 417583 | F91: 304755 | G91: 160986 | H91: 212810 | I91: 278517 | J91: 298521 | K91: 311001 | L91: 339530 | M91: 269509 | N91: 248919 | O91: 318619 | P91: 3588622 | Q91: 299051.83 | R91: 1
B93: Banco de Machala | C93: Cajero Automático | D93: 175322 | E93: 166290 | F93: 150683 | G93: 93703 | H93: 113552 | I93: 136371 | J93: 143926 | K93: 140068 | L93: 143606 | M93: 152224 | N93: 146850 | O93: 186279 | P93: 1748874 | Q93: 145739.5 | R93: 0.62064898
C94: Cajero Automático Plus | D94: 0 | E94: 0 | F94: 0 | G94: 0 | H94: 0 | I94: 0 | J94: 0 | K94: 0 | L94: 0 | M94: 0 | N94: 0 | O94: 0 | P94: 0 | Q94: 0 | R94: 0
C95: Cajero Automático Móvil | D95: 0 | E95: 0 | F95: 0 | G95: 0 | H95: 0 | I95: 0 | J95: 0 | K95: 0 | L95: 0 | M95: 0 | N95: 0 | O95: 0 | P95: 0 | Q95: 0 | R95: 0
C96: Corresponsal No Bancario | D96: 0 | E96: 0 | F96: 0 | G96: 0 | H96: 0 | I96: 0 | J96: 0 | K96: 0 | L96: 0 | M96: 0 | N96: 0 | O96: 0 | P96: 0 | Q96: 0 | R96: 0
C97: Oficina / Ventanilla | D97: 123727 | E97: 110189 | F97: 94413 | G97: 48169 | H97: 55053 | I97: 80050 | J97: 86464 | K97: 81210 | L97: 90830 | M97: 96201 | N97: 90542 | O97: 112093 | P97: 1068941 | Q97: 89078.417 | R97: 0.37935102
C98: Ventanilla Compartida | D98: 0 | E98: 0 | F98: 0 | G98: 0 | H98: 0 | I98: 0 | J98: 0 | K98: 0 | L98: 0 | M98: 0 | N98: 0 | O98: 0 | P98: 0 | Q98: 0 | R98: 0
B99: Total Banco de Machala | D99: 299049 | E99: 276479 | F99: 245096 | G99: 141872 | H99: 168605 | I99: 216421 | J99: 230390 | K99: 221278 | L99: 234436 | M99: 248425 | N99: 237392 | O99: 298372 | P99: 2817815 | Q99: 234817.92 | R99: 1
B101: Banco del Pacífico | C101: Cajero Automático | D101: 1620713 | E101: 1590852 | F101: 1215849 | G101: 745836 | H101: 941009 | I101: 1103134 | J101: 1177099 | K101: 1187392 | L101: 1231325 | M101: 1351855 | N101: 1215958 | O101: 1564892 | P101: 14945914 | Q101: 1245492.8 | R101: 0.53279606
C102: Cajero Automático Plus | D102: 1061580 | E102: 1030535 | F102: 823295 | G102: 563150 | H102: 718275 | I102: 811461 | J102: 883216 | K102: 937020 | L102: 1002649 | M102: 1126218 | N102: 1059601 | O102: 1390965 | P102: 11407965 | Q102: 950663.75 | R102: 0.40667428
C103: Cajero Automático Móvil | D103: 0 | E103: 0 | F103: 0 | G103: 0 | H103: 0 | I103: 0 | J103: 0 | K103: 0 | L103: 0 | M103: 0 | N103: 0 | O103: 0 | P103: 0 | Q103: 0 | R103: 0
C104: Corresponsal No Bancario | D104: 0 | E104: 0 | F104: 0 | G104: 0 | H104: 0 | I104: 0 | J104: 0 | K104: 0 | L104: 0 | M104: 0 | N104: 0 | O104: 0 | P104: 0 | Q104: 0 | R104: 0
C105: Oficina / Ventanilla | D105: 231376 | E105: 198618 | F105: 155144 | G105: 67457 | H105: 86287 | I105: 124290 | J105: 138074 | K105: 133148 | L105: 139361 | M105: 141242 | N105: 128072 | O105: 154900 | P105: 1697969 | Q105: 141497.42 | R105: 0.060529666
C106: Ventanilla Compartida | D106: 0 | E106: 0 | F106: 0 | G106: 0 | H106: 0 | I106: 0 | J106: 0 | K106: 0 | L106: 0 | M106: 0 | N106: 0 | O106: 0 | P106: 0 | Q106: 0 | R106: 0
B107: Total Banco del Pacífico | D107: 2913669 | E107: 2820005 | F107: 2194288 | G107: 1376443 | H107: 1745571 | I107: 2038885 | J107: 2198389 | K107: 2257560 | L107: 2373335 | M107: 2619315 | N107: 2403631 | O107: 3110757 | P107: 28051848 | Q107: 2337654 | R107: 1
B109: Banco Pichincha | C109: Cajero Automático | D109: 6228718 | E109: 6128548 | F109: 4451133 | G109: 2379291 | H109: 3015774 | I109: 3972906 | J109: 4435159 | K109: 4693666 | L109: 4833601 | M109: 5503976 | N109: 5177326 | O109: 6450686 | P109: 57270784 | Q109: 4772565.3 | R109: 0.64581431
C110: Cajero Automático Plus | D110: 0 | E110: 0 | F110: 0 | G110: 0 | H110: 0 | I110: 0 | J110: 0 | K110: 0 | L110: 0 | M110: 0 | N110: 0 | O110: 0 | P110: 0 | Q110: 0 | R110: 0
C111: Cajero Automático Móvil | D111: 0 | E111: 0 | F111: 0 | G111: 0 | H111: 0 | I111: 0 | J111: 0 | K111: 0 | L111: 0 | M111: 0 | N111: 0 | O111: 0 | P111: 0 | Q111: 0 | R111: 0
C112: Corresponsal No Bancario | D112: 1952031 | E112: 1951692 | F112: 1466558 | G112: 1011329 | H112: 1253013 | I112: 1611905 | J112: 1818813 | K112: 1926296 | L112: 2018419 | M112: 2236823 | N112: 2109739 | O112: 2530991 | P112: 21887609 | Q112: 1823967.4 | R112: 0.24681574
C113: Oficina / Ventanilla | D113: 1148175 | E113: 1036489 | F113: 764764 | G113: 345179 | H113: 444210 | I113: 718334 | J113: 762480 | K113: 729370 | L113: 811623 | M113: 852151 | N113: 775238 | O113: 896899 | P113: 9284912 | Q113: 773742.67 | R113: 0.10470136
C114: Ventanilla Compartida | D114: 27974 | E114: 26798 | F114: 20437 | G114: 11750 | H114: 14075 | I114: 18258 | J114: 17936 | K114: 18851 | L114: 19096 | M114: 19815 | N114: 17129 | O114: 24531 | P114: 236650 | Q114: 19720.833 | R114: 0.002668585
B115: Total Banco Pichincha | D115: 9356898 | E115: 9143527 | F115: 6702892 | G115: 3747549 | H115: 4727072 | I115: 6321403 | J115: 7034388 | K115: 7368183 | L115: 7682739 | M115: 8612765 | N115: 8079432 | O115: 9903107 | P115: 88679955 | Q115: 7389996.2 | R115: 1
...

Sheet SECCIÓN VII
B1: SUPERINTENDENCIA DE BANCOS DEL ECUADOR INTENDENCIA NACIONAL DE RIESGOS Y ESTUDIOS DIRECCIÓN DE ESTUDIOS Y GESTIÓN DE LA INFORMACIÓN SUBDIRECCIÓN DE ESTADÍSTICAS Y ESTUDIOS
B3: ESTADÍSTICAS DE RETIROS DE DINERO EN EFECTIVO SOBRE CUENTAS DE AHORRO EN CANALES PROPIOS DE LA ENTIDAD
B4: Enero a Diciembre 2020
B5: Fecha de publicación: Enero 2021
B6: Datos Provisionales
B8: SECCIÓN VII: RETIROS DE DINERO POR ENTIDAD FINANCIERA POR PROVINCIA
B10: 7.1 Evolución de Transacciones de Retiros de Dinero por Entidad Financiera por Provincia
B11: 2 | C11: 3 | D11: 4 | E11: 5 | F11: 6 | G11: 7 | H11: 8 | I11: 9 | J11: 10 | K11: 11 | L11: 12 | M11: 13 | N11: 14 | O11: 15
B12: Entidad Financiera | C12: Provincia | D12: Enero | E12: Febrero | F12: Marzo | G12: Abril | H12: Mayo | I12: Junio | J12: Julio | K12: Agosto | L12: Septiembre | M12: Octubre | N12: Noviembre | O12: Diciembre | P12: Total | Q12: Promedio | R12: % Número de retiros
B13: Banco Amazonas | C13: Azuay | D13: 0 | E13: 0 | F13: 0 | G13: 0 | H13: 0 | I13: 0 | J13: 0 | K13: 0 | L13: 0 | M13: 0 | N13: 0 | O13: 0 | P13: 0 | Q13: 0 | R13: 0
C14: Bolívar | D14: 0 | E14: 0 | F14: 0 | G14: 0 | H14: 0 | I14: 0 | J14: 0 | K14: 0 | L14: 0 | M14: 0 | N14: 0 | O14: 0 | P14: 0 | Q14: 0 | R14: 0
C15: Cañar | D15: 0 | E15: 0 | F15: 0 | G15: 0 | H15: 0 | I15: 0 | J15: 0 | K15: 0 | L15: 0 | M15: 0 | N15: 0 | O15: 0 | P15: 0 | Q15: 0 | R15: 0
C16: Carchi | D16: 0 | E16: 0 | F16: 0 | G16: 0 | H16: 0 | I16: 0 | J16: 0 | K16: 0 | L16: 0 | M16: 0 | N16: 0 | O16: 0 | P16: 0 | Q16: 0 | R16: 0
C17: Cotopaxi | D17: 0 | E17: 0 | F17: 0 | G17: 0 | H17: 0 | I17: 0 | J17: 0 | K17: 0 | L17: 0 | M17: 0 | N17: 0 | O17: 0 | P17: 0 | Q17: 0 | R17: 0
C18: Chimborazo | D18: 0 | E18: 0 | F18: 0 | G18: 0 | H18: 0 | I18: 0 | J18: 0 | K18: 0 | L18: 0 | M18: 0 | N18: 0 | O18: 0 | P18: 0 | Q18: 0 | R18: 0
C19: El Oro | D19: 0 | E19: 0 | F19: 0 | G19: 0 | H19: 0 | I19: 0 | J19: 0 | K19: 0 | L19: 0 | M19: 0 | N19: 0 | O19: 0 | P19: 0 | Q19: 0 | R19: 0
C20: Esmeraldas | D20: 0 | E20: 0 | F20: 0 | G20: 0 | H20: 0 | I20: 0 | J20: 0 | K20: 0 | L20: 0 | M20: 0 | N20: 0 | O20: 0 | P20: 0 | Q20: 0 | R20: 0
C21: Guayas | D21: 1602 | E21: 1519 | F21: 1441 | G21: 675 | H21: 677 | I21: 958 | J21: 1036 | K21: 956 | L21: 1072 | M21: 1156 | N21: 1028 | O21: 1459 | P21: 13579 | Q21: 1131.5833 | R21: 0.79937599
C22: Imbabura | D22: 0 | E22: 0 | F22: 0 | G22: 0 | H22: 0 | I22: 0 | J22: 0 | K22: 0 | L22: 0 | M22: 0 | N22: 0 | O22: 0 | P22: 0 | Q22: 0 | R22: 0
C23: Loja | D23: 0 | E23: 0 | F23: 0 | G23: 0 | H23: 0 | I23: 0 | J23: 0 | K23: 0 | L23: 0 | M23: 0 | N23: 0 | O23: 0 | P23: 0 | Q23: 0 | R23: 0
C24: Los Ríos | D24: 0 | E24: 0 | F24: 0 | G24: 0 | H24: 0 | I24: 0 | J24: 0 | K24: 0 | L24: 0 | M24: 0 | N24: 0 | O24: 0 | P24: 0 | Q24: 0 | R24: 0
C25: Manabí | D25: 0 | E25: 0 | F25: 0 | G25: 0 | H25: 0 | I25: 0 | J25: 0 | K25: 0 | L25: 0 | M25: 0 | N25: 0 | O25: 0 | P25: 0 | Q25: 0 | R25: 0
... C36: Santa Elena | D36: 0 | E36: 0 | F36: 0 | G36: 0 | H36: 0 | I36: 0 | J36: 0 | K36: 0 | L36: 0 | M36: 0 | N36: 0 | O36: 0 | P36: 0 | Q36: 0 | R36: 0
B37: Total Banco Amazonas | D37: 2036 | E37: 1914 | F37: 1723 | G37: 851 | H37: 872 | I37: 1208 | J37: 1319 | K37: 1221 | L37: 1336 | M37: 1412 | N37: 1272 | O37: 1823 | P37: 16987 | Q37: 1415.5833 | R37: 1
B39: Banco del Austro | C39: Azuay | D39: 200162 | E39: 186584 | F39: 138640 | G39: 79881 | H39: 107413 | I39: 137656 | J39: 149914 | K39: 156255 | L39: 167650 | M39: 182156 | N39: 172764 | O39: 210347 | P39: 1889422 | Q39: 157451.83 | R39: 0.36739605
C40: Bolívar | D40: 0 | E40: 0 | F40: 0 | G40: 0 | H40: 0 | I40: 0 | J40: 0 | K40: 0 | L40: 0 | M40: 0 | N40: 0 | O40: 0 | P40: 0 | Q40: 0 | R40: 0
C41: Cañar | D41: 60337 | E41: 56923 | F41: 43789 | G41: 26568 | H41: 35326 | I41: 46004 | J41: 47873 | K41: 47061 | L41: 50829 | M41: 53664 | N41: 48955 | O41: 57658 | P41: 574987 | Q41: 47915.583 | R41: 0.1118056
C42: Carchi | D42: 5707 | E42: 5328 | F42: 3845 | G42: 2370 | H42: 2793 | I42: 3383 | J42: 3432 | K42: 3666 | L42: 4043 | M42: 4826 | N42: 4349 | O42: 5704 | P42: 49446 | Q42: 4120.5 | R42: 0.0096147209
C43: Cotopaxi | D43: 5721 | E43: 5406 | F43: 4340 | G43: 2827 | H43: 3554 | I43: 4075 | J43: 4323 | K43: 4877 | L43: 4301 | M43: 4619 | N43: 4494 | O43: 5695 | P43: 54232 | Q43: 4519.3333 | R43: 0.010545353
C44: Chimborazo | D44: 12857 | E44: 12471 | F44: 8653 | G44: 5028 | H44: 6563 | I44: 8740 | J44: 8856 | K44: 9997 | L44: 10227 | M44: 10688 | N44: 9941 | O44: 12810 | P44: 116831 | Q44: 9735.9167 | R44: 0.022717661
C45: El Oro | D45: 32131 | E45: 31119 | F45: 25787 | G45: 17440 | H45: 21919 | I45: 25893 | J45: 27526 | K45: 26548 | L45: 26861 | M45: 29597 | N45: 27749 | O45: 32925 | P45: 325495 | Q45: 27124.583 | R45: 0.063292148
C46: Esmeraldas | D46: 4926 | E46: 5207 | F46: 4316 | G46: 3188 | H46: 3853 | I46: 4060 | J46: 4210 | K46: 4063 | L46: 4515 | M46: 5228 | N46: 4359 | O46: 6508 | P46: 54433 | Q46: 4536.0833 | R46: 0.010584438
C47: Guayas | D47: 45583 | E47: 42520 | F47: 32207 | G47: 17149 | H47: 24626 | I47: 33593 | J47: 36908 | K47: 35327 | L47: 37353 | M47: 40174 | N47: 36047 | O47: 47881 | P47: 429368 | Q47: 35780.667 | R47: 0.08349014
C48: Imbabura | D48: 23838 | E48: 22899 | F48: 16046 | G48: 8748 | H48: 10127 | I48: 12355 | J48: 14570 | K48: 17642 | L48: 16297 | M48: 18152 | N48: 16246 | O48: 22661 | P48: 199581 | Q48: 16631.75 | R48: 0.038808308
C49: Loja | D49: 15723 | E49: 14773 | F49: 11417 | G49: 6192 | H49: 8258 | I49: 10505 | J49: 11178 | K49: 11442 | L49: 12557 | M49: 14607 | N49: 12887 | O49: 15241 | P49: 144780 | Q49: 12065 | R49: 0.028152313
C50: Los Ríos | D50: 0 | E50: 0 | F50: 0 | G50: 0 | H50: 0 | I50: 0 | J50: 0 | K50: 0 | L50: 0 | M50: 0 | N50: 0 | O50: 0 | P50: 0 | Q50: 0 | R50: 0
C51: Manabí | D51: 5680 | E51: 5098 | F51: 4536 | G51: 2309 | H51: 3039 | I51: 3900 | J51: 4345 | K51: 4178 | L51: 4399 | M51: 4966 | N51: 4485 | O51: 6001 | P51: 52936 | Q51: 4411.3333 | R51: 0.010293348
... C62: Santa Elena | D62: 4906 | E62: 5266 | F62: 4025 | G62: 3387 | H62: 2739 | I62: 3434 | J62: 3960 | K62: 4753 | L62: 5848 | M62: 4651 | N62: 4185 | O62: 5403 | P62: 52557 | Q62: 4379.75 | R62: 0.010219651
B63: Total Banco del Austro | D63: 556494 | E63: 526347 | F63: 393095 | G63: 225464 | H63: 296577 | I63: 381135 | J63: 411705 | K63: 426684 | L63: 447248 | M63: 480385 | N63: 445430 | O63: 552175 | P63: 5142739 | Q63: 428561.58 | R63: 1
B65: Banco de Guayaquil | C65: Azuay | D65: 90667 | E65: 91367 | F65: 64734 | G65: 40363 | H65: 43918 | I65: 57632 | J65: 467153 | K65: 64452 | L65: 488774 | M65: 67343 | N65: 64692 | O65: 80947 | P65: 1622042 | Q65: 135170.17 | R65: 0.044686028
C66: Bolívar | D66: 10462 | E66: 11039 | F66: 7293 | G66: 4078 | H66: 4635 | I66: 6038 | J66: 4486 | K66: 6794 | L66: 4971 | M66: 7657 | N66: 8482 | O66: 10191 | P66: 86126 | Q66: 7177.1667 | R66: 0.002372706
C67: Cañar | D67: 18435 | E67: 16643 | F67: 14714 | G67: 8839 | H67: 10738 | I67: 14179 | J67: 12336 | K67: 14917 | L67: 12641 | M67: 15005 | N67: 15471 | O67: 17989 | P67: 171907 | Q67: 14325.583 | R67: 0.0047359076
C68: Carchi | D68: 6527 | E68: 6431 | F68: 5115 | G68: 2418 | H68: 2876 | I68: 4180 | J68: 3620 | K68: 4893 | L68: 3857 | M68: 6456 | N68: 6089 | O68: 7133 | P68: 59595 | Q68: 4966.25 | R68: 0.0016417971
C69: Cotopaxi | D69: 23505 | E69: 21066 | F69: 17176 | G69: 9327 | H69: 9545 | I69: 13279 | J69: 10620 | K69: 15667 | L69: 11072 | M69: 19150 | N69: 19575 | O69: 22573 | P69: 192555 | Q69: 16046.25 | R69: 0.0053047443
C70: Chimborazo | D70: 67725 | E70: 62531 | F70: 47676 | G70: 27956 | H70: 31640 | I70: 43566 | J70: 27709 | K70: 48343 | L70: 28121 | M70: 49474 | N70: 52537 | O70: 61653 | P70: 548931 | Q70: 45744.25 | R70: 0.015122633
C71: El Oro | D71: 69488 | E71: 64598 | F71: 59778 | G71: 34562 | H71: 41550 | I71: 55545 | J71: 53996 | K71: 59871 | L71: 55807 | M71: 64623 | N71: 67099 | O71: 74302 | P71: 701219 | Q71: 58434.917 | R71: 0.019318052
C72: Esmeraldas | D72: 68132 | E72: 62251 | F72: 55357 | G72: 33156 | H72: 38166 | I72: 46946 | J72: 43113 | K72: 53913 | L72: 46009 | M72: 61718 | N72: 11298 | O72: 87752 | P72: 607811 | Q72: 50650.917 | R72: 0.016744732
C73: Guayas | D73: 1715975 | E73: 1539060 | F73: 1487261 | G73: 909138 | H73: 1081040 | I73: 1441928 | J73: 1173894 | K73: 1535132 | L73: 1187500 | M73: 1637899 | N73: 1661809 | O73: 1980879 | P73: 17351515 | Q73: 1445959.6 | R73: 0.47802109
C74: Imbabura | D74: 33433 | E74: 31644 | F74: 25699 | G74: 11985 | H74: 13391 | I74: 19385 | J74: 22805 | K74: 24923 | L74: 26503 | M74: 28967 | N74: 30548 | O74: 35695 | P74: 304978 | Q74: 25414.833 | R74: 0.0084019128
C75: Loja | D75: 24049 | E75: 20578 | F75: 16136 | G75: 6261 | H75: 9993 | I75: 14110 | J75: 13101 | K75: 14547 | L75: 17008 | M75: 18307 | N75: 18876 | O75: 21915 | P75: 194881 | Q75: 16240.083 | R75: 0.0053688239
C76: Los Ríos | D76: 203546 | E76: 182737 | F76: 184078 | G76: 117765 | H76: 131908 | I76: 165602 | J76: 169729 | K76: 170366 | L76: 170177 | M76: 184836 | N76: 190800 | O76: 235494 | P76: 2107038 | Q76: 175586.5 | R76: 0.0580473
C77: Manabí | D77: 238568 | E77: 219291 | F77: 207794 | G77: 127161 | H77: 133893 | I77: 172556 | J77: 187377 | K77: 192014 | L77: 199365 | M77: 213566 | N77: 209345 | O77: 246846 | P77: 2347776 | Q77: 195648 | R77: 0.06467945
... C88: Santa Elena | D88: 129270 | E88: 123487 | F88: 104120 | G88: 66863 | H88: 71967 | I88: 93509 | J88: 102674 | K88: 97863 | L88: 109603 | M88: 116354 | N88: 123331 | O88: 146521 | P88: 1285562 | Q88: 107130.17 | R88: 0.035416259
B89: Total Banco de Guayaquil | D89: 3636390 | E89: 3339408 | F89: 3012153 | G89: 1838633 | H89: 2109870 | I89: 2764666 | J89: 2923349 | K89: 3017675 | L89: 3090959 | M89: 3267287 | N89: 3338384 | O89: 3959865 | P89: 36298639 | Q89: 3024886.6 | R89: 1
B91: Banco Bolivariano | C91: Azuay | D91: 21218 | E91: 17611 | F91: 13916 | G91: 7522 | H91: 9855 | I91: 14147 | J91: 14600 | K91: 15227 | L91: 15178 | M91: 15319 | N91: 14723 | O91: 16112 | P91: 175428 | Q91: 14619 | R91: 0.013274722
C92: Bolívar | D92: 17 | E92: 19 | F92: 24 | G92: 3 | H92: 7 | I92: 11 | J92: 14 | K92: 11 | L92: 9 | M92: 7 | N92: 9 | O92: 7 | P92: 138 | Q92: 11.5 | R92: 1.0442527e-05
C93: Cañar | D93: 11636 | E93: 9700 | F93: 10157 | G93: 5688 | H93: 7035 | I93: 9193 | J93: 9655 | K93: 10218 | L93: 11181 | M93: 10156 | N93: 10621 | O93: 12102 | P93: 117342 | Q93: 9778.5 | R93: 0.0088793262
C94: Carchi | D94: 0 | E94: 0 | F94: 0 | G94: 0 | H94: 0 | I94: 0 | J94: 0 | K94: 0 | L94: 0 | M94: 0 | N94: 0 | O94: 0 | P94: 0 | Q94: 0 | R94: 0
C95: Cotopaxi | D95: 1561 | E95: 1331 | F95: 1079 | G95: 830 | H95: 1099 | I95: 1692 | J95: 1500 | K95: 1552 | L95: 1391 | M95: 1657 | N95: 1852 | O95: 2108 | P95: 17652 | Q95: 1471 | R95: 0.0013357354
C96: Chimborazo | D96: 126 | E96: 108 | F96: 77 | G96: 47 | H96: 58 | I96: 50 | J96: 71 | K96: 72 | L96: 88 | M96: 97 | N96: 86 | O96: 82 | P96: 962 | Q96: 80.166667 | R96: 7.2795007e-05
C97: El Oro | D97: 16432 | E97: 15536 | F97: 14749 | G97: 9630 | H97: 11415 | I97: 14183 | J97: 14226 | K97: 14317 | L97: 14629 | M97: 14882 | N97: 14610 | O97: 18400 | P97: 173009 | Q97: 14417.417 | R97: 0.013091675
C98: Esmeraldas | D98: 11437 | E98: 9808 | F98: 10043 | G98: 8222 | H98: 9348 | I98: 9337 | J98: 9858 | K98: 9009 | L98: 8986 | M98: 10832 | N98: 9457 | O98: 14977 | P98: 121314 | Q98: 10109.5 | R98: 0.0091798893
C99: Guayas | D99: 1028118 | E99: 927115 | F99: 864322 | G99: 546289 | H99: 650356 | I99: 832769 | J99: 861419 | K99: 849407 | L99: 855950 | M99: 888273 | N99: 915875 | O99: 1094122 | P99: 10314015 | Q99: 859501.25 | R99: 0.78046653
C100: Imbabura | D100: 251 | E100: 206 | F100: 159 | G100: 58 | H100: 74 | I100: 128 | J100: 162 | K100: 193 | L100: 193 | M100: 158 | N100: 173 | O100: 284 | P100: 2039 | Q100: 169.91667 | R100: 0.00015429212
C101: Loja | D101: 6591 | E101: 5940 | F101: 4637 | G101: 2266 | H101: 3113 | I101: 4513 | J101: 4759 | K101: 4872 | L101: 4870 | M101: 5243 | N101: 5455 | O101: 6157 | P101: 58416 | Q101: 4868 | R101: 0.0044203671
C102: Los Ríos | D102: 33215 | E102: 30026 | F102: 29521 | G102: 20253 | H102: 23592 | I102: 27894 | J102: 28236 | K102: 27338 | L102: 28580 | M102: 29374 | N102: 29805 | O102: 38778 | P102: 346612 | Q102: 28884.333 | R102: 0.026228298
C103: Manabí | D103: 41112 | E103: 36868 | F103: 35459 | G103: 20659 | H103: 23975 | I103: 28945 | J103: 30223 | K103: 30945 | L103: 31236 | M103: 34632 | N103: 34196 | O103: 43523 | P103: 391773 | Q103: 32647.75 | R103: 0.029645653
... C114: Santa Elena | D114: 22469 | E114: 21529 | F114: 17622 | G114: 10645 | H114: 11765 | I114: 14688 | J114: 14853 | K114: 14523 | L114: 15402 | M114: 17112 | N114: 17158 | O114: 20117 | P114: 197883 | Q114: 16490.25 | R114: 0.014973903
B115: Total Banco Bolivariano | D115: 1350730 | E115: 1214459 | F115: 1113232 | G115: 693058 | H115: 821626 | I115: 1052001 | J115: 1085012 | K115: 1080692 | L115: 1092927 | M115: 1139120 | N115: 1167595 | O115: 1404740 | P115: 13215192 | Q115: 1101266 | R115: 1
B117: Citibank | C117: Azuay | D117: 0 | E117: 0 | F117: 0 | G117: 0 | H117: 0 | I117: 0 | J117: 0 | K117: 0 | L117: 0 | M117: 0 | N117: 0 | O117: 0 | P117: 0 | Q117: 0
C118: Bolívar | D118: 0 | E118: 0 | F118: 0 | G118: 0 | H118: 0 | I118: 0 | J118: 0 | K118: 0 | L118: 0 | M118: 0 | N118: 0 | O118: 0 | P118: 0 | Q118: 0
C119: Cañar | D119: 0 | E119: 0 | F119: 0 | G119: 0 | H119: 0 | I119: 0 | J119: 0 | K119: 0 | L119: 0 | M119: 0 | N119: 0 | O119: 0 | P119: 0 | Q119: 0
C120: Carchi | D120: 0 | E120: 0 | F120: 0 | G120: 0 | H120: 0 | I120: 0 | J120: 0 | K120: 0 | L120: 0 | M120: 0 | N120: 0 | O120: 0 | P120: 0 | Q120: 0
C121: Cotopaxi | D121: 0 | E121: 0 | F121: 0 | G121: 0 | H121: 0 | I121: 0 | J121: 0 | K121: 0 | L121: 0 | M121: 0 | N121: 0 | O121: 0 | P121: 0 | Q121: 0
C122: Chimborazo | D122: 0 | E122: 0 | F122: 0 | G122: 0 | H122: 0 | I122: 0 | J122: 0 | K122: 0 | L122: 0 | M122: 0 | N122: 0 | O122: 0 | P122: 0 | Q122: 0
C123: El Oro | D123: 0 | E123: 0 | F123: 0 | G123: 0 | H123: 0 | I123: 0 | J123: 0 | K123: 0 | L123: 0 | M123: 0 | N123: 0 | O123: 0 | P123: 0 | Q123: 0
C124: Esmeraldas | D124: 0 | E124: 0 | F124: 0 | G124: 0 | H124: 0 | I124: 0 | J124: 0 | K124: 0 | L124: 0 | M124: 0 | N124: 0 | O124: 0 | P124: 0 | Q124: 0
C125: Guayas | D125: 0 | E125: 0 | F125: 0 | G125: 0 | H125: 0 | I125: 0 | J125: 0 | K125: 0 | L125: 0 | M125: 0 | N125: 0 | O125: 0 | P125: 0 | Q125: 0
C126: Imbabura | D126: 0 | E126: 0 | F126: 0 | G126: 0 | H126: 0 | I126: 0 | J126: 0 | K126: 0 | L126: 0 | M126: 0 | N126: 0 | O126: 0 | P126: 0 | Q126: 0
C127: Loja | D127: 0 | E127: 0 | F127: 0 | G127: 0 | H127: 0 | I127: 0 | J127: 0 | K127: 0 | L127: 0 | M127: 0 | N127: 0 | O127: 0 | P127: 0 | Q127: 0
C128: Los Ríos | D128: 0 | E128: 0 | F128: 0 | G128: 0 | H128: 0 | I128: 0 | J128: 0 | K128: 0 | L128: 0 | M128: 0 | N128: 0 | O128: 0 | P128: 0 | Q128: 0
C129: Manabí | D129: 0 | E129: 0 | F129: 0 | G129: 0 | H129: 0 | I129: 0 | J129: 0 | K129: 0 | L129: 0 | M129: 0 | N129: 0 | O129: 0 | P129: 0 | Q129: 0
... C140: Santa Elena | D140: 0 | E140: 0 | F140: 0 | G140: 0 | H140: 0 | I140: 0 | J140: 0 | K140: 0 | L140: 0 | M140: 0 | N140: 0 | O140: 0 | P140: 0 | Q140: 0
B141: Total Banco Citibank | D141: 0 | E141: 0 | F141: 0 | G141: 0 | H141: 0 | I141: 0 | J141: 0 | K141: 0 | L141: 0 | M141: 0 | N141: 0 | O141: 0 | P141: 0 | Q141: 0
B143: Banco Comercial de Manabí | C143: Azuay | D143: 0 | E143: 0 | F143: 0 | G143: 0 | H143: 0 | I143: 0 | J143: 0 | K143: 0 | L143: 0 | M143: 0 | N143: 0 | O143: 0 | P143: 0 | Q143: 0 | R143: 0
C144: Bolívar | D144: 0 | E144: 0 | F144: 0 | G144: 0 | H144: 0 | I144: 0 | J144: 0 | K144: 0 | L144: 0 | M144: 0 | N144: 0 | O144: 0 | P144: 0 | Q144: 0 | R144: 0
C145: Cañar | D145: 0 | E145: 0 | F145: 0 | G145: 0 | H145: 0 | I145: 0 | J145: 0 | K145: 0 | L145: 0 | M145: 0 | N145: 0 | O145: 0 | P145: 0 | Q145: 0 | R145: 0
C146: Carchi | D146: 0 | E146: 0 | F146: 0 | G146: 0 | H146: 0 | I146: 0 | J146: 0 | K146: 0 | L146: 0 | M146: 0 | N146: 0 | O146: 0 | P146: 0 | Q146: 0 | R146: 0
C147: Cotopaxi | D147: 0 | E147: 0 | F147: 0 | G147: 0 | H147: 0 | I147: 0 | J147: 0 | K147: 0 | L147: 0 | M147: 0 | N147: 0 | O147: 0 | P147: 0 | Q147: 0 | R147: 0
C148: Chimborazo | D148: 0 | E148: 0 | F148: 0 | G148: 0 | H148: 0 | I148: 0 | J148: 0 | K148: 0 | L148: 0 | M148: 0 | N148: 0 | O148: 0 | P148: 0 | Q148: 0 | R148: 0
C149: El Oro | D149: 0 | E149: 0 | F149: 0 | G149: 0 | H149: 0 | I149: 0 | J149: 0 | K149: 0 | L149: 0 | M149: 0 | N149: 0 | O149: 0 | P149: 0 | Q149: 0 | R149: 0
C150: Esmeraldas | D150: 0 | E150: 0 | F150: 0 | G150: 0 | H150: 0 | I150: 0 | J150: 0 | K150: 0 | L150: 0 | M150: 0 | N150: 0 | O150: 0 | P150: 0 | Q150: 0 | R150: 0
C151: Guayas | D151: 239 | E151: 233 | F151: 169 | G151: 9 | H151: 72 | I151: 153 | J151: 195 | K151: 149 | L151: 188 | M151: 213 | N151: 180 | O151: 248 | P151: 2048 | Q151: 170.66667 | R151: 0.00564858
C152: Imbabura | D152: 0 | E152: 0 | F152: 0 | G152: 0 | H152: 0 | I152: 0 | J152: 0 | K152: 0 | L152: 0 | M152: 0 | N152: 0 | O152: 0 | P152: 0 | Q152: 0 | R152: 0
C153: Loja | D153: 0 | E153: 0 | F153: 0 | G153: 0 | H153: 0 | I153: 0 | J153: 0 | K153: 0 | L153: 0 | M153: 0 | N153: 0 | O153: 0 | P153: 0 | Q153: 0 | R153: 0
C154: Los Ríos | D154: 0 | E154: 0 | F154: 0 | G154: 0 | H154: 0 | I154: 0 | J154: 0 | K154: 0 | L154: 0 | M154: 0 | N154: 0 | O154: 0 | P154: 0 | Q154: 0 | R154: 0
C155: Manabí | D155: 36749 | E155: 34028 | F155: 32497 | G155: 19631 | H155: 24648 | I155: 27755 | J155: 28907 | K155: 25352 | L155: 29479 | M155: 32515 | N155: 30453 | O155: 38507 | P155: 360521 | Q155: 30043.417 | R155: 0.99435142
... C166: Santa Elena | D166: 0 | E166: 0 | F166: 0 | G166: 0 | H166: 0 | I166: 0 | J166: 0 | K166: 0 | L166: 0 | M166: 0 | N166: 0 | O166: 0 | P166: 0 | Q166: 0 | R166: 0
B167: Total Banco Comercial de Manabí | D167: 36988 | E167: 34261 | F167: 32666 | G167: 19640 | H167: 24720 | I167: 27908 | J167: 29102 | K167: 25501 | L167: 29667 | M167: 32728 | N167: 30633 | O167: 38755 | P167: 362569 | Q167: 30214.083 | R167: 1
B169: Banco del Litoral | C169: Azuay | D169: 0 | E169: 0 | F169: 0 | G169: 0 | H169: 0 | I169: 0 | J169: 0 | K169: 0 | L169: 0 | M169: 0 | N169: 0 | O169: 0 | P169: 0 | Q169: 0 | R169: 0
...

Sheet SECCIÓN VIII
B1: SUPERINTENDENCIA DE BANCOS DEL ECUADOR INTENDENCIA NACIONAL DE RIESGOS Y ESTUDIOS DIRECCIÓN DE ESTUDIOS Y GESTIÓN DE LA INFORMACIÓN SUBDIRECCIÓN DE ESTADÍSTICAS Y ESTUDIOS
B3: ESTADÍSTICAS DE RETIROS DE DINERO EN EFECTIVO SOBRE CUENTAS DE AHORRO EN CANALES PROPIOS DE LA ENTIDAD
B4: Enero a Diciembre 2020
B5: Fecha de publicación: Enero 2021
B6: Datos Provisionales
B8: SECCIÓN VIII: RETIROS DE DINERO POR ENTIDAD FINANCIERA POR ORDENANTE
B10: 8.1 Evolución de Transacciones de Retiros de Dinero por Entidad Financiera por Ordenante
C11: } | D11: 4 | E11: 5 | F11: 6 | G11: 7 | H11: 8 | I11: 9 | J11: 10 | K11: 11 | L11: 12 | M11: 13 | N11: 14 | O11: 15
B12: Entidad Financiera | C12: Ordenante | D12: Enero | E12: Febrero | F12: Marzo | G12: Abril | H12: Mayo | I12: Junio | J12: Julio | K12: Agosto | L12: Septiembre | M12: Octubre | N12: Noviembre | O12: Diciembre | P12: Total | Q12: Promedio | R12: % Número de retiros
B13: Banco Amazonas | C13: Cliente | D13: 2036 | E13: 1914 | F13: 1723 | G13: 851 | H13: 872 | I13: 1208 | J13: 1319 | K13: 1221 | L13: 1336 | M13: 1412 | N13: 1272 | O13: 1823 | P13: 16987 | Q13: 1415.5833 | R13: 1
C14: Usuario | D14: 0 | E14: 0 | F14: 0 | G14: 0 | H14: 0 | I14: 0 | J14: 0 | K14: 0 | L14: 0 | M14: 0 | N14: 0 | O14: 0 | P14: 0 | Q14: 0 | R14: 0
B15: Total Banco Amazonas | D15: 2036 | E15: 1914 | F15: 1723 | G15: 851 | H15: 872 | I15: 1208 | J15: 1319 | K15: 1221 | L15: 1336 | M15: 1412 | N15: 1272 | O15: 1823 | P15: 16987 | Q15: 1415.5833 | R15: 1
B17: Banco del Austro | C17: Cliente | D17: 421019 | E17: 390681 | F17: 299695 | G17: 169404 | H17: 223574 | I17: 296123 | J17: 320620 | K17: 329040 | L17: 346681 | M17: 367261 | N17: 341624 | O17: 413328 | P17: 3919050 | Q17: 326587.5 | R17: 0.76205501
C18: Usuario | D18: 135475 | E18: 135666 | F18: 93400 | G18: 56060 | H18: 73003 | I18: 85012 | J18: 91085 | K18: 97644 | L18: 100567 | M18: 113124 | N18: 103806 | O18: 138847 | P18: 1223689 | Q18: 101974.08 | R18: 0.23794499
B19: Total Banco del Austro | D19: 556494 | E19: 526347 | F19: 393095 | G19: 225464 | H19: 296577 | I19: 381135 | J19: 411705 | K19: 426684 | L19: 447248 | M19: 480385 | N19: 445430 | O19: 552175 | P19: 5142739 | Q19: 428561.58 | R19: 1
B21: Banco de Guayaquil | C21: Cliente | D21: 2528322 | E21: 2292220 | F21: 2047059 | G21: 1240701 | H21: 1476417 | I21: 1974875 | J21: 2091564 | K21: 2134433 | L21: 2194868 | M21: 2308652 | N21: 2350380 | O21: 2784127 | P21: 25423618 | Q21: 2118634.8 | R21: 0.70040141
C22: Usuario | D22: 1108068 | E22: 1047188 | F22: 965094 | G22: 597932 | H22: 633453 | I22: 789791 | J22: 831785 | K22: 883242 | L22: 896091 | M22: 958635 | N22: 988004 | O22: 1175738 | P22: 10875021 | Q22: 906251.75 | R22: 0.29959859
B23: Total Banco de Guayaquil | D23: 3636390 | E23: 3339408 | F23: 3012153 | G23: 1838633 | H23: 2109870 | I23: 2764666 | J23: 2923349 | K23: 3017675 | L23: 3090959 | M23: 3267287 | N23: 3338384 | O23: 3959865 | P23: 36298639 | Q23: 3024886.6 | R23: 1
B25: Banco Bolivariano | C25: Cliente | D25: 1057706 | E25: 955626 | F25: 880658 | G25: 516274 | H25: 618676 | I25: 830574 | J25: 868213 | K25: 859148 | L25: 867082 | M25: 905001 | N25: 927723 | O25: 1111956 | P25: 10398637 | Q25: 866553.08 | R25: 0.78686991
C26: Usuario | D26: 293024 | E26: 258833 | F26: 232574 | G26: 176784 | H26: 202950 | I26: 221427 | J26: 216799 | K26: 221544 | L26: 225845 | M26: 234119 | N26: 239872 | O26: 292784 | P26: 2816555 | Q26: 234712.92 | R26: 0.21313009
B27: Total Banco Bolivariano | D27: 1350730 | E27: 1214459 | F27: 1113232 | G27: 693058 | H27: 821626 | I27: 1052001 | J27: 1085012 | K27: 1080692 | L27: 1092927 | M27: 1139120 | N27: 1167595 | O27: 1404740 | P27: 13215192 | Q27: 1101266 | R27: 1
B29: Citibank | C29: Cliente | D29: 0 | E29: 0 | F29: 0 | G29: 0 | H29: 0 | I29: 0 | J29: 0 | K29: 0 | L29: 0 | M29: 0 | N29: 0 | O29: 0 | P29: 0 | Q29: 0
C30: Usuario | D30: 0 | E30: 0 | F30: 0 | G30: 0 | H30: 0 | I30: 0 | J30: 0 | K30: 0 | L30: 0 | M30: 0 | N30: 0 | O30: 0 | P30: 0 | Q30: 0
B31: Total Banco Citibank | D31: 0 | E31: 0 | F31: 0 | G31: 0 | H31: 0 | I31: 0 | J31: 0 | K31: 0 | L31: 0 | M31: 0 | N31: 0 | O31: 0 | P31: 0 | Q31: 0
B33: Banco Comercial de Manabí | C33: Cliente | D33: 24402 | E33: 22557 | F33: 21476 | G33: 11553 | H33: 13818 | I33: 17573 | J33: 19505 | K33: 17080 | L33: 19493 | M33: 22145 | N33: 20270 | O33: 25652 | P33: 235524 | Q33: 19627 | R33: 0.64959773
C34: Usuario | D34: 12586 | E34: 11704 | F34: 11190 | G34: 8087 | H34: 10902 | I34: 10335 | J34: 9597 | K34: 8421 | L34: 10174 | M34: 10583 | N34: 10363 | O34: 13103 | P34: 127045 | Q34: 10587.083 | R34: 0.35040227
B35: Total Banco Comercial de Manabí | D35: 36988 | E35: 34261 | F35: 32666 | G35: 19640 | H35: 24720 | I35: 27908 | J35: 29102 | K35: 25501 | L35: 29667 | M35: 32728 | N35: 30633 | O35: 38755 | P35: 362569 | Q35: 30214.083 | R35: 1
B37: Banco del Litoral | C37: Cliente | D37: 4419 | E37: 5836 | F37: 3555 | G37: 2276 | H37: 2738 | I37: 3561 | J37: 3942 | K37: 3364 | L37: 3464 | M37: 3862 | N37: 3307 | O37: 4578 | P37: 44902 | Q37: 3741.8333 | R37: 1
C38: Usuario | D38: 0 | E38: 0 | F38: 0 | G38: 0 | H38: 0 | I38: 0 | J38: 0 | K38: 0 | L38: 0 | M38: 0 | N38: 0 | O38: 0 | P38: 0 | Q38: 0 | R38: 0
B39: Total Banco del Litoral | D39: 4419 | E39: 5836 | F39: 3555 | G39: 2276 | H39: 2738 | I39: 3561 | J39: 3942 | K39: 3364 | L39: 3464 | M39: 3862 | N39: 3307 | O39: 4578 | P39: 44902 | Q39: 3741.8333 | R39: 1
B41: Banco General Rumiñahui | C41: Cliente | D41: 224523 | E41: 216070 | F41: 170304 | G41: 109269 | H41: 136312 | I41: 151081 | J41: 162780 | K41: 176816 | L41: 192065 | M41: 207101 | N41: 167376 | O41: 248929 | P41: 2162626 | Q41: 180218.83 | R41: 0.76353694
C42: Usuario | D42: 65291 | E42: 59455 | F42: 48239 | G42: 39010 | H42: 46665 | I42: 49046 | J42: 50902 | K42: 54952 | L42: 57701 | M42: 61216 | N42: 58669 | O42: 78607 | P42: 669753 | Q42: 55812.75 | R42: 0.23646306
B43: Total Banco General Rumiñahui | D43: 289814 | E43: 275525 | F43: 218543 | G43: 148279 | H43: 182977 | I43: 200127 | J43: 213682 | K43: 231768 | L43: 249766 | M43: 268317 | N43: 226045 | O43: 327536 | P43: 2832379 | Q43: 236031.58 | R43: 1
B45: Banco Internacional | C45: Cliente | D45: 592202 | E45: 569695 | F45: 439016 | G45: 278742 | H45: 335463 | I45: 378057 | J45: 447558 | K45: 467489 | L45: 470450 | M45: 512808 | N45: 461827 | O45: 529975 | P45: 5483282 | Q45: 456940.17 | R45: 0.65688124
C46: Usuario | D46: 310793 | E46: 306509 | F46: 235942 | G46: 179289 | H46: 207180 | I46: 179703 | J46: 207674 | K46: 224736 | L46: 227319 | M46: 247235 | N46: 230815 | O46: 306971 | P46: 2864166 | Q46: 238680.5 | R46: 0.34311876
B47: Total Banco Internacional | D47: 902995 | E47: 876204 | F47: 674958 | G47: 458031 | H47: 542643 | I47: 557760 | J47: 655232 | K47: 692225 | L47: 697769 | M47: 760043 | N47: 692642 | O47: 836946 | P47: 8347448 | Q47: 695620.67 | R47: 1
B49: Banco de Loja | C49: Cliente | D49: 354913 | E49: 345136 | F49: 250333 | G49: 128765 | H49: 173071 | I49: 233500 | J49: 251400 | K49: 260839 | L49: 284672 | M49: 269509 | N49: 248919 | O49: 318619 | P49: 3119676 | Q49: 259973 | R49: 0.86932421
C50: Usuario | D50: 72959 | E50: 72447 | F50: 54422 | G50: 32221 | H50: 39739 | I50: 45017 | J50: 47121 | K50: 50162 | L50: 54858 | M50: 0 | N50: 0 | O50: 0 | P50: 468946 | Q50: 39078.833 | R50: 0.13067579
B51: Total Banco de Loja | D51: 427872 | E51: 417583 | F51: 304755 | G51: 160986 | H51: 212810 | I51: 278517 | J51: 298521 | K51: 311001 | L51: 339530 | M51: 269509 | N51: 248919 | O51: 318619 | P51: 3588622 | Q51: 299051.83 | R51: 1
B53: Banco de Machala | C53: Cliente | D53: 276022 | E53: 254243 | F53: 226726 | G53: 130050 | H53: 154212 | I53: 201490 | J53: 215784 | K53: 205458 | L53: 217427 | M53: 231463 | N53: 220376 | O53: 276519 | P53: 2609770 | Q53: 217480.83 | R53: 0.92616797
C54: Usuario | D54: 23027 | E54: 22236 | F54: 18370 | G54: 11822 | H54: 14393 | I54: 14931 | J54: 14606 | K54: 15820 | L54: 17009 | M54: 16962 | N54: 17016 | O54: 21853 | P54: 208045 | Q54: 17337.083 | R54: 0.073832029
B55: Total Banco de Machala | D55: 299049 | E55: 276479 | F55: 245096 | G55: 141872 | H55: 168605 | I55: 216421 | J55: 230390 | K55: 221278 | L55: 234436 | M55: 248425 | N55: 237392 | O55: 298372 | P55: 2817815 | Q55: 234817.92 | R55: 1
B57: Banco del Pacífico | C57: Cliente | D57: 2210947 | E57: 2118950 | F57: 1630887 | G57: 910491 | H57: 1193333 | I57: 1510571 | J57: 1665680 | K57: 1727098 | L57: 1815516 | M57: 1999242 | N57: 1831569 | O57: 2351982 | P57: 20966266 | Q57: 1747188.8 | R57: 0.74741122
C58: Usuario | D58: 702722 | E58: 701055 | F58: 563401 | G58: 465952 | H58: 552238 | I58: 528314 | J58: 532709 | K58: 530462 | L58: 557819 | M58: 620073 | N58: 572062 | O58: 758775 | P58: 7085582 | Q58: 590465.17 | R58: 0.25258878
B59: Total Banco del Pacífico | D59: 2913669 | E59: 2820005 | F59: 2194288 | G59: 1376443 | H59: 1745571 | I59: 2038885 | J59: 2198389 | K59: 2257560 | L59: 2373335 | M59: 2619315 | N59: 2403631 | O59: 3110757 | P59: 28051848 | Q59: 2337654 | R59: 1
B61: Banco Pichincha | C61: Cliente | D61: 8565021 | E61: 8366249 | F61: 6126825 | G61: 3344788 | H61: 4241529 | I61: 5770396 | J61: 6461359 | K61: 6759518 | L61: 7074410 | M61: 7935287 | N61: 7466693 | O61: 9094549 | P61: 81206624 | Q61: 6767218.7 | R61: 0.91572694
C62: Usuario | D62: 791877 | E62: 777278 | F62: 576067 | G62: 402761 | H62: 485543 | I62: 551007 | J62: 573029 | K62: 608665 | L62: 608329 | M62: 677478 | N62: 612739 | O62: 808558 | P62: 7473331 | Q62: 622777.58 | R62: 0.084273058
B63: Total Banco Pichincha | D63: 9356898 | E63: 9143527 | F63: 6702892 | G63: 3747549 | H63: 4727072 | I63: 6321403 | J63: 7034388 | K63: 7368183 | L63: 7682739 | M63: 8612765 | N63: 8079432 | O63: 9903107 | P63: 88679955 | Q63: 7389996.3 | R63: 1
B65: Banco Produbanco Grupo Promerica | C65: Cliente | D65: 1164355 | E65: 1123841 | F65: 822018 | G65: 452703 | H65: 558569 | I65: 741588 | J65: 811557 | K65: 858397 | L65: 864266 | M65: 949963 | N65: 863332 | O65: 2137379 | P65: 11347968 | Q65: 945664 | R65: 0.86768036
C66: Usuario | D66: 193279 | E66: 194288 | F66: 145941 | G66: 82450 | H66: 101353 | I66: 116021 | J66: 119712 | K66: 121310 | L66: 124388 | M66: 134749 | N66: 122969 | O66: 274084 | P66: 1730544 | Q66: 144212 | R66: 0.13231964
B67: Total Banco Produbanco Grupo Promerica | D67: 1357634 | E67: 1318129 | F67: 967959 | G67: 535153 | H67: 659922 | I67: 857609 | J67: 931269 | K67: 979707 | L67: 988654 | M67: 1084712 | N67: 986301 | O67: 2411463 | P67: 13078512 | Q67: 1089876 | R67: 1
B69: Banco Solidario | C69: Cliente | D69: 73669 | E69: 69642 | F69: 45812 | G69: 18144 | H69: 25346 | I69: 43733 | J69: 48918 | K69: 49647 | L69: 52802 | M69: 53798 | N69: 52752 | O69: 62510 | P69: 596773 | Q69: 49731.083 | R69: 0.84446102
C70: Usuario | D70: 11796 | E70: 11838 | F70: 9215 | G70: 5029 | H70: 6929 | I70: 8258 | J70: 7939 | K70: 8705 | L70: 9027 | M70: 7891 | N70: 9211 | O70: 14080 | P70: 109918 | Q70: 9159.8333 | R70: 0.15553898
B71: Total Banco Solidario | D71: 85465 | E71: 81480 | F71: 55027 | G71: 23173 | H71: 32275 | I71: 51991 | J71: 56857 | K71: 58352 | L71: 61829 | M71: 61689 | N71: 61963 | O71: 76590 | P71: 706691 | Q71: 58890.917 | R71: 1
B73: Banco Coopnacional | C73: Cliente | D73: 108524 | E73: 96850 | F73: 80882 | G73: 48106 | H73: 64534 | I73: 88278 | J73: 92482 | K73: 81442 | L73: 88894 | M73: 92258 | N73: 85319 | O73: 96629 | P73: 1024198 | Q73: 85349.833 | R73: 1
C74: Usuario | D74: 0 | E74: 0 | F74: 0 | G74: 0 | H74: 0 | I74: 0 | J74: 0 | K74: 0 | L74: 0 | M74: 0 | N74: 0 | O74: 0 | P74: 0 | Q74: 0 | R74: 0
B75: Total Banco Coopnacional | D75: 108524 | E75: 96850 | F75: 80882 | G75: 48106 | H75: 64534 | I75: 88278 | J75: 92482 | K75: 81442 | L75: 88894 | M75: 92258 | N75: 85319 | O75: 96629 | P75: 1024198 | Q75: 85349.833 | R75: 1
B77: Banco Procredit | C77: Cliente | D77: 15353 | E77: 14671 | F77: 10909 | G77: 5898 | H77: 7929 | I77: 9965 | J77: 10929 | K77: 11104 | L77: 12147 | M77: 13251 | N77: 11857 | O77: 15375 | P77: 139388 | Q77: 11615.667 | R77: 0.87356091
C78: Usuario | D78: 2434 | E78: 2790 | F78: 1652 | G78: 893 | H78: 1071 | I78: 1343 | J78: 1342 | K78: 1472 | L78: 1658 | M78: 1871 | N78: 1670 | O78: 1979 | P78: 20175 | Q78: 1681.25 | R78: 0.12643909
B79: Total Banco Procredit | D79: 17787 | E79: 17461 | F79: 12561 | G79: 6791 | H79: 9000 | I79: 11308 | J79: 12271 | K79: 12576 | L79: 13805 | M79: 15122 | N79: 13527 | O79: 17354 | P79: 159563 | Q79: 13296.917 | R79: 1
B81: Banco Capital | C81: Cliente | D81: 754 | E81: 656 | F81: 496 | G81: 318 | H81: 348 | I81: 443 | J81: 452 | K81: 520 | L81: 532 | M81: 554 | N81: 512 | O81: 723 | P81: 6308 | Q81: 525.66667 | R81: 1
C82: Usuario | D82: 0 | E82: 0 | F82: 0 | G82: 0 | H82: 0 | I82: 0 | J82: 0 | K82: 0 | L82: 0 | M82: 0 | N82: 0 | O82: 0 | P82: 0 | Q82: 0 | R82: 0
B83: Total Banco Capital | D83: 754 | E83: 656 | F83: 496 | G83: 318 | H83: 348 | I83: 443 | J83: 452 | K83: 520 | L83: 532 | M83: 554 | N83: 512 | O83: 723 | P83: 6308 | Q83: 525.66667 | R83: 1
B85: Banco Finca | C85: Cliente | D85: 5413 | E85: 5357 | F85: 4272 | G85: 2031 | H85: 2704 | I85: 3112 | J85: 3460 | K85: 3370 | L85: 4066 | M85: 4279 | N85: 3894 | O85: 4976 | P85: 46934 | Q85: 3911.1667 | R85: 1
C86: Usuario | D86: 0 | E86: 0 | F86: 0 | G86: 0 | H86: 0 | I86: 0 | J86: 0 | K86: 0 | L86: 0 | M86: 0 | N86: 0 | O86: 0 | P86: 0 | Q86: 0 | R86: 0
B87: Total Banco Finca | D87: 5413 | E87: 5357 | F87: 4272 | G87: 2031 | H87: 2704 | I87: 3112 | J87: 3460 | K87: 3370 | L87: 4066 | M87: 4279 | N87: 3894 | O87: 4976 | P87: 46934 | Q87: 3911.1667 | R87: 1
B89: Banco Delbank | C89: Cliente | D89: 6478 | E89: 5786 | F89: 4513 | G89: 2712 | H89: 3431 | I89: 4890 | J89: 5282 | K89: 4854 | L89: 5189 | M89: 5630 | N89: 5026 | O89: 5954 | P89: 59745 | Q89: 4978.75 | R89: 0.91188681
C90: Usuario | D90: 707 | E90: 622 | F90: 362 | G90: 124 | H90: 217 | I90: 355 | J90: 558 | K90: 496 | L90: 498 | M90: 559 | N90: 517 | O90: 758 | P90: 5773 | Q90: 481.08333 | R90: 0.08811319
B91: Total Banco Delbank | D91: 7185 | E91: 6408 | F91: 4875 | G91: 2836 | H91: 3648 | I91: 5245 | J91: 5840 | K91: 5350 | L91: 5687 | M91: 6189 | N91: 5543 | O91: 6712 | P91: 65518 | Q91: 5459.8333 | R91: 1
B93: Banco Dmiro | C93: Cliente | D93: 6937 | E93: 6512 | F93: 4755 | G93: 1394 | H93: 1761 | I93: 2973 | J93: 4138 | K93: 4088 | L93: 4389 | M93: 4838 | N93: 4273 | O93: 5334 | P93: 51392 | Q93: 4282.6667 | R93: 1
C94: Usuario | D94: 0 | E94: 0 | F94: 0 | G94: 0 | H94: 0 | I94: 0 | J94: 0 | K94: 0 | L94: 0 | M94: 0 | N94: 0 | O94: 0 | P94: 0 | Q94: 0 | R94: 0
B95: Total Banco Dmiro | D95: 6937 | E95: 6512 | F95: 4755 | G95: 1394 | H95: 1761 | I95: 2973 | J95: 4138 | K95: 4088 | L95: 4389 | M95: 4838 | N95: 4273 | O95: 5334 | P95: 51392 | Q95: 4282.6667 | R95: 1
B97: Banco Desarrollo de los Pueblos | C97: Cliente | D97: 28436 | E97: 25815 | F97: 20411 | G97: 12077 | H97: 13770 | I97: 18714 | J97: 19430 | K97: 19443 | L97: 21203 | M97: 23155 | N97: 20686 | O97: 26376 | P97: 249516 | Q97: 20793 | R97: 0.76175996
C98: Usuario | D98: 6781 | E98: 6658 | F98: 5667 | G98: 5641 | H98: 6780 | I98: 6351 | J98: 6074 | K98: 6523 | L98: 6130 | M98: 6730 | N98: 6706 | O98: 7995 | P98: 78036 | Q98: 6503 | R98: 0.23824004
B99: Total Banco Desarrollo de los Pueblos | D99: 35217 | E99: 32473 | F99: 26078 | G99: 17718 | H99: 20550 | I99: 25065 | J99: 25504 | K99: 25966 | L99: 27333 | M99: 29885 | N99: 27392 | O99: 34371 | P99: 327552 | Q99: 27296 | R99: 1
B101: Banco Visionfund | C101: Cliente | D101: 8102 | E101: 7451 | F101: 4897 | G101: 1560 | H101: 1751 | I101: 2425 | J101: 5520 | K101: 6735 | L101: 7394 | M101: 7554 | N101: 7423 | O101: 8665 | P101: 69477 | Q101: 5789.75 | R101: 1
C102: Usuario | D102: 0 | E102: 0 | F102: 0 | G102: 0 | H102: 0 | I102: 0 | J102: 0 | K102: 0 | L102: 0 | M102: 0 | N102: 0 | O102: 0 | P102: 0 | Q102: 0 | R102: 0
B103: Total Banco Visionfund | D103: 8102 | E103: 7451 | F103: 4897 | G103: 1560 | H103: 1751 | I103: 2425 | J103: 5520 | K103: 6735 | L103: 7394 | M103: 7554 | N103: 7423 | O103: 8665 | P103: 69477 | Q103: 5789.75 | R103: 1
B105: Diners Club | C105: Cliente | D105: 0 | E105: 0 | F105: 0 | G105: 0 | H105: 0 | I105: 0 | J105: 0 | K105: 0 | L105: 0 | M105: 0 | N105: 0 | O105: 0 | P105: 0 | Q105: 0
C106: Usuario | D106: 0 | E106: 0 | F106: 0 | G106: 0 | H106: 0 | I106: 0 | J106: 0 | K106: 0 | L106: 0 | M106: 0 | N106: 0 | O106: 0 | P106: 0 | Q106: 0
B107: Total Diners Club | D107: 0 | E107: 0 | F107: 0 | G107: 0 | H107: 0 | I107: 0 | J107: 0 | K107: 0 | L107: 0 | M107: 0 | N107: 0 | O107: 0 | P107: 0 | Q107: 0
B109: Servipagos | C109: Cliente | D109: 0 | E109: 0 | F109: 0 | G109: 0 | H109: 0 | I109: 0 | J109: 0 | K109: 0 | L109: 0 | M109: 0 | N109: 0 | O109: 0 | Q109: 0 | R109: 0
C110: Usuario | D110: 134279 | E110: 132045 | F110: 76573 | G110: 12642 | H110: 26315 | I110: 65330 | J110: 74841 | K110: 82202 | L110: 83161 | M110: 92640 | N110: 81381 | O110: 99360 | P110: 960769 | Q110: 80064.083 | R110: 1
B111: Total Servipagos | D111: 134279 | E111: 132045 | F111: 76573 | G111: 12642 | H111: 26315 | I111: 65330 | J111: 74841 | K111: 82202 | L111: 83161 | M111: 92640 | N111: 81381 | O111: 99360 | P111: 960769 | Q111: 80064.083 | R111: 1
B113: Total | D113: 21544651 | E113: 20636370 | F113: 16135331 | G113: 9464804 | H113: 11658889 | I113: 14957371 | J113: 16297665 | K113: 16897460 | L113: 17528920 | M113: 19102888 | N113: 18152210 | O113: 23519450 | P113: 2.0589601e+08 | Q113: 17158001 | R113: 1
B115: 8.2 Evolución del Monto de Retiros de Dinero por Entidad Financiera por Ordenante
B116: (en dólares)
B117: Entidad Financiera | C117: Ordenante | D117: Enero | E117: Febrero | F117: Marzo | G117: Abril | H117: Mayo | I117: Junio | J117: Julio | K117: Agosto | L117: Septiembre | M117: Octubre | N117: Noviembre | O117: Diciembre | P117: Total | Q117: Promedio | R117: Promedio
B118: Banco Amazonas | C118: Cliente | D118: 1158491.7 | E118: 971326.14 | F118: 1017495.6 | G118: 515735.66 | H118: 617369.55 | I118: 603919.85 | J118: 619730.51 | K118: 563372.3 | L118: 641498.7 | M118: 608069.8 | N118: 654451.59 | O118: 987649 | P118: 8959110.3 | Q118: 746592.53 | R118: 1
C119: Usuario | D119: 0 | E119: 0 | F119: 0 | G119: 0 | H119: 0 | I119: 0 | J119: 0 | K119: 0 | L119: 0 | M119: 0 | N119: 0 | O119: 0 | P119: 0 | Q119: 0 | R119: 0
B120: Total Banco Amazonas | D120: 1158491.7 | E120: 971326.14 | F120: 1017495.6 | G120: 515735.66 | H120: 617369.55 | I120: 603919.85 | J120: 619730.51 | K120: 563372.3 | L120: 641498.7 | M120: 608069.8 | N120: 654451.59 | O120: 987649 | P120: 8959110.3 | Q120: 746592.53 | R120: 1
B122: Banco del Austro | C122: Cliente | D122: 1.2652653e+08 | E122: 1.1348792e+08 | F122: 97182970 | G122: 53443180 | H122: 65062989 | I122: 88724025 | J122: 97805778 | K122: 99415398 | L122: 1.0830634e+08 | M122: 1.090612e+08 | N122: 98531553 | O122: 1.2606912e+08 | P122: 1.183617e+09 | Q122: 98634750 | R122: 0.92462723
C123: Usuario | D123: 10005670 | E123: 10088645 | F123: 7559980 | G123: 5088160 | H123: 6524445 | I123: 7120205 | J123: 7453090 | K123: 7755920 | L123: 7809850 | M123: 8489315 | N123: 7739315 | O123: 10850220 | P123: 96484815 | Q123: 8040401.3 | R123: 0.075372767
B124: Total Banco del Austro | D124: 1.365322e+08 | E124: 1.2357656e+08 | F124: 1.0474295e+08 | G124: 58531340 | H124: 71587434 | I124: 95844230 | J124: 1.0525887e+08 | K124: 1.0717132e+08 | L124: 1.1611619e+08 | M124: 1.1755051e+08 | N124: 1.0627087e+08 | O124: 1.3691934e+08 | P124: 1.2801018e+09 | Q124: 1.0667515e+08 | R124: 1
B126: Banco de Guayaquil | C126: Cliente | D126: 3.4506671e+08 | E126: 2.9199434e+08 | F126: 2.8096193e+08 | G126: 1.8691965e+08 | H126: 2.0784627e+08 | I126: 2.4664078e+08 | J126: 2.6326405e+08 | K126: 2.4764076e+08 | L126: 2.7106348e+08 | M126: 2.8365277e+08 | N126: 2.8019493e+08 | O126: 3.6960611e+08 | P126: 3.2748518e+09 | Q126: 2.7290431e+08 | R126: 0.82920863
C127: Usuario | D127: 64159170 | E127: 61619020 | F127: 60420040 | G127: 41582075 | H127: 42781925 | I127: 49439745 | J127: 51701815 | K127: 54191835 | L127: 54621050 | M127: 58404920 | N127: 59830195 | O127: 75766525 | P127: 6.7451831e+08 | Q127: 56209860 | R127: 0.17079137
B128: Total Banco de Guayaquil | D128: 4.0922588e+08 | E128: 3.5361336e+08 | F128: 3.4138197e+08 | G128: 2.2850172e+08 | H128: 2.5062819e+08 | I128: 2.9608052e+08 | J128: 3.1496587e+08 | K128: 3.0183259e+08 | L128: 3.2568453e+08 | M128: 3.4205769e+08 | N128: 3.4002513e+08 | O128: 4.4537263e+08 | P128: 3.9493701e+09 | Q128: 3.2911417e+08 | R128: 1
B130: Banco Bolivariano | C130: Cliente | D130: 2.0762657e+08 | E130: 1.869374e+08 | F130: 1.91936e+08 | G130: 1.4012007e+08 | H130: 1.4117622e+08 | I130: 1.7482645e+08 | J130: 1.789552e+08 | K130: 1.7098456e+08 | L130: 1.7833051e+08 | M130: 1.8868764e+08 | N130: 1.8737949e+08 | O130: 2.460058e+08 | P130: 2.1929659e+09 | Q130: 1.8274716e+08 | R130: 0.9250621
C131: Usuario | D131: 17585655 | E131: 15524265 | F131: 14986420 | G131: 12779670 | H131: 14162785 | I131: 14108460 | J131: 13512195 | K131: 13544190 | L131: 13751195 | M131: 14202210 | N131: 14550590 | O131: 18941270 | P131: 1.776489e+08 | Q131: 14804075 | R131: 0.074937904
B132: Total Banco Bolivariano | D132: 2.2521223e+08 | E132: 2.0246167e+08 | F132: 2.0692242e+08 | G132: 1.5289974e+08 | H132: 1.5533901e+08 | I132: 1.8893491e+08 | J132: 1.924674e+08 | K132: 1.8452875e+08 | L132: 1.920817e+08 | M132: 2.0288985e+08 | N132: 2.0193008e+08 | O132: 2.6494707e+08 | P132: 2.3706148e+09 | Q132: 1.9755123e+08 | R132: 1
...

Sheet SECCIÓN IX
B1: SUPERINTENDENCIA DE BANCOS DEL ECUADOR INTENDENCIA NACIONAL DE RIESGOS Y ESTUDIOS DIRECCIÓN DE ESTUDIOS Y GESTIÓN DE LA INFORMACIÓN SUBDIRECCIÓN DE ESTADÍSTICAS Y ESTUDIOS
B3: ESTADÍSTICAS DE RETIROS DE DINERO EN EFECTIVO SOBRE CUENTAS DE AHORRO EN CANALES PROPIOS DE LA ENTIDAD
B4: Enero a Diciembre 2020
B5: Fecha de publicación: Enero 2021
B6: Datos Provisionales
B8: SECCIÓN IX: RETIROS DE DINERO POR CANAL POR PROVINCIA
B10: 9.1 Evolución de Transacciones de Retiros de Dinero por Canal por Provincia
C11: 2 | D11: 3 | E11: 4 | F11: 5 | G11: 6 | H11: 7 | I11: 8 | J11: 9 | K11: 10 | L11: 11 | M11: 12 | N11: 13 | O11: 14 | P11: 15
B12: Canal | C12: Provincia | D12: Enero | E12: Febrero | F12: Marzo | G12: Abril | H12: Mayo | I12: Junio | J12: Julio | K12: Agosto | L12: Septiembre | M12: Octubre | N12: Noviembre | O12: Diciembre | P12: Total | Q12: Promedio | R12: % Número de retiros
B13: Cajero Automático | C13: Azuay | D13: 458105 | E13: 430274 | F13: 314185 | G13: 181015 | H13: 232003 | I13: 296393 | J13: 731781 | K13: 348336 | L13: 779759 | M13: 398128 | N13: 379214 | O13: 497458 | P13: 5046651 | Q13: 420554.25 | R13: 0.035526979
C14: Bolívar | D14: 61442 | E14: 65505 | F14: 39043 | G14: 25868 | H14: 31258 | I14: 37488 | J14: 40435 | K14: 46389 | L14: 46061 | M14: 50807 | N14: 41742 | O14: 62166 | P14: 548204 | Q14: 45683.667 | R14: 0.0038591993
C15: Cañar | D15: 93410 | E15: 83731 | F15: 67675 | G15: 44019 | H15: 54875 | I15: 66149 | J15: 71447 | K15: 77375 | L15: 72529 | M15: 83226 | N15: 79597 | O15: 98068 | P15: 892101 | Q15: 74341.75 | R15: 0.0062801358
C16: Carchi | D16: 78269 | E16: 78175 | F16: 60029 | G16: 34527 | H16: 42347 | I16: 53813 | J16: 61631 | K16: 67383 | L16: 70182 | M16: 68567 | N16: 71224 | O16: 90676 | P16: 776823 | Q16: 64735.25 | R16: 0.0054686117
C17: Cotopaxi | D17: 248297 | E17: 239750 | F17: 184429 | G17: 112111 | H17: 137901 | I17: 163842 | J17: 175379 | K17: 201453 | L17: 195762 | M17: 229136 | N17: 211114 | O17: 275340 | P17: 2374514 | Q17: 197876.17 | R17: 0.016715899
C18: Chimborazo | D18: 263738 | E18: 258748 | F18: 177057 | G18: 98008 | H18: 123128 | I18: 160860 | J18: 154317 | K18: 180980 | L18: 161694 | M18: 200715 | N18: 190932 | O18: 247643 | P18: 2217820 | Q18: 184818.33 | R18: 0.015612818
C19: El Oro | D19: 420688 | E19: 426326 | F19: 352333 | G19: 207289 | H19: 260311 | I19: 320209 | J19: 338006 | K19: 355005 | L19: 362335 | M19: 405223 | N19: 391355 | O19: 492567 | P19: 4331647 | Q19: 360970.58 | R19: 0.030493556
C20: Esmeraldas | D20: 294731 | E20: 308410 | F20: 256482 | G20: 169375 | H20: 199714 | I20: 215849 | J20: 232380 | K20: 240557 | L20: 252734 | M20: 308767 | N20: 258342 | O20: 396241 | P20: 3133582 | Q20: 261131.83 | R20: 0.022059521
C21: Guayas | D21: 4277510 | E21: 4027543 | F21: 3466817 | G21: 2082006 | H21: 2582884 | I21: 3295148 | J21: 3192726 | K21: 3515317 | L21: 3206266 | M21: 3919581 | N21: 3784310 | O21: 5014431 | P21: 42364539 | Q21: 3530378.3 | R21: 0.29823423
C22: Imbabura | D22: 336601 | E22: 341545 | F22: 244775 | G22: 139035 | H22: 173070 | I22: 223574 | J22: 248409 | K22: 270395 | L22: 263418 | M22: 289111 | N22: 277959 | O22: 368500 | P22: 3176392 | Q22: 264699.33 | R22: 0.022360891
C23: Loja | D23: 403777 | E23: 392825 | F23: 287207 | G23: 149756 | H23: 204782 | I23: 274119 | J23: 291161 | K23: 310184 | L23: 333614 | M23: 326311 | N23: 302390 | O23: 390105 | P23: 3666231 | Q23: 305519.25 | R23: 0.025809217
C24: Los Ríos | D24: 601303 | E24: 588482 | F24: 529544 | G24: 359667 | H24: 425388 | I24: 479609 | J24: 508991 | K24: 522579 | L24: 528440 | M24: 592851 | N24: 563906 | O24: 741771 | P24: 6442531 | Q24: 536877.58 | R24: 0.045353575
C25: Manabí | D25: 886585 | E25: 879908 | F25: 712783 | G25: 426415 | H25: 499554 | I25: 595887 | J25: 676262 | K25: 689099 | L25: 715478 | M25: 822916 | N25: 758578 | O25: 1008094 | P25: 8671559 | Q25: 722629.92 | R25: 0.061045295
... C36: Santa Elena | D36: 247541 | E36: 257565 | F36: 203423 | G36: 126105 | H36: 143479 | I36: 173728 | J36: 190353 | K36: 190478 | L36: 209980 | M36: 237982 | N36: 221497 | O36: 279425 | P36: 2481556 | Q36: 206796.33 | R36: 0.017469444
B37: Total Cajero Automático | D37: 15002936 | E37: 14474861 | F37: 11357557 | G37: 6585609 | H37: 8051740 | I37: 10170243 | J37: 11045419 | K37: 11519404 | L37: 11808526 | M37: 13009865 | N37: 12402841 | O37: 16622226 | P37: 1.4205123e+08 | Q37: 11837602 | R37: 1
B39: Cajero Automático Plus | C39: Azuay | D39: 39651 | E39: 36292 | F39: 24341 | G39: 12387 | H39: 17968 | I39: 22731 | J39: 24529 | K39: 25980 | L39: 27506 | M39: 29590 | N39: 28316 | O39: 34222 | P39: 323513 | Q39: 26959.417 | R39: 0.02835852
C40: Bolívar | D40: 0 | E40: 0 | F40: 0 | G40: 0 | H40: 0 | I40: 0 | J40: 0 | K40: 0 | L40: 0 | M40: 0 | N40: 0 | O40: 0 | P40: 0 | Q40: 0 | R40: 0
C41: Cañar | D41: 10237 | E41: 13231 | F41: 11627 | G41: 8276 | H41: 10012 | I41: 12265 | J41: 12783 | K41: 13301 | L41: 13859 | M41: 14914 | N41: 13192 | O41: 16829 | P41: 150526 | Q41: 12543.833 | R41: 0.013194816
C42: Carchi | D42: 1978 | E42: 1010 | F42: 1121 | G42: 707 | H42: 842 | I42: 745 | J42: 992 | K42: 624 | L42: 988 | M42: 880 | N42: 1865 | O42: 2289 | P42: 14041 | Q42: 1170.0833 | R42: 0.0012308067
C43: Cotopaxi | D43: 7313 | E43: 7399 | F43: 5714 | G43: 3435 | H43: 4345 | I43: 5113 | J43: 5630 | K43: 6258 | L43: 6822 | M43: 7289 | N43: 7164 | O43: 8877 | P43: 75359 | Q43: 6279.9167 | R43: 0.0066058232
C44: Chimborazo | D44: 48528 | E44: 48448 | F44: 35306 | G44: 25493 | H44: 33712 | I44: 39914 | J44: 42425 | K44: 49742 | L44: 54043 | M44: 60677 | N44: 54487 | O44: 66073 | P44: 558848 | Q44: 46570.667 | R44: 0.048987528
C45: El Oro | D45: 21136 | E45: 21250 | F45: 18504 | G45: 13365 | H45: 17908 | I45: 17726 | J45: 19260 | K45: 19787 | L45: 19470 | M45: 22608 | N45: 22266 | O45: 29619 | P45: 242899 | Q45: 20241.583 | R45: 0.021292053
C46: Esmeraldas | D46: 12632 | E46: 12641 | F46: 11372 | G46: 8820 | H46: 8751 | I46: 9193 | J46: 10615 | K46: 11066 | L46: 11355 | M46: 10940 | N46: 5786 | O46: 8705 | P46: 121876 | Q46: 10156.333 | R46: 0.010683413
C47: Guayas | D47: 450420 | E47: 426826 | F47: 352738 | G47: 255641 | H47: 337474 | I47: 368823 | J47: 404963 | K47: 416022 | L47: 436375 | M47: 484945 | N47: 453286 | O47: 595843 | P47: 4983356 | Q47: 415279.67 | R47: 0.43683128
C48: Imbabura | D48: 35008 | E48: 35970 | F48: 22953 | G48: 8016 | H48: 10292 | I48: 17796 | J48: 20032 | K48: 27723 | L48: 34740 | M48: 41846 | N48: 39027 | O48: 49281 | P48: 342684 | Q48: 28557 | R48: 0.030039012
C49: Loja | D49: 0 | E49: 0 | F49: 0 | G49: 0 | H49: 0 | I49: 0 | J49: 0 | K49: 0 | L49: 0 | M49: 0 | N49: 0 | O49: 0 | P49: 0 | Q49: 0 | R49: 0
C50: Los Ríos | D50: 39730 | E50: 41964 | F50: 37297 | G50: 33912 | H50: 39729 | I50: 40156 | J50: 40646 | K50: 40551 | L50: 41826 | M50: 47898 | N50: 42674 | O50: 58028 | P50: 504411 | Q50: 42034.25 | R50: 0.044215686
C51: Manabí | D51: 106391 | E51: 104548 | F51: 92328 | G51: 66328 | H51: 80574 | I51: 87984 | J51: 95234 | K51: 94662 | L51: 94553 | M51: 109678 | N51: 101098 | O51: 136710 | P51: 1170088 | Q51: 97507.333 | R51: 0.10256764
... C62: Santa Elena | D62: 14808 | E62: 14964 | F62: 12454 | G62: 9118 | H62: 11055 | I62: 10900 | J62: 13249 | K62: 12575 | L62: 12779 | M62: 14386 | N62: 17589 | O62: 29227 | P62: 173104 | Q62: 14425.333 | R62: 0.01517396
B63: Total Cajero Automático Plus | D63: 1061580 | E63: 1030535 | F63: 823295 | G63: 563150 | H63: 718275 | I63: 811461 | J63: 883216 | K63: 937020 | L63: 1002649 | M63: 1126218 | N63: 1059601 | O63: 1390965 | P63: 11407965 | Q63: 950663.75 | R63: 1
B65: Cajero Automático Móvil | C65: Azuay | D65: 0 | E65: 0 | F65: 0 | G65: 0 | H65: 0 | I65: 0 | J65: 0 | K65: 0 | L65: 0 | M65: 0 | N65: 0 | O65: 0 | P65: 0 | Q65: 0
C66: Bolívar | D66: 0 | E66: 0 | F66: 0 | G66: 0 | H66: 0 | I66: 0 | J66: 0 | K66: 0 | L66: 0 | M66: 0 | N66: 0 | O66: 0 | P66: 0 | Q66: 0
C67: Cañar | D67: 0 | E67: 0 | F67: 0 | G67: 0 | H67: 0 | I67: 0 | J67: 0 | K67: 0 | L67: 0 | M67: 0 | N67: 0 | O67: 0 | P67: 0 | Q67: 0
C68: Carchi | D68: 0 | E68: 0 | F68: 0 | G68: 0 | H68: 0 | I68: 0 | J68: 0 | K68: 0 | L68: 0 | M68: 0 | N68: 0 | O68: 0 | P68: 0 | Q68: 0
C69: Cotopaxi | D69: 0 | E69: 0 | F69: 0 | G69: 0 | H69: 0 | I69: 0 | J69: 0 | K69: 0 | L69: 0 | M69: 0 | N69: 0 | O69: 0 | P69: 0 | Q69: 0
C70: Chimborazo | D70: 0 | E70: 0 | F70: 0 | G70: 0 | H70: 0 | I70: 0 | J70: 0 | K70: 0 | L70: 0 | M70: 0 | N70: 0 | O70: 0 | P70: 0 | Q70: 0
C71: El Oro | D71: 0 | E71: 0 | F71: 0 | G71: 0 | H71: 0 | I71: 0 | J71: 0 | K71: 0 | L71: 0 | M71: 0 | N71: 0 | O71: 0 | P71: 0 | Q71: 0
C72: Esmeraldas | D72: 0 | E72: 0 | F72: 0 | G72: 0 | H72: 0 | I72: 0 | J72: 0 | K72: 0 | L72: 0 | M72: 0 | N72: 0 | O72: 0 | P72: 0 | Q72: 0
C73: Guayas | D73: 0 | E73: 0 | F73: 0 | G73: 0 | H73: 0 | I73: 0 | J73: 0 | K73: 0 | L73: 0 | M73: 0 | N73: 0 | O73: 0 | P73: 0 | Q73: 0
C74: Imbabura | D74: 0 | E74: 0 | F74: 0 | G74: 0 | H74: 0 | I74: 0 | J74: 0 | K74: 0 | L74: 0 | M74: 0 | N74: 0 | O74: 0 | P74: 0 | Q74: 0
C75: Loja | D75: 0 | E75: 0 | F75: 0 | G75: 0 | H75: 0 | I75: 0 | J75: 0 | K75: 0 | L75: 0 | M75: 0 | N75: 0 | O75: 0 | P75: 0 | Q75: 0
C76: Los Ríos | D76: 0 | E76: 0 | F76: 0 | G76: 0 | H76: 0 | I76: 0 | J76: 0 | K76: 0 | L76: 0 | M76: 0 | N76: 0 | O76: 0 | P76: 0 | Q76: 0
C77: Manabí | D77: 0 | E77: 0 | F77: 0 | G77: 0 | H77: 0 | I77: 0 | J77: 0 | K77: 0 | L77: 0 | M77: 0 | N77: 0 | O77: 0 | P77: 0 | Q77: 0
... C88: Santa Elena | D88: 0 | E88: 0 | F88: 0 | G88: 0 | H88: 0 | I88: 0 | J88: 0 | K88: 0 | L88: 0 | M88: 0 | N88: 0 | O88: 0 | P88: 0 | Q88: 0
B89: Total Cajero Automático Móvil | D89: 0 | E89: 0 | F89: 0 | G89: 0 | H89: 0 | I89: 0 | J89: 0 | K89: 0 | L89: 0 | M89: 0 | N89: 0 | O89: 0 | P89: 0 | Q89: 0
B91: Corresponsal No Bancario | C91: Azuay | D91: 36155 | E91: 32704 | F91: 24206 | G91: 14492 | H91: 18979 | I91: 25277 | J91: 27019 | K91: 28308 | L91: 28650 | M91: 30459 | N91: 29930 | O91: 33862 | P91: 330041 | Q91: 27503.417 | R91: 0.01213222
C92: Bolívar | D92: 20299 | E92: 20699 | F92: 13949 | G92: 6914 | H92: 8997 | I92: 11913 | J92: 14468 | K92: 15820 | L92: 16037 | M92: 18215 | N92: 18283 | O92: 21054 | P92: 186648 | Q92: 15554 | R92: 0.0068611313
C93: Cañar | D93: 6995 | E93: 6348 | F93: 4564 | G93: 2849 | H93: 4116 | I93: 5530 | J93: 7512 | K93: 8318 | L93: 9277 | M93: 9425 | N93: 8555 | O93: 10023 | P93: 83512 | Q93: 6959.3333 | R93: 0.0030698791
C94: Carchi | D94: 23658 | E94: 24414 | F94: 16690 | G94: 10761 | H94: 13175 | I94: 17840 | J94: 19750 | K94: 21351 | L94: 22298 | M94: 29103 | N94: 24875 | O94: 28170 | P94: 252085 | Q94: 21007.083 | R94: 0.0092665782
C95: Cotopaxi | D95: 62756 | E95: 61346 | F95: 44281 | G95: 30456 | H95: 35045 | I95: 46157 | J95: 54149 | K95: 58887 | L95: 58514 | M95: 65731 | N95: 61047 | O95: 71106 | P95: 649475 | Q95: 54122.917 | R95: 0.02387453
C96: Chimborazo | D96: 47824 | E96: 45291 | F96: 17329 | G96: 8735 | H96: 12505 | I96: 18209 | J96: 21191 | K96: 21954 | L96: 23096 | M96: 23545 | N96: 24797 | O96: 29052 | P96: 293528 | Q96: 24460.667 | R96: 0.010790012
C97: El Oro | D97: 55794 | E97: 48728 | F97: 37377 | G97: 22632 | H97: 31059 | I97: 41868 | J97: 46220 | K97: 48628 | L97: 50107 | M97: 55585 | N97: 54719 | O97: 60674 | P97: 553391 | Q97: 46115.917 | R97: 0.020342507
C98: Esmeraldas | D98: 135788 | E98: 139578 | F98: 113215 | G98: 86670 | H98: 95789 | I98: 117118 | J98: 128732 | K98: 132978 | L98: 134015 | M98: 146730 | N98: 111656 | O98: 169798 | P98: 1512067 | Q98: 126005.58 | R98: 0.055583185
C99: Guayas | D99: 454324 | E99: 427422 | F99: 371265 | G99: 267544 | H99: 345311 | I99: 417536 | J99: 462544 | K99: 474391 | L99: 487570 | M99: 520022 | N99: 507387 | O99: 596827 | P99: 5332143 | Q99: 444345.25 | R99: 0.19600817
C100: Imbabura | D100: 55518 | E100: 52804 | F100: 37504 | G100: 24544 | H100: 29455 | I100: 39434 | J100: 46474 | K100: 49490 | L100: 52064 | M100: 56506 | N100: 52598 | O100: 60256 | P100: 556647 | Q100: 46387.25 | R100: 0.020462197
C101: Loja | D101: 26021 | E101: 25019 | F101: 17237 | G101: 7805 | H101: 12944 | I101: 18303 | J101: 17617 | K101: 20334 | L101: 21465 | M101: 23593 | N101: 22714 | O101: 26176 | P101: 239228 | Q101: 19935.667 | R101: 0.0087939583
C102: Los Ríos | D102: 146503 | E102: 138762 | F102: 118463 | G102: 76771 | H102: 101061 | I102: 124313 | J102: 137107 | K102: 139566 | L102: 136180 | M102: 154580 | N102: 147729 | O102: 175536 | P102: 1596571 | Q102: 133047.58 | R102: 0.058689529
C103: Manabí | D103: 193453 | E103: 189075 | F103: 149738 | G103: 102499 | H103: 119539 | I103: 152752 | J103: 169611 | K103: 181518 | L103: 193039 | M103: 214430 | N103: 203238 | O103: 240485 | P103: 2109377 | Q103: 175781.42 | R103: 0.077540143
... C114: Santa Elena | D114: 42061 | E114: 40252 | F114: 35144 | G114: 23785 | H114: 28064 | I114: 36299 | J114: 40810 | K114: 41819 | L114: 43112 | M114: 45962 | N114: 44680 | O114: 50624 | P114: 472612 | Q114: 39384.333 | R114: 0.017373093
B115: Total Corresponsal No Bancario | D115: 2421834 | E115: 2375742 | F115: 1844106 | G115: 1280021 | H115: 1589520 | I115: 2040228 | J115: 2275250 | K115: 2402410 | L115: 2496329 | M115: 2739326 | N115: 2628632 | O115: 3110279 | P115: 27203677 | Q115: 2266973.1 | R115: 1
B117: Oficina / Ventanilla | C117: Azuay | D117: 155454 | E117: 145338 | F117: 101921 | G117: 49912 | H117: 68457 | I117: 97187 | J117: 105405 | K117: 102184 | L117: 109567 | M117: 108988 | N117: 101732 | O117: 119838 | P117: 1265983 | Q117: 105498.58 | R117: 0.050678565
C118: Bolívar | D118: 20071 | E118: 18157 | F118: 13494 | G118: 8241 | H118: 9628 | I118: 14194 | J118: 14903 | K118: 14278 | L118: 15881 | M118: 16043 | N118: 15556 | O118: 19016 | P118: 179462 | Q118: 14955.167 | R118: 0.0071840433
C119: Cañar | D119: 44770 | E119: 39793 | F119: 30927 | G119: 16936 | H119: 21806 | I119: 31638 | J119: 33134 | K119: 30763 | L119: 34496 | M119: 35436 | N119: 31791 | O119: 36934 | P119: 388424 | Q119: 32368.667 | R119: 0.015549001
C120: Carchi | D120: 20792 | E120: 19206 | F120: 14342 | G120: 6764 | H120: 8323 | I120: 13418 | J120: 14447 | K120: 14174 | L120: 16124 | M120: 17592 | N120: 15512 | O120: 18713 | P120: 179407 | Q120: 14950.583 | R120: 0.0071818416
C121: Cotopaxi | D121: 54591 | E121: 48721 | F121: 37759 | G121: 18492 | H121: 21438 | I121: 31438 | J121: 34676 | K121: 32987 | L121: 38650 | M121: 39862 | N121: 36077 | O121: 44914 | P121: 439605 | Q121: 36633.75 | R121: 0.017597828
C122: Chimborazo | D122: 58768 | E122: 52261 | F122: 39216 | G122: 18881 | H122: 24228 | I122: 37459 | J122: 39787 | K122: 39511 | L122: 43029 | M122: 44580 | N122: 41487 | O122: 49599 | P122: 488806 | Q122: 40733.833 | R122: 0.019567393
C123: El Oro | D123: 148778 | E123: 128325 | F123: 107574 | G123: 54033 | H123: 64224 | I123: 93260 | J123: 101665 | K123: 94834 | L123: 105362 | M123: 110536 | N123: 103109 | O123: 124989 | P123: 1236689 | Q123: 103057.42 | R123: 0.049505897
C124: Esmeraldas | D124: 50167 | E124: 46744 | F124: 37941 | G124: 21816 | H124: 25093 | I124: 36127 | J124: 38266 | K124: 35283 | L124: 38591 | M124: 40996 | N124: 34912 | O124: 44085 | P124: 450021 | Q124: 37501.75 | R124: 0.018014791
C125: Guayas | D125: 870068 | E125: 774893 | F125: 652828 | G125: 349877 | H125: 460860 | I125: 650463 | J125: 694747 | K125: 664388 | L125: 733522 | M125: 726913 | N125: 687565 | O125: 811510 | P125: 8077634 | Q125: 673136.17 | R125: 0.32335577
C126: Imbabura | D126: 79033 | E126: 71127 | F126: 53140 | G126: 24659 | H126: 29707 | I126: 45338 | J126: 50659 | K126: 49714 | L126: 55079 | M126: 56796 | N126: 52697 | O126: 60965 | P126: 628914 | Q126: 52409.5 | R126: 0.025176056
C127: Loja | D127: 98126 | E127: 88483 | F127: 62984 | G127: 29931 | H127: 38547 | I127: 53933 | J127: 58881 | K127: 55094 | L127: 66530 | M127: 26754 | N127: 24808 | O127: 29520 | P127: 633591 | Q127: 52799.25 | R127: 0.025363281
C128: Los Ríos | D128: 86535 | E128: 77578 | F128: 62054 | G128: 29958 | H128: 35757 | I128: 64990 | J128: 68117 | K128: 58354 | L128: 64740 | M128: 66593 | N128: 61447 | O128: 72775 | P128: 748898 | Q128: 62408.167 | R128: 0.029979136
C129: Manabí | D129: 155383 | E129: 142001 | F129: 110717 | G129: 53826 | H129: 66855 | I129: 95117 | J129: 109184 | K129: 103405 | L129: 115828 | M129: 123927 | N129: 106898 | O129: 127676 | P129: 1310817 | Q129: 109234.75 | R129: 0.052473315
... C140: Santa Elena | D140: 39674 | E140: 32239 | F140: 24518 | G140: 12711 | H140: 16048 | I140: 24473 | J140: 27091 | K140: 22692 | L140: 27383 | M140: 27403 | N140: 27903 | O140: 31703 | P140: 313838 | Q140: 26153.167 | R140: 0.012563249
B141: Total Oficina / Ventanilla | D141: 3025718 | E141: 2724380 | F141: 2086873 | G141: 1022373 | H141: 1285090 | I141: 1916952 | J141: 2075548 | K141: 2019533 | L141: 2202033 | M141: 2207342 | N141: 2043685 | O141: 2371113 | P141: 24980640 | Q141: 2081720 | R141: 1
B143: Ventanilla Compartida | C143: Azuay | D143: 800 | E143: 758 | F143: 480 | G143: 189 | H143: 276 | I143: 453 | J143: 471 | K143: 468 | L143: 496 | M143: 514 | N143: 465 | O143: 636 | P143: 6006 | Q143: 500.5 | R143: 0.023786139
C144: Bolívar | D144: 259 | E144: 290 | F144: 185 | G144: 156 | H144: 164 | I144: 171 | J144: 212 | K144: 228 | L144: 225 | M144: 207 | N144: 204 | O144: 302 | P144: 2603 | Q144: 216.91667 | R144: 0.010308911
C145: Cañar | D145: 60 | E145: 44 | F145: 39 | G145: 23 | H145: 18 | I145: 38 | J145: 52 | K145: 43 | L145: 53 | M145: 44 | N145: 46 | O145: 58 | P145: 518 | Q145: 43.166667 | R145: 0.0020514851
C146: Carchi | D146: 281 | E146: 297 | F146: 194 | G146: 165 | H146: 155 | I146: 179 | J146: 207 | K146: 224 | L146: 258 | M146: 249 | N146: 195 | O146: 325 | P146: 2729 | Q146: 227.41667 | R146: 0.010807921
C147: Cotopaxi | D147: 476 | E147: 410 | F147: 345 | G147: 224 | H147: 279 | I147: 335 | J147: 340 | K147: 398 | L147: 360 | M147: 370 | N147: 331 | O147: 475 | P147: 4343 | Q147: 361.91667 | R147: 0.0172
C148: Chimborazo | D148: 845 | E148: 817 | F148: 602 | G148: 378 | H148: 503 | I148: 683 | J148: 654 | K148: 655 | L148: 631 | M148: 633 | N148: 582 | O148: 877 | P148: 7860 | Q148: 655 | R148: 0.031128713
C149: El Oro | D149: 1540 | E149: 1443 | F149: 1253 | G149: 651 | H149: 755 | I149: 1058 | J149: 1019 | K149: 1043 | L149: 1172 | M149: 1126 | N149: 1035 | O149: 1508 | P149: 13603 | Q149: 1133.5833 | R149: 0.053873267
C150: Esmeraldas | D150: 256 | E150: 262 | F150: 227 | G150: 167 | H150: 174 | I150: 214 | J150: 207 | K150: 188 | L150: 189 | M150: 195 | N150: 159 | O150: 238 | P150: 2476 | Q150: 206.33333 | R150: 0.0098059406
C151: Guayas | D151: 5841 | E151: 5818 | F151: 4590 | G151: 2418 | H151: 3312 | I151: 3986 | J151: 3939 | K151: 3711 | L151: 3887 | M151: 4335 | N151: 3685 | O151: 5087 | P151: 50609 | Q151: 4217.4167 | R151: 0.20043168
C152: Imbabura | D152: 474 | E152: 453 | F152: 323 | G152: 217 | H152: 206 | I152: 300 | J152: 277 | K152: 342 | L152: 307 | M152: 383 | N152: 323 | O152: 462 | P152: 4067 | Q152: 338.91667 | R152: 0.016106931
C153: Loja | D153: 5417 | E153: 4843 | F153: 3609 | G153: 2291 | H153: 706 | I153: 794 | J153: 900 | K153: 1001 | L153: 1041 | M153: 1006 | N153: 859 | O153: 1444 | P153: 23911 | Q153: 1992.5833 | R153: 0.09469703
C154: Los Ríos | D154: 1122 | E154: 1099 | F154: 998 | G154: 611 | H154: 656 | I154: 828 | J154: 812 | K154: 823 | L154: 884 | M154: 910 | N154: 731 | O154: 1188 | P154: 10662 | Q154: 888.5 | R154: 0.042225743
C155: Manabí | D155: 577 | E155: 595 | F155: 474 | G155: 285 | H155: 318 | I155: 416 | J155: 369 | K155: 428 | L155: 461 | M155: 495 | N155: 411 | O155: 643 | P155: 5472 | Q155: 456 | R155: 0.021671287
... C166: Santa Elena | D166: 758 | E166: 708 | F166: 563 | G166: 337 | H166: 445 | I166: 531 | J166: 505 | K166: 484 | L166: 519 | M166: 586 | N166: 434 | O166: 635 | P166: 6505 | Q166: 542.08333 | R166: 0.025762376
B167: Total Ventanilla Compartida | D167: 32583 | E167: 30852 | F167: 23500 | G167: 13651 | H167: 14264 | I167: 18487 | J167: 18232 | K167: 19093 | L167: 19383 | M167: 20137 | N167: 17451 | O167: 24867 | P167: 252500 | Q167: 21041.667 | R167: 1
B169: Total | D169: 21544651 | E169: 20636370 | F169: 16135331 | G169: 9464804 | H169: 11658889 | I169: 14957371 | J169: 16297665 | K169: 16897460 | L169: 17528920 | M169: 19102888 | N169: 18152210 | O169: 23519450 | P169: 2.0589601e+08 | Q169: 17158001 | R169: 1
...

Sheet SECCIÓN X
B1: SUPERINTENDENCIA DE BANCOS DEL ECUADOR INTENDENCIA NACIONAL DE RIESGOS Y ESTUDIOS DIRECCIÓN DE ESTUDIOS Y GESTIÓN DE LA INFORMACIÓN SUBDIRECCIÓN DE ESTADÍSTICAS Y ESTUDIOS
B3: ESTADÍSTICAS DE RETIROS DE DINERO EN EFECTIVO SOBRE CUENTAS DE AHORRO EN CANALES PROPIOS DE LA ENTIDAD
B4: Enero a Diciembre 2020
B5: Fecha de publicación: Enero 2021
B6: Datos Provisionales
B8: SECCIÓN X: RETIROS DE DINERO POR CANAL POR ORDENANTE
B10: 10.1 Evolución de Transacciones de Retiros de Dinero por Canal por Ordenante
C11: 2 | D11: 3 | E11: 4 | F11: 5 | G11: 6 | H11: 7 | I11: 8 | J11: 9 | K11: 10 | L11: 11 | M11: 12 | N11: 13 | O11: 14 | P11: 15
B12: Canal | C12: Ordenante | D12: Enero | E12: Febrero | F12: Marzo | G12: Abril | H12: Mayo | I12: Junio | J12: Julio | K12: Agosto | L12: Septiembre | M12: Octubre | N12: Noviembre | O12: Diciembre | P12: Total | Q12: Promedio | R12: % Número de retiros
B13: Cajero Automático | C13: Cliente | D13: 11549923 | E13: 11142130 | F13: 8625811 | G13: 4724719 | H13: 5910359 | I13: 7788632 | J13: 8562384 | K13: 8921755 | L13: 9157900 | M13: 10193358 | N13: 9686059 | O13: 13078803 | P13: 1.0934183e+08 | Q13: 9111819.4 | R13: 0.76973522
C14: Usuario | D14: 3453013 | E14: 3332731 | F14: 2731746 | G14: 1860890 | H14: 2141381 | I14: 2381611 | J14: 2483035 | K14: 2597649 | L14: 2650626 | M14: 2816507 | N14: 2716782 | O14: 3543423 | P14: 32709394 | Q14: 2725782.8 | R14: 0.23026478
B15: Total Cajero Automático | D15: 15002936 | E15: 14474861 | F15: 11357557 | G15: 6585609 | H15: 8051740 | I15: 10170243 | J15: 11045419 | K15: 11519404 | L15: 11808526 | M15: 13009865 | N15: 12402841 | O15: 16622226 | P15: 1.4205123e+08 | Q15: 11837602 | R15: 1
B17: Cajero Automático Plus | C17: Cliente | D17: 816357 | E17: 785551 | F17: 617005 | G17: 373636 | H17: 491504 | I17: 604648 | J17: 673551 | K17: 719608 | L17: 775245 | M17: 871637 | N17: 819415 | O17: 1065123 | P17: 8613280 | Q17: 717773.33 | R17: 0.75502335
C18: Usuario | D18: 245223 | E18: 244984 | F18: 206290 | G18: 189514 | H18: 226771 | I18: 206813 | J18: 209665 | K18: 217412 | L18: 227404 | M18: 254581 | N18: 240186 | O18: 325842 | P18: 2794685 | Q18: 232890.42 | R18: 0.24497665
B19: Total Cajero Automático Plus | D19: 1061580 | E19: 1030535 | F19: 823295 | G19: 563150 | H19: 718275 | I19: 811461 | J19: 883216 | K19: 937020 | L19: 1002649 | M19: 1126218 | N19: 1059601 | O19: 1390965 | P19: 11407965 | Q19: 950663.75 | R19: 1
B21: Cajero Automático Móvil | C21: Cliente | D21: 0 | E21: 0 | F21: 0 | G21: 0 | H21: 0 | I21: 0 | J21: 0 | K21: 0 | L21: 0 | M21: 0 | N21: 0 | O21: 0 | P21: 0 | Q21: 0
C22: Usuario | D22: 0 | E22: 0 | F22: 0 | G22: 0 | H22: 0 | I22: 0 | J22: 0 | K22: 0 | L22: 0 | M22: 0 | N22: 0 | O22: 0 | P22: 0 | Q22: 0
B23: Total Cajero Automático Móvil | D23: 0 | E23: 0 | F23: 0 | G23: 0 | H23: 0 | I23: 0 | J23: 0 | K23: 0 | L23: 0 | M23: 0 | N23: 0 | O23: 0 | P23: 0 | Q23: 0
B25: Corresponsal No Bancario | C25: Cliente | D25: 2421834 | E25: 2375742 | F25: 1844106 | G25: 1280021 | H25: 1589520 | I25: 2040228 | J25: 2275250 | K25: 2402410 | L25: 2496329 | M25: 2739326 | N25: 2628632 | O25: 3110279 | P25: 27203677 | Q25: 2266973.1 | R25: 1
C26: Usuario | D26: 0 | E26: 0 | F26: 0 | G26: 0 | H26: 0 | I26: 0 | J26: 0 | K26: 0 | L26: 0 | M26: 0 | N26: 0 | O26: 0 | P26: 0 | Q26: 0 | R26: 0
B27: Total Corresponsal No Bancario | D27: 2421834 | E27: 2375742 | F27: 1844106 | G27: 1280021 | H27: 1589520 | I27: 2040228 | J27: 2275250 | K27: 2402410 | L27: 2496329 | M27: 2739326 | N27: 2628632 | O27: 3110279 | P27: 27203677 | Q27: 2266973.1 | R27: 1
B29: Oficina / Ventanilla | C29: Cliente | D29: 2891439 | E29: 2592335 | F29: 2010300 | G29: 1009731 | H29: 1258775 | I29: 1851622 | J29: 2000707 | K29: 1937331 | L29: 2118872 | M29: 2114702 | N29: 1962304 | O29: 2271753 | P29: 24019871 | Q29: 2001655.9 | R29: 0.96153946
C30: Usuario | D30: 134279 | E30: 132045 | F30: 76573 | G30: 12642 | H30: 26315 | I30: 65330 | J30: 74841 | K30: 82202 | L30: 83161 | M30: 92640 | N30: 81381 | O30: 99360 | P30: 960769 | Q30: 80064.083 | R30: 0.038460544
B31: Total Oficina / Ventanilla | D31: 3025718 | E31: 2724380 | F31: 2086873 | G31: 1022373 | H31: 1285090 | I31: 1916952 | J31: 2075548 | K31: 2019533 | L31: 2202033 | M31: 2207342 | N31: 2043685 | O31: 2371113 | P31: 24980640 | Q31: 2081720 | R31: 1
B33: Ventanilla Compartida | C33: Cliente | D33: 0 | E33: 0 | F33: 0 | G33: 0 | H33: 0 | I33: 0 | J33: 0 | K33: 0 | L33: 0 | M33: 0 | N33: 0 | O33: 0 | P33: 0 | Q33: 0 | R33: 0
C34: Usuario | D34: 32583 | E34: 30852 | F34: 23500 | G34: 13651 | H34: 14264 | I34: 18487 | J34: 18232 | K34: 19093 | L34: 19383 | M34: 20137 | N34: 17451 | O34: 24867 | P34: 252500 | Q34: 21041.667 | R34: 1
B35: Total Ventanilla Compartida | D35: 32583 | E35: 30852 | F35: 23500 | G35: 13651 | H35: 14264 | I35: 18487 | J35: 18232 | K35: 19093 | L35: 19383 | M35: 20137 | N35: 17451 | O35: 24867 | P35: 252500 | Q35: 21041.667 | R35: 1
B37: Total | D37: 21544651 | E37: 20636370 | F37: 16135331 | G37: 9464804 | H37: 11658889 | I37: 14957371 | J37: 16297665 | K37: 16897460 | L37: 17528920 | M37: 19102888 | N37: 18152210 | O37: 23519450 | P37: 205896009 | Q37: 17158001 | R37: 1
B39: 1.2 Evolución del Monto de Retiros de Dinero por Canal por Ordenante
B40: (en dólares)
B41: Canal | C41: Ordenante | D41: Enero | E41: Febrero | F41: Marzo | G41: Abril | H41: Mayo | I41: Junio | J41: Julio | K41: Agosto | L41: Septiembre | M41: Octubre | N41: Noviembre | O41: Diciembre | P41: Total | Q41: Promedio | R41: Promedio
B42: Cajero Automático | C42: Cliente | D42: 1.2216511e+09 | E42: 1.1985541e+09 | F42: 1.0434545e+09 | G42: 6.9459569e+08 | H42: 8.2043502e+08 | I42: 9.4871449e+08 | J42: 1.022858e+09 | K42: 1.0606091e+09 | L42: 1.0664482e+09 | M42: 1.1768222e+09 | N42: 1.093761e+09 | O42: 1660146495 | P42: 1.300805e+10 | Q42: 1.0840042e+09 | R42: 0.84703022
C43: Usuario | D43: 2.3181832e+08 | E43: 2.2756543e+08 | F43: 1.9428557e+08 | G43: 1.4761726e+08 | H43: 1.674308e+08 | I43: 1.7391641e+08 | J43: 1.790178e+08 | K43: 1.8613106e+08 | L43: 1.8911821e+08 | M43: 1.9920811e+08 | N43: 1.8823373e+08 | O43: 2.6485158e+08 | P43: 2.3491943e+09 | Q43: 1.9576619e+08 | R43: 0.15296978
B44: Total Cajero Automático | D44: 1.4534694e+09 | E44: 1.4261195e+09 | F44: 1.2377401e+09 | G44: 8.4221295e+08 | H44: 9.8786582e+08 | I44: 1.1226309e+09 | J44: 1.2018758e+09 | K44: 1.2467402e+09 | L44: 1.2555665e+09 | M44: 1.3760303e+09 | N44: 1.2819948e+09 | O44: 1.9249981e+09 | P44: 1.5357244e+10 | Q44: 1.2797704e+09 | R44: 1
B46: Cajero Automático Plus | C46: Cliente | D46: 80763146 | E46: 79557184 | F46: 70493390 | G46: 52820759 | H46: 64898487 | I46: 70146958 | J46: 75293608 | K46: 79054526 | L46: 84449588 | M46: 95486762 | N46: 87096014 | O46: 1.2963548e+08 | P46: 9.696959e+08 | Q46: 80807992 | R46: 0.84880646
C47: Usuario | D47: 14237550 | E47: 14464495 | F47: 12886158 | G47: 13262235 | H47: 15429515 | I47: 13024245 | J47: 12851965 | K47: 13085080 | L47: 13614649 | M47: 15209284 | N47: 14094559 | O47: 20567217 | P47: 172726952 | Q47: 14393913 | R47: 0.15119354
B48: Total Cajero Automático Plus | D48: 95000696 | E48: 94021679 | F48: 83379548 | G48: 66082994 | H48: 80328002 | I48: 83171203 | J48: 88145574 | K48: 92139606 | L48: 98064237 | M48: 1.1069605e+08 | N48: 1.0119057e+08 | O48: 1.502027e+08 | P48: 1.1424229e+09 | Q48: 95201904 | R48: 1
B50: Cajero Automático Móvil | C50: Cliente | D50: 0 | E50: 0 | F50: 0 | G50: 0 | H50: 0 | I50: 0 | J50: 0 | K50: 0 | L50: 0 | M50: 0 | N50: 0 | O50: 0 | P50: 0 | Q50: 0
C51: Usuario | D51: 0 | E51: 0 | F51: 0 | G51: 0 | H51: 0 | I51: 0 | J51: 0 | K51: 0 | L51: 0 | M51: 0 | N51: 0 | O51: 0 | P51: 0 | Q51: 0
B52: Total Cajero Automático Móvil | D52: 0 | E52: 0 | F52: 0 | G52: 0 | H52: 0 | I52: 0 | J52: 0 | K52: 0 | L52: 0 | M52: 0 | N52: 0 | O52: 0 | P52: 0 | Q52: 0
B54: Corresponsal No Bancario | C54: Cliente | D54: 1.5992788e+08 | E54: 1.5999948e+08 | F54: 1.3218417e+08 | G54: 99828259 | H54: 1.299024e+08 | I54: 1.5647305e+08 | J54: 1.7358102e+08 | K54: 1.8170907e+08 | L54: 1.8711822e+08 | M54: 2.0620502e+08 | N54: 1.9293653e+08 | O54: 2.5373734e+08 | P54: 2.0336024e+09 | Q54: 1.6946687e+08 | R54: 1
C55: Usuario | D55: 0 | E55: 0 | F55: 0 | G55: 0 | H55: 0 | I55: 0 | J55: 0 | K55: 0 | L55: 0 | M55: 0 | N55: 0 | O55: 0 | P55: 0 | Q55: 0 | R55: 0
B56: Total Corresponsal No Bancario | D56: 1.5992788e+08 | E56: 1.5999948e+08 | F56: 1.3218417e+08 | G56: 99828259 | H56: 1.299024e+08 | I56: 1.5647305e+08 | J56: 1.7358102e+08 | K56: 1.8170907e+08 | L56: 1.8711822e+08 | M56: 2.0620502e+08 | N56: 1.9293653e+08 | O56: 2.5373734e+08 | P56: 2.0336024e+09 | Q56: 1.6946687e+08 | R56: 1
B58: Oficina / Ventanilla | C58: Cliente | D58: 1.7764531e+09 | E58: 1.5660464e+09 | F58: 1.2877641e+09 | G58: 7.42889e+08 | H58: 8.3392046e+08 | I58: 1.1612446e+09 | J58: 1.2436474e+09 | K58: 1.1678401e+09 | L58: 1.3275843e+09 | M58: 1.365088e+09 | N58: 1.2468798e+09 | O58: 1.462392e+09 | P58: 1.5181749e+10 | Q58: 1.2651458e+09 | R58: 0.98085211
C59: Usuario | D59: 37277424 | E59: 35709370 | F59: 22985299 | G59: 5615120.1 | H59: 9743524.9 | I59: 24154218 | J59: 26205201 | K59: 25966200 | L59: 25383993 | M59: 27444599 | N59: 23735788 | O59: 32152700 | P59: 2.9637344e+08 | Q59: 24697786 | R59: 0.019147893
B60: Total Oficina / Ventanilla | D60: 1.8137305e+09 | E60: 1.6017557e+09 | F60: 1.3107494e+09 | G60: 7.4850412e+08 | H60: 8.4366399e+08 | I60: 1.1853988e+09 | J60: 1.2698526e+09 | K60: 1.1938063e+09 | L60: 1.3529683e+09 | M60: 1.3925326e+09 | N60: 1.2706155e+09 | O60: 1.4945447e+09 | P60: 1.5478123e+10 | Q60: 1.2898436e+09 | R60: 1
B62: Ventanilla Compartida | C62: Cliente | D62: 0 | E62: 0 | F62: 0 | G62: 0 | H62: 0 | I62: 0 | J62: 0 | K62: 0 | L62: 0 | M62: 0 | N62: 0 | O62: 0 | P62: 0 | Q62: 0 | R62: 0
C63: Usuario | D63: 18937416 | E63: 18662824 | F63: 14210551 | G63: 8476438.3 | H63: 8387358.9 | I63: 10156050 | J63: 10278070 | K63: 10221517 | L63: 11490424 | M63: 11526369 | N63: 9899970.6 | O63: 15496688 | P63: 1.4774368e+08 | Q63: 12311973 | R63: 1
B64: Total Ventanilla Compartida | D64: 18937416 | E64: 18662824 | F64: 14210551 | G64: 8476438.3 | H64: 8387358.9 | I64: 10156050 | J64: 10278070 | K64: 10221517 | L64: 11490424 | M64: 11526369 | N64: 9899970.6 | O64: 15496688 | P64: 1.4774368e+08 | Q64: 12311973 | R64: 1
B66: Total | D66: 3.5410659e+09 | E66: 3.3005592e+09 | F66: 2.7782638e+09 | G66: 1.7651048e+09 | H66: 2.0501476e+09 | I66: 2.55783e+09 | J66: 2.7437331e+09 | K66: 2.7246167e+09 | L66: 2.9052076e+09 | M66: 3.0969903e+09 | N66: 2.8566374e+09 | O66: 3.8389795e+09 | P66: 3.4159136e+10 | Q66: 2.8465947e+09 | R66: 1
B68: 1.3. Evolución del Monto Promedio de Retiros de Dinero por Canal por Ordenante
B69: (en dólares)
B70: Canal | C70: Provincia | D70: Enero | E70: Febrero | F70: Marzo | G70: Abril | H70: Mayo | I70: Junio | J70: Julio | K70: Agosto | L70: Septiembre | M70: Octubre | N70: Noviembre | O70: Diciembre | P70: Promedio
B71: Cajero Automático | C71: Cliente | D71: 105.77136 | E71: 107.56956 | F71: 120.96886 | G71: 147.01312 | H71: 138.81306 | I71: 121.80759 | J71: 119.45949 | K71: 118.87898 | L71: 116.45118 | M71: 115.4499 | N71: 112.92116 | O71: 126.93413 | P71: 121.0032
C72: Usuario | D72: 67.135084 | E72: 68.281968 | F72: 71.121389 | G72: 79.326161 | H72: 78.188234 | I72: 73.024692 | J72: 72.096366 | K72: 71.653661 | L72: 71.34851 | M72: 70.728782 | N72: 69.285548 | O72: 74.744556 | P72: 72.244579
B73: Promedio Cajero Automático | D73: 86.453224 | E73: 87.925766 | F73: 96.045123 | G73: 113.16964 | H73: 108.50065 | I73: 97.416141 | J73: 95.777926 | K73: 95.266319 | L73: 93.899844 | M73: 93.089341 | N73: 91.103355 | O73: 100.83934 | P73: 96.623889
B75: Cajero Automático Plus | C75: Cliente | D75: 98.931161 | E75: 101.27564 | F75: 114.25092 | G75: 141.36957 | H75: 132.04061 | I75: 116.01288 | J75: 111.78605 | K75: 109.85776 | L75: 108.93277 | M75: 109.54877 | N75: 106.29048 | O75: 121.7094 | P75: 114.33384
C76: Usuario | D76: 58.059603 | E76: 59.042611 | F76: 62.466227 | G76: 69.980239 | H76: 68.040071 | I76: 62.975949 | J76: 61.297618 | K76: 60.185638 | L76: 59.869875 | M76: 59.742416 | N76: 58.681851 | O76: 63.120215 | P76: 61.955193
B77: Promedio Cajero Automático Plus | D77: 78.495382 | E77: 80.159128 | F77: 88.358574 | G77: 105.6749 | H77: 100.04034 | I77: 89.494416 | J77: 86.541836 | K77: 85.021701 | L77: 84.401324 | M77: 84.645593 | N77: 82.486165 | O77: 92.414807 | P77: 88.144514
B79: Cajero Automático Móvil | C79: Cliente
C80: Usuario
B81: Promedio Cajero Automático Móvil
B83: Corresponsal No Bancario | C83: Cliente | D83: 66.035854 | E83: 67.347159 | F83: 71.67927 | G83: 77.989548 | H83: 81.724293 | I83: 76.693903 | J83: 76.290965 | K83: 75.636163 | L83: 74.957354 | M83: 75.275823 | N83: 73.398077 | O83: 81.580252 | P83: 74.884055
C84: Usuario
B85: Promedio Corresponsal No Bancario | D85: 66.035854 | E85: 67.347159 | F85: 71.67927 | G85: 77.989548 | H85: 81.724293 | I85: 76.693903 | J85: 76.290965 | K85: 75.636163 | L85: 74.957354 | M85: 75.275823 | N85: 73.398077 | O85: 81.580252 | P85: 74.884055
B87: Oficina / Ventanilla | C87: Cliente | D87: 614.38373 | E87: 604.10647 | F87: 640.58306 | G87: 735.72961 | H87: 662.48572 | I87: 627.14993 | J87: 621.60397 | K87: 602.80877 | L87: 626.55239 | M87: 645.52264 | N87: 635.41621 | O87: 643.72843 | P87: 638.33924
C88: Usuario | D88: 277.61172 | E88: 270.43334 | F88: 300.17498 | G88: 444.16391 | H88: 370.26505 | I88: 369.72628 | J88: 350.14499 | K88: 315.88283 | L88: 305.23915 | M88: 296.24999 | N88: 291.66253 | O88: 323.59803 | P88: 326.26273
B89: Promedio Oficina / Ventanilla | D89: 445.99772 | E89: 437.2699 | F89: 470.37902 | G89: 589.94676 | H89: 516.37539 | I89: 498.43811 | J89: 485.87448 | K89: 459.3458 | L89: 465.89577 | M89: 470.88632 | N89: 463.53937 | O89: 483.66323 | P89: 482.30099
B91: Ventanilla Compartida | C91: Cliente
C92: Usuario | D92: 581.20541 | E92: 604.91455 | F92: 604.70431 | G92: 620.939 | H92: 588.0089 | I92: 549.36169 | J92: 563.73796 | K92: 535.35417 | L92: 592.80936 | M92: 572.39753 | N92: 567.30105 | O92: 623.18287 | P92: 583.65973
B93: Promedio Ventanilla Compartida | D93: 581.20541 | E93: 604.91455 | F93: 604.70431 | G93: 620.939 | H93: 588.0089 | I93: 549.36169 | J93: 563.73796 | K93: 535.35417 | L93: 592.80936 | M93: 572.39753 | N93: 567.30105 | O93: 623.18287 | P93: 583.65973
B95: Promedio | D95: 164.3594 | E95: 159.93894 | F95: 172.18511 | G95: 186.49142 | H95: 175.84416 | I95: 171.008 | J95: 168.3513 | K95: 161.24416 | L95: 165.73797 | M95: 162.12158 | N95: 157.37133 | O95: 163.22573 | P95: 165.9048

Sheet SECCIÓN XI Y XII
B1: SUPERINTENDENCIA DE BANCOS DEL ECUADOR INTENDENCIA NACIONAL DE RIESGOS Y ESTUDIOS DIRECCIÓN DE ESTUDIOS Y GESTIÓN DE LA INFORMACIÓN SUBDIRECCIÓN DE ESTADÍSTICAS Y ESTUDIOS
B3: ESTADÍSTICAS DE RETIROS DE DINERO EN EFECTIVO SOBRE CUENTAS DE AHORRO EN CANALES PROPIOS DE LA ENTIDAD
B4: =+Contenido!B4 -> Enero a Diciembre 2020
B5: =+'SECCIÓN I'!B5 -> Fecha de publicación: Enero 2021
B6: Datos Provisionales
B8: SECCIÓN XI: CONSIDERANDOS
B10: Las estadísticas presentadas se basan en la información reportada por las entidades financieras controladas por la Superintendencia de Bancos, a través del Formulario No. 1 de la Circular No. SB-DNEI-2016-0002-C: “Detalle de Retiros de Dinero en Canales Propios”. El presente informe contiene únicamente los retiros de dinero en efectivo efectuados sobre una cuenta de ahorro en la cual el cliente o usuario posee saldo disponible y que han sido realizados a través de los diferentes canales propios que la entidad financiera pone a disposición. Quedan excluidos de este informe el pago y depósito de cheques, retiros realizados sobre una póliza de acumulación, inversión o depósito a plazo fijo que hayan vencido, avances de efectivo, retiros de dinero en canales ubicados geográficamente en el exterior y retiros de dinero por cierres de cuentas.
B12: SECCIÓN XII: CONTACTOS
B14: Contacto Teléfonos: 02 2996100, 02 2997600, ext. 1919 Email: dnei_sas@superbancos.gob.ec
